Workbook
Name Excel_BuiltIn__FilterDatabase: 'Декретчицы'!$B$4:$N$5
Name Excel_BuiltIn__FilterDatabase: 'Инвалиды'!$A$4:$H$4
Name Excel_BuiltIn__FilterDatabase: 'Нетрудоспособность '!$A$2:$L$2
Name Excel_BuiltIn__FilterDatabase: 'Список сотрудников'!$A$2:$AO$2
Name Excel_BuiltIn__FilterDatabase: 'Список уволенных'!$A$2:$W$2
Name Excel_BuiltIn__FilterDatabase: 'Справочник'!$A$1:$E$143
Name Excel_BuiltIn__FilterDatabase: 'Срочники'!$A$4:$I$4
Name Excel_BuiltIn__FilterDatabase: 'Текучесть'!$A$2:$AR$10
Name Вид_занятости: 'Вып_списки'!$H$2:$H$3
Name Вид_обучения: 'Вып_списки'!$M$2:$M$3
Name Город: 'Вып_списки'!$F$2:$F$12
Name Категория_должности: 'Вып_списки'!$E$2:$E$7
Name Компания: 'Вып_списки'!$B$2:$B$8
Name Месяц: 'Вып_списки'!$A$2:$A$13
Name Направление_обучения: 'Вып_списки'!$N$2:$N$4
Name Приоритет_закрытия: 'Вып_списки'!$P$2:$P$4
Name Причина_нетрудоспособности: 'Вып_списки'!$L$2:$L$8
Name Причины_изменения: 'Вып_списки'!$J$2:$J$11
Name Причины_невключения: 'Вып_списки'!$I$2:$I$10
Name Продуктивный: 'Вып_списки'!$O$2:$O$3
Name Рабочий_день: 'Вып_списки'!$D$2:$D$4
Name Расшифровка_статей_увольнения: 'Расшифровка статей увольнения'!$B$2:$B$36
Name Реальные_причины_увольнения: 'Реальные причины увольнения'!$A$2:$A$29
Name Статьи_увольнения: 'Расшифровка статей увольнения'!$A$2:$A$36
Name Тип_договора: 'Вып_списки'!$C$2:$C$3
Name Функция: 'Вып_списки'!$G$2:$G$6
Name ЦФО: 'Вып_списки'!$R$2:$R$24

Sheet Инструкция
A1: Инструкция по заполнению отчета
A4: Отчет заполняется на ежемесячной основе в 1 рабочий день месяца, следующего за отчетным
A5: Все листы, кроме "Список сотрудников" заполняются нарастающим итогом с начала года
A6: Лист "Список сотрудников" заполняются на последний календарный день месяца
A8: Лист "Список сотрудников" | B8: Заполняется вручную
A9: Ежемесячно отражается численность работающих сотрудников (списочная) на последнюю дату месяца, включая своместителей, декретчиц, прогульщиков и т.д.
A10: за ИСКЮЧЕНИЕМ (не включаем):
A11: − сотрудники, находящиеся на декретном больничном листе
A12: − сотрудники, находящихся в отпуске по уходу за ребенком (до 1,5 или до 3 лет)
A13: − сотрудники с длительным прогулом или с длительным невыясненным отсутствием
A14: − сотрудники, находящиеся в длительном (3 месяца и более) отпуске без сохранения заработной платы
A15: − внутренние совместители (по той должности, которая является для них работой по совместительству)
A16: Сотрудники, уволенные в последний календарный день месяца включаются на оба листа: и в численность, и в уволенные
A17: Лист "Список сотрудников" в шаблоне | B17: Комментарии по данным для отчета
A18: Таб.№ | B18: табельный номер сотрудника
A19: ФИО | B19: ФИО сотрудника
A20: Дата начала работы в ГК (при переводе из одного юрлица в другое) | B20: первичная дата приема на работу (при переводе внутри ГК)
A21: Дата начала работы в юрлице | B21: дата начала работы в юрлице
A22: Дата рождения | B22: дата рождения
A23: Подразделение | B23: Наименование подразделения
A24: Должность | B24: Наименование должности
A25: Пол сотрудника | B25: Пол сотрудника
A26: Категория персонала | B26: Категория персонала: см.лист "Справочник"
A27: Город, фактическое место работы | B27: Наименование места работы сотрудника (название города).
A28: полный \ неполный рабочий день | B28: полный – для сотрудников, работающих полный рабочий день Не полный – для сотрудников, работающих не полный рабочий день
... A30: Основное место работы/Совместительство | B30: Вид работы основной или совместитель
A31: Включаем \ не включаем в отчет
A32: Причина невключения сотрудника в отчет | B32: см.список исключений выше
A33: Функция | B33: Функция к которой относиться сотрудник
A34: Месяц | B34: месяц, за который предоставляется отчет
A35: Изменение поля "включаем/не включаем"
A36: Причина изменения "включаем/не включаем" | B36: см.список исключений выше (если в течении отчетного месяца изменился статус сотрудника)
A37: Юридическое лицо | B37: Юридическое лицо
A39: Лист "Список уволенных" | B39: Заполняется вручную
A40: Лист "Список уволенных" в шаблоне | B40: Комментарии по данным для отчета
A41: Таб. № | B41: табельный номер сотрудника
A42: ФИО | B42: ФИО сотрудника
A43: Подразделение | B43: Наименование должности
A44: Должность | B44: Вид работы основной или совместитель
A45: Функция | B45: не заполняем
A46: Основное место работы/Совместительство | B46: Вид работы основной или совместитель
A47: Дата увольнения | B47: Дата увольнения
A48: Категории персонала | B48: Категория персонала: см.лист "Справочник"
... A64: Лист "Декретчицы" | B64: Заполняется вручную
A66: Цветовой код:
A67: период перед окончанием декрета (перед достижением ребенка указанного возраста (1,5; 3 года))
B68: меньше, чем 6 месяцев
B69: меньше, чем 3 месяца
A72: Лист "Текучесть" | B72: Заполняется вручную
A73: Ежемесячно отражается численность работающих сотрудников (списочная) на последнюю дату месяца (список сотрудников (включаем)) по функциям
A74: за ИСКЮЧЕНИЕМ (не включаем):
A75: − сотрудники, находящиеся на декретном больничном листе
A76: − сотрудники, находящихся в отпуске по уходу за ребенком (до 1,5 или до 3 лет)
A77: − сотрудники с длительным прогулом или с длительным невыясненным отсутствием
A78: − сотрудники, находящиеся в длительном (3 месяца и более) отпуске без сохранения заработной платы
A79: − внутренние совместители (по той должности, которая является для них работой по совместительству)
A81: Ежемесячно отражается численностьуволенных в течении соответствующего месяца по причинам "включаем" по функциям
A83: Информацию можно получить на листах "Сводный по юрлицам" и "Сводный по увольнениям"
A85: Лист "Отпуска" | B85: Заполняется вручную
A87: Цветовой код:
A88: задолженность по ежегодным отпускам
B89: свыше 35 дней
B90: свыше 42 дней
A92: В список включаем всех сотрудников, у кого на начало месяца количество дней неотгуляррного отпуска свыше 28.
A93: В последующие месяца сотрудников не удаляем, новых сотрудников добавляем ниже. В комментариях указываем предполагаемую дату снижения.
A95: Лист "Вакансии" | B95: Заполняется вручную
A97: Цветовой код:
A98: закрытие вакансий
B99: свыше 10 рабочих дней в работе
B100: свыше 15 рабочих дней в работе
A101: В список включаем все вакансии, имеющиеся в разработке. Закрытые вакансии не удаляем.
A105: Лист "Нетрудоспособность" | B105: Заполняется вручную
A107: В список включаем все листы нетрудоспособности нарастующим итогом, кроме совместителей
A109: Лист "Прогульщики" | B109: Заполняется вручную
A111: В список включаем всех прогульщиков нарастующим итогом
A113: Лист "Обучение" | B113: Заполняется вручную
A115: В список включаем всех сотрудников, прошедших обучение, нарастующим итогом
A116: Вид обучения: внутреннее или внешнее
A117: Тип обучения: профессиональное или личностное
A119: Лист "Сводный по юрлицам" | B119: Формируется автоматически, частично заполняем вручную
A120: Обновляем сводную таблицу и напротив наименования организации заполняем данные по текущей численности. Если есть расхождение по численности - пишем комментарии.
A121: На конец прошлого месяца
A122: Вновь пришедшие
A123: Уволившиеся
A124: Стал "включаем в численность"
A125: Стал "исключаем из численности"
A126: Проверка
A127: Комментарии к расхождениям
A130: Лист "Сводный по увольнениям" | B130: Формируется автоматически
A131: Обновляем сводную таблицу. Полученное количество увольнений по функциям вносим на лист текучесть
A134: Лист "Сводный по исключениям" | B134: Формируется автоматически
A135: Обновляем сводную таблицу. Кол-во декретчиц должно совпадать с листом Декретчицы

Sheet Справочник
A1: Подразделение | B1: Должность | C1: Категория персонала | D1: Продуктивность | E1: Функция | F1: Город | G1: Уровень управления | H1: ЦФО
A2: Административно-хозяйственный отдел | B2: Уборщик помещений | C2: рабочий | D2: Не продуктивный | E2: Вспомогательные | F2: Ростов-на-Дону | G2: 7ПП | H2: ЦФО Служба логистики (2 ур)
A3: Администрация | B3: Директор | C3: директор | D3: Не продуктивный | E3: Вспомогательные | F3: Ростов-на-Дону | G3: 2БП | H3: ЦФО Амурская легенда (1 ур)
A4: Азовский СЦ | B4: Кассир-приемщик | C4: служащий | D4: Продуктивный | E4: Сервис | F4: Азов | G4: 7БП | H4: ЦФО МГС (1 ур)
A5: Азовский СЦ | B5: Начальник сервисного центра | C5: руководитель отдела | D5: Продуктивный | E5: Сервис | F5: Азов | G5: 5БП | H5: ЦФО МГС (1 ур)
A6: Аксайский СЦ | B6: Начальник сервисного центра | C6: руководитель отдела | D6: Продуктивный | E6: Сервис | F6: Аксай | G6: 5БП | H6: ЦФО МГС (1 ур)
A7: Аксайский СЦ | B7: Техник | C7: рабочий | D7: Продуктивный | E7: Сервис | F7: Аксай | G7: 7БП | H7: ЦФО МГС (1 ур)
A8: Батайский СЦ | B8: Кассир-приемщик | C8: служащий | D8: Продуктивный | E8: Сервис | F8: Батайск | G8: 7БП | H8: ЦФО МГС (1 ур)
A9: Батайский СЦ | B9: Начальник сервисного центра | C9: руководитель отдела | D9: Продуктивный | E9: Сервис | F9: Батайск | G9: 5БП | H9: ЦФО МГС (1 ур)
A10: Бухгалтерия | B10: Бухгалтер по расчету заработной платы | C10: специалист | D10: Не продуктивный | E10: Вспомогательные | F10: Ростов-на-Дону | G10: 6ПП | H10: ЦФО Финслужба (2 ур)
A11: Бухгалтерия | B11: Заместитель главного бухгалтера | C11: специалист | D11: Не продуктивный | E11: Вспомогательные | F11: Ростов-на-Дону | G11: 5ПП | H11: ЦФО Финслужба (2 ур)
A12: Бухгалтерия | B12: Помощник бухгалтера | C12: служащий | D12: Не продуктивный | E12: Вспомогательные | F12: Ростов-на-Дону | G12: 6ПП | H12: ЦФО Финслужба (2 ур)
... A170: Руководство | B170: Председатель совета директоров | C170: директор | D170: Не продуктивный | E170: Вспомогательные | F170: Ростов-на-Дону | G170: 1БП | H170: ЦФО Руководство (2 ур)
A171: Руководство | B171: Сборщик | C171: рабочий | D171: Продуктивный | E171: Производство | F171: Ростов-на-Дону | G171: 7БП
A172: Руководство | B172: Финансовый директор | C172: директор направления | D172: Не продуктивный | E172: Вспомогательные | F172: Ростов-на-Дону | G172: 2ПП | H172: ЦФО Руководство (2 ур)
A173: Руководство (основное) | B173: Директор | C173: директор | D173: Не продуктивный | E173: Вспомогательные | F173: Ростов-на-Дону | G173: 2БП | H173: ЦФО МГС (1 ур)
A174: Руководство конструкторского бюро | B174: Директор по научной работе | C174: директор направления | D174: Не продуктивный | E174: Вспомогательные | F174: Ростов-на-Дону | G174: 1ПП | H174: ЦФО Руководство (2 ур)
A175: Руководство конструкторского бюро | B175: Заместитель главного бухгалтера | C175: специалист | D175: Не продуктивный | E175: Вспомогательные | F175: Ростов-на-Дону | G175: 5ПП | H175: ЦФО Финслужба (2 ур)
A176: Руководство конструкторского бюро | B176: Технический директор | C176: директор направления | D176: Не продуктивный | E176: Вспомогательные | F176: Ростов-на-Дону | G176: 3ПП | H176: ЦФО Производство БМИ (1 ур)
A177: Сальский СЦ | B177: Кассир-приемщик | C177: служащий | D177: Продуктивный | E177: Сервис | F177: Сальск | G177: 7БП | H177: ЦФО МГС (1 ур)
A178: Сальский СЦ | B178: Начальник сервисного центра | C178: руководитель отдела | D178: Продуктивный | E178: Сервис | F178: Сальск | G178: 5БП | H178: ЦФО МГС (1 ур)
A179: Сальский СЦ | B179: Техник | C179: рабочий | D179: Продуктивный | E179: Сервис | F179: Сальск | G179: 7БП | H179: ЦФО МГС (1 ур)
A180: Сборочный участок №1 | B180: Инженер-электроник | C180: специалист | D180: Продуктивный | E180: Производство | F180: Ростов-на-Дону | G180: 6БП | H180: ЦФО Производство №1 (1 ур)
A181: Сборочный участок №1 | B181: Мастер участка | C181: руководитель отдела | D181: Не продуктивный | E181: Производство | F181: Ростов-на-Дону | G181: 5ПП | H181: ЦФО Производство №1 (1 ур)
A182: Сборочный участок №1 | B182: Регулировщик радиоэлектронной аппаратуры и приборов | C182: рабочий | D182: Продуктивный | E182: Производство | F182: Ростов-на-Дону | G182: 7БП | H182: ЦФО Производство №1 (1 ур)
A183: Сборочный участок №1 | B183: Слесарь-сборщик радиоэлектронной аппаратуры | C183: рабочий | D183: Продуктивный | E183: Производство | F183: Ростов-на-Дону | G183: 7БП | H183: ЦФО Производство №1 (1 ур)
... A313: Участок сборки счетчиков | B313: Монтажник | C313: рабочий | D313: Продуктивный | E313: Производство | F313: Ростов-на-Дону | G313: 7БП | H313: ЦФО Производство №2 (1 ур)
A314: Отдел материально-технического обеспечения | B314: Старший оператор 1С

Sheet Вып_списки
A1: Месяц | B1: Компания | C1: Тип договора | D1: Рабочий день | E1: категория персонала | F1: Город, фактическое место работы | G1: Функции | H1: Вид занятости | I1: причины невключения | J1: причины изменения | L1: причина нетрудоспособности | M1: Вид обучения | N1: Направление обучения | O1: Продуктивность | P1: Приоритет закрытия | Q1: Вид приема | R1: ЦФО
A2: Январь | B2: АЛМАЗ | C2: постоянный | D2: полный | E2: директор | F2: Ростов-на-Дону | G2: Продажи | H2: Основное место | I2: отпуск по беременности и родам (Декрет) | J2: уход в отпуск по беременности и родам | K2: стал исключаем | L2: заболевание | M2: Внутренее | N2: Профессиональное | O2: Продуктивный | P2: Первоочередная | Q2: Перевод | R2: ЦФО Амурская легенда (1 ур)
A3: Февраль | B3: Метрогазсервис | C3: временный | D3: неполный | E3: директор направления | F3: Азов | G3: Производство | H3: Совместительство | I3: отпуск по уходу за ребенком до 1,5 и 3-х лет | J3: уход в отпуск по уходу за ребенком до 1,5 и 3-х лет | K3: стал исключаем | L3: уход за больным членом семьи | M3: Внешнее | N3: Личностное | O3: Не продуктивный | P3: Текущая | Q3: Подбор | R3: ЦФО Главный метролог (1 ур)
A4: Март | B4: НПО Турбулентность-Дон | D4: сокращенный | E4: руководитель отдела | F4: Аксай | G4: Вспомогательные | I4: длительный прогул | J4: начало длительного прогула | K4: стал исключаем | L4: травма | N4: Разрешительные документы | P4: Резерв | Q4: Приведи друга | R4: ЦФО Директор НПО (2 ур)
A5: Апрель | B5: ИП Корниенко М.С. | E5: специалист | F5: Батайск | G5: Сервис | I5: длительное отсутствие по невыясненным причинам | J5: начало длительного отсутствие по невыясненным причинам | K5: стал исключаем | L5: отпуск по беременности и родам | R5: ЦФО КБ (2 ур)
A6: Май | B6: Амурская легенда | E6: служащий | F6: Волгодонск | G6: Логистика | I6: длительный отпуск без сохранения з/п | J6: уход в отпуск без сохранения з/п | K6: стал исключаем | L6: протезирование в стационаре | R6: ЦФО Ком.служба (2 ур)
A7: Июнь | B7: Милака | E7: рабочий | F7: Каменск-Шахтинск | I7: длительный больничный | J7: выход из отпуска по беременности и родам | K7: стал включаем | L7: долечивание в санатории | R7: ЦФО МГС (1 ур)
A8: Июль | F8: Новочеркасск | I8: внутренний соместитель | J8: выход из отпуска по уходу за ребенком до 1,5 и 3-х лет | K8: стал включаем | L8: иное состояние | R8: ЦФО Милака (1 ур)
A9: Август | F9: Таганрог | I9: внешний совместитель | J9: конец длительного прогула | K9: стал включаем | R9: ЦФО Производство №1 (1 ур)
A10: Сентябрь | F10: Шахты | I10: мобилизация | J10: конец длительного отсутствие по невыясненным причинам | K10: стал включаем | R10: ЦФО Производство №2 (1 ур)
A11: Октябрь | F11: Сальск | J11: выход из отпуска без сохранения з/п | K11: стал включаем | R11: ЦФО Производство БМИ (1 ур)
A12: Ноябрь | F12: Миллерово | R12: ЦФО Руководство (2 ур)
A13: Декабрь | R13: ЦФО Сервисная служба (1+2 ур)
R14: ЦФО Служба безопасности (2 ур)
R15: ЦФО Служба технического директора (2 ур)
R16: ЦФО Служба развития (2 ур)
R17: ЦФО Служба логистики (2 ур)
R18: ЦФО Экспериментальный цех (2 ур)
R19: ЦФО Служба автоматизации (2 ур)

Sheet Список сотрудников
A1: Выгрузка из 1С | B1: Выгрузка из 1С | C1: Заполняется вручную | D1: Выгрузка из 1С | E1: Выгрузка из 1С | F1: Выгрузка из 1С | G1: Выгрузка из 1С | H1: Заполняется автоматически | I1: Заполняется автоматически | J1: Заполняется автоматически | K1: Заполняем вручную, настроен выпадающий список | L1: Заполняется автоматически | M1: Заполняется автоматически | N1: Выгрузка из 1С | O1: Выгрузка из 1С | P1: Выгрузка из 1С | Q1: Заполняется автоматически | R1: Заполняем вручную, настроен выпадающий список | S1: Заполняется автоматически | T1: Заполняем вручную, настроен выпадающий список | U1: Заполняется автоматически | V1: Заполняем вручную, настроен выпадающий список | W1: Заполняется автоматически | AB1: стаж работы в компании | AJ1: возраст
A2: Таб.№ | B2: ФИО | C2: Дата начала работы в ГК (при переводе из одного юрлица в другое) | D2: Дата начала работы в юрлице | E2: Дата рождения | F2: Подразделение | G2: Должность | H2: Пол сотрудника | I2: Категория персонала | J2: Уровень управления | K2: ЦФО | L2: Продуктивность | M2: Город, фактическое место работы | N2: полный \ неполный рабочий день | O2: Ставка | P2: Основное место работы/Совместительство | Q2: Включаем \ не включаем в отчет | R2: Причина невключения сотрудника в отчет | S2: Функция | T2: Месяц | U2: Изменение поля "включаем/не включаем" | V2: Юридическое лицо | W2: Сегодня | AB2: лет | AC2: месяцев | AD2: дней | AJ2: лет | AK2: месяцев | AL2: дней
A3: 00506 | B3: Мегрелишвили Михаил Эмзарович | D3: 29.01.2026 | E3: 27.05.1984 | F3: Руководство (основное) | G3: Директор | H3: =IF(ISBLANK(B3),"-",IF(ISERROR(FIND("вич",B3,1)),"ж","м")) -> м | I3: #REF! | J3: #REF! | K3: ЦФО Производство №2 (1 ур) | O3: 3/10 | P3: Внешнее совместительство | Q3: =IF(R3="","включаем","не включаем") -> не включаем | R3: внешний совместитель | T3: Май | V3: АЛМАЗ ООО | W3: 46173
A4: 00436 | B4: Павлова Лариса Викторовна | D4: 01.04.2024 | E4: 20.04.1976 | F4: Руководство | G4: Главный бухгалтер | H4: =IF(ISBLANK(B4),"-",IF(ISERROR(FIND("вич",B4,1)),"ж","м")) -> ж | I4: #REF! | J4: #REF! | K4: ЦФО Производство №2 (1 ур) | O4: 1 | P4: Основное место работы | Q4: =IF(R4="","включаем","не включаем") -> включаем | T4: Май | V4: АЛМАЗ ООО | W4: 46173
A5: 00238 | B5: Лазарева Марина Владимировна | D5: 02.08.2021 | E5: 13.10.1983 | F5: Руководство | G5: Бухгалтер | H5: =IF(ISBLANK(B5),"-",IF(ISERROR(FIND("вич",B5,1)),"ж","м")) -> ж | I5: #REF! | J5: #REF! | K5: ЦФО Производство №2 (1 ур) | O5: 1 | P5: Внешнее совместительство | Q5: =IF(R5="","включаем","не включаем") -> не включаем | R5: внешний совместитель | T5: Май | V5: АЛМАЗ ООО | W5: 46173
A6: 00407 | B6: Полякова Кристина Валентиновна | D6: 17.07.2023 | E6: 05.09.1983 | F6: Производство №2 | G6: Инженер по подготовке производства | H6: =IF(ISBLANK(B6),"-",IF(ISERROR(FIND("вич",B6,1)),"ж","м")) -> ж | I6: #REF! | J6: #REF! | K6: ЦФО Производство №2 (1 ур) | O6: 1 | P6: Основное место работы | Q6: =IF(R6="","включаем","не включаем") -> включаем | T6: Май | V6: АЛМАЗ ООО | W6: 46173
A7: 00495 | B7: Цимбалова Любовь Витальевна | D7: 22.07.2025 | E7: 10.12.1995 | F7: Производство №2 | G7: Диспетчер 1С ERP | H7: =IF(ISBLANK(B7),"-",IF(ISERROR(FIND("вич",B7,1)),"ж","м")) -> ж | I7: #REF! | J7: #REF! | K7: ЦФО Производство №2 (1 ур) | O7: 1 | P7: Основное место работы | Q7: =IF(R7="","включаем","не включаем") -> включаем | T7: Май | V7: АЛМАЗ ООО | W7: 46173
A8: 00510 | B8: Сорокина Светлана Петровна | D8: 15.05.2026 | E8: 19.07.1963 | F8: Производство №2 | G8: Специалист по управлению товарными запасами | H8: =IF(ISBLANK(B8),"-",IF(ISERROR(FIND("вич",B8,1)),"ж","м")) -> ж | I8: #REF! | J8: #REF! | K8: ЦФО Производство №2 (1 ур) | O8: 1 | P8: Основное место работы | Q8: =IF(R8="","включаем","не включаем") -> включаем | T8: Май | V8: АЛМАЗ ООО | W8: 46173
A9: 0000000038 | B9: Оганесян Кристина Лазаревна | D9: 01.04.2016 | E9: 13.03.1981 | F9: Участок сборки счетчиков | G9: Бригадир сборщиков | H9: =IF(ISBLANK(B9),"-",IF(ISERROR(FIND("вич",B9,1)),"ж","м")) -> ж | I9: #REF! | J9: #REF! | K9: ЦФО Производство №2 (1 ур) | O9: 1 | P9: Основное место работы | Q9: =IF(R9="","включаем","не включаем") -> включаем | T9: Май | V9: АЛМАЗ ООО | W9: 46173
A10: 00201 | B10: Подгорная Олеся Владимировна | D10: 23.09.2020 | E10: 20.10.1983 | F10: Участок сборки счетчиков | G10: Бригадир сборщиков | H10: =IF(ISBLANK(B10),"-",IF(ISERROR(FIND("вич",B10,1)),"ж","м")) -> ж | I10: #REF! | J10: #REF! | K10: ЦФО Производство №2 (1 ур) | O10: 1 | P10: Основное место работы | Q10: =IF(R10="","включаем","не включаем") -> включаем | T10: Май | V10: АЛМАЗ ООО | W10: 46173
A11: 00468 | B11: Беседин Вадим Вадимович | D11: 03.03.2025 | E11: 10.05.1979 | F11: Участок сборки счетчиков | G11: Сборщик | H11: =IF(ISBLANK(B11),"-",IF(ISERROR(FIND("вич",B11,1)),"ж","м")) -> м | I11: #REF! | J11: #REF! | K11: ЦФО Производство №2 (1 ур) | O11: 1 | P11: Основное место работы | Q11: =IF(R11="","включаем","не включаем") -> включаем | T11: Май | V11: АЛМАЗ ООО | W11: 46173
A12: 00489 | B12: Богачева Алла Александровна | D12: 01.07.2025 | E12: 26.07.1981 | F12: Участок сборки счетчиков | G12: Сборщик | H12: =IF(ISBLANK(B12),"-",IF(ISERROR(FIND("вич",B12,1)),"ж","м")) -> ж | I12: #REF! | J12: #REF! | K12: ЦФО Производство №2 (1 ур) | O12: 1 | P12: Основное место работы | Q12: =IF(R12="","включаем","не включаем") -> включаем | T12: Май | V12: АЛМАЗ ООО | W12: 46173
A13: 00483 | B13: Добровольская Людмила Николаевна | D13: 27.05.2025 | E13: 23.08.1981 | F13: Участок сборки счетчиков | G13: Сборщик | H13: =IF(ISBLANK(B13),"-",IF(ISERROR(FIND("вич",B13,1)),"ж","м")) -> ж | I13: #REF! | J13: #REF! | K13: ЦФО Производство №2 (1 ур) | O13: 1 | P13: Основное место работы | Q13: =IF(R13="","включаем","не включаем") -> включаем | T13: Май | V13: АЛМАЗ ООО | W13: 46173
A14: 00416 | B14: Земляков Василий Владимирович | D14: 22.09.2023 | E14: 08.04.1972 | F14: Участок сборки счетчиков | G14: Сборщик | H14: =IF(ISBLANK(B14),"-",IF(ISERROR(FIND("вич",B14,1)),"ж","м")) -> м | I14: #REF! | J14: #REF! | K14: ЦФО Производство №2 (1 ур) | O14: 1 | P14: Основное место работы | Q14: =IF(R14="","включаем","не включаем") -> включаем | T14: Май | V14: АЛМАЗ ООО | W14: 46173
A15: 00499 | B15: Зимовец Полина Александровна | D15: 21.10.2025 | E15: 09.02.2004 | F15: Участок сборки счетчиков | G15: Сборщик | H15: =IF(ISBLANK(B15),"-",IF(ISERROR(FIND("вич",B15,1)),"ж","м")) -> ж | I15: #REF! | J15: #REF! | K15: ЦФО Производство №2 (1 ур) | O15: 1 | P15: Основное место работы | Q15: =IF(R15="","включаем","не включаем") -> включаем | T15: Май | V15: АЛМАЗ ООО | W15: 46173
A16: 00487 | B16: Кейсон Алексея Викторовна | D16: 01.07.2025 | E16: 24.12.2000 | F16: Участок сборки счетчиков | G16: Сборщик | H16: =IF(ISBLANK(B16),"-",IF(ISERROR(FIND("вич",B16,1)),"ж","м")) -> ж | I16: #REF! | J16: #REF! | K16: ЦФО Производство №2 (1 ур) | O16: 1 | P16: Основное место работы | Q16: =IF(R16="","включаем","не включаем") -> включаем | T16: Май | V16: АЛМАЗ ООО | W16: 46173
A17: 00421 | B17: Кобцева Наталья Алексеевна | D17: 04.10.2023 | E17: 09.05.1977 | F17: Участок сборки счетчиков | G17: Сборщик | H17: =IF(ISBLANK(B17),"-",IF(ISERROR(FIND("вич",B17,1)),"ж","м")) -> ж | I17: #REF! | J17: #REF! | K17: ЦФО Производство №2 (1 ур) | O17: 1 | P17: Основное место работы | Q17: =IF(R17="","включаем","не включаем") -> включаем | T17: Май | V17: АЛМАЗ ООО | W17: 46173
... A21: 00511 | B21: Свистов Максим Вячеславович | D21: 18.05.2026 | E21: 14.01.1975 | F21: Участок сборки счетчиков | G21: Сборщик | H21: =IF(ISBLANK(B21),"-",IF(ISERROR(FIND("вич",B21,1)),"ж","м")) -> м | I21: #REF! | J21: #REF! | K21: ЦФО Производство №2 (1 ур) | O21: 1 | P21: Основное место работы | Q21: =IF(R21="","включаем","не включаем") -> включаем | T21: Май | V21: АЛМАЗ ООО | W21: 46173
A22: 00478 | B22: Фомина Алена Игоревна | D22: 12.05.2025 | E22: 18.10.1996 | F22: Участок сборки счетчиков | G22: Сборщик | H22: =IF(ISBLANK(B22),"-",IF(ISERROR(FIND("вич",B22,1)),"ж","м")) -> ж | I22: #REF! | J22: #REF! | K22: ЦФО Производство №2 (1 ур) | O22: 1 | P22: Основное место работы | Q22: =IF(R22="","включаем","не включаем") -> не включаем | R22: отпуск по беременности и родам (Декрет) | T22: Май | V22: АЛМАЗ ООО | W22: 46173
A23: 00486 | B23: Азриян Артур Ашотович | D23: 09.06.2025 | E23: 14.04.1999 | F23: Участок сборки счетчиков | G23: Мастер участка | H23: =IF(ISBLANK(B23),"-",IF(ISERROR(FIND("вич",B23,1)),"ж","м")) -> м | I23: #REF! | J23: #REF! | K23: ЦФО Производство №2 (1 ур) | O23: 1 | P23: Основное место работы | Q23: =IF(R23="","включаем","не включаем") -> включаем | T23: Май | V23: АЛМАЗ ООО | W23: 46173
A24: 00497 | B24: Сафронов Игорь Александрович | D24: 01.09.2025 | E24: 12.03.1992 | F24: Участок сборки счетчиков | G24: Мастер участка | H24: =IF(ISBLANK(B24),"-",IF(ISERROR(FIND("вич",B24,1)),"ж","м")) -> м | I24: #REF! | J24: #REF! | K24: ЦФО Производство №2 (1 ур) | O24: 1 | P24: Основное место работы | Q24: =IF(R24="","включаем","не включаем") -> включаем | T24: Май | V24: АЛМАЗ ООО | W24: 46173
A25: 00419 | B25: Андреев Артем Евгеньевич | D25: 28.09.2023 | E25: 12.07.2002 | F25: Участок СПУ-5 | G25: Бригадир участка | H25: =IF(ISBLANK(B25),"-",IF(ISERROR(FIND("вич",B25,1)),"ж","м")) -> м | I25: #REF! | J25: #REF! | K25: ЦФО Производство №2 (1 ур) | O25: 1 | P25: Основное место работы | Q25: =IF(R25="","включаем","не включаем") -> включаем | T25: Май | V25: АЛМАЗ ООО | W25: 46173
A26: 00496 | B26: Клюшник Сергей Романович | D26: 01.08.2025 | E26: 07.10.2004 | F26: Участок СПУ-5 | G26: Слесарь-калибровщик | H26: =IF(ISBLANK(B26),"-",IF(ISERROR(FIND("вич",B26,1)),"ж","м")) -> м | I26: #REF! | J26: #REF! | K26: ЦФО Производство №2 (1 ур) | O26: 1 | P26: Основное место работы | Q26: =IF(R26="","включаем","не включаем") -> включаем | T26: Май | V26: АЛМАЗ ООО | W26: 46173
A27: 0000000044 | B27: Сокол Рита Васильевна | D27: 01.04.2016 | E27: 25.06.1963 | F27: Участок упаковки | G27: Сборщик-упаковщик | H27: =IF(ISBLANK(B27),"-",IF(ISERROR(FIND("вич",B27,1)),"ж","м")) -> ж | I27: #REF! | J27: #REF! | K27: ЦФО Производство №2 (1 ур) | O27: 1 | P27: Основное место работы | Q27: =IF(R27="","включаем","не включаем") -> включаем | T27: Май | V27: АЛМАЗ ООО | W27: 46173
A28: 00166 | B28: Сухарева Ольга Андреевна | D28: 22.10.2019 | E28: 24.07.1961 | F28: Участок упаковки | G28: Сборщик-упаковщик | H28: =IF(ISBLANK(B28),"-",IF(ISERROR(FIND("вич",B28,1)),"ж","м")) -> ж | I28: #REF! | J28: #REF! | K28: ЦФО Производство №2 (1 ур) | O28: 1 | P28: Основное место работы | Q28: =IF(R28="","включаем","не включаем") -> включаем | T28: Май | V28: АЛМАЗ ООО | W28: 46173
A29: 00163 | B29: Тарасов Василий Михайлович | D29: 26.09.2019 | E29: 19.01.1984 | F29: Участок ремонта гарантийных приборов | G29: Сборщик | H29: =IF(ISBLANK(B29),"-",IF(ISERROR(FIND("вич",B29,1)),"ж","м")) -> м | I29: #REF! | J29: #REF! | K29: ЦФО Производство №2 (1 ур) | O29: 1 | P29: Основное место работы | Q29: =IF(R29="","включаем","не включаем") -> включаем | T29: Май | V29: АЛМАЗ ООО | W29: 46173
A30: 00488 | B30: Очнев Олег Юрьевич | D30: 01.07.2025 | E30: 07.02.1972 | F30: Участок ремонта гарантийных приборов | G30: Монтажник РЭА | H30: =IF(ISBLANK(B30),"-",IF(ISERROR(FIND("вич",B30,1)),"ж","м")) -> м | I30: #REF! | J30: #REF! | K30: ЦФО Производство №2 (1 ур) | O30: 1 | P30: Основное место работы | Q30: =IF(R30="","включаем","не включаем") -> включаем | T30: Май | V30: АЛМАЗ ООО | W30: 46173
A31: 00512 | B31: Гладуненко Павел Александрович | D31: 19.05.2026 | E31: 18.12.1980 | F31: Участок монтажа радиоэлектронной аппаратуры | G31: Монтажник РЭА | H31: =IF(ISBLANK(B31),"-",IF(ISERROR(FIND("вич",B31,1)),"ж","м")) -> м | I31: #REF! | J31: #REF! | K31: ЦФО Производство №2 (1 ур) | O31: 1 | P31: Основное место работы | Q31: =IF(R31="","включаем","не включаем") -> включаем | T31: Май | V31: АЛМАЗ ООО | W31: 46173
A32: 00449 | B32: Добровольский Дмитрий Дмитриевич | D32: 01.08.2024 | E32: 05.07.1984 | F32: Участок ремонта и обслуживания оборудования | G32: Бригадир участка | H32: =IF(ISBLANK(B32),"-",IF(ISERROR(FIND("вич",B32,1)),"ж","м")) -> м | I32: #REF! | J32: #REF! | K32: ЦФО Производство №2 (1 ур) | O32: 1 | P32: Основное место работы | Q32: =IF(R32="","включаем","не включаем") -> включаем | T32: Май | V32: АЛМАЗ ООО | W32: 46173
A33: 00443 | B33: Андронов Николай Леонидович | D33: 14.06.2024 | E33: 01.09.1988 | F33: Участок ремонта и обслуживания оборудования | G33: Слесарь КИПиА | H33: =IF(ISBLANK(B33),"-",IF(ISERROR(FIND("вич",B33,1)),"ж","м")) -> м | I33: #REF! | J33: #REF! | K33: ЦФО Производство №2 (1 ур) | O33: 1 | P33: Основное место работы | Q33: =IF(R33="","включаем","не включаем") -> включаем | T33: Май | V33: АЛМАЗ ООО | W33: 46173
A34: 00221 | B34: Кравченко Александр Борисович | D34: 30.04.2021 | E34: 12.04.1971 | F34: Участок ремонта и обслуживания оборудования | G34: Слесарь КИПиА | H34: =IF(ISBLANK(B34),"-",IF(ISERROR(FIND("вич",B34,1)),"ж","м")) -> м | I34: #REF! | J34: #REF! | K34: ЦФО Производство №2 (1 ур) | O34: 1 | P34: Основное место работы | Q34: =IF(R34="","включаем","не включаем") -> включаем | T34: Май | V34: АЛМАЗ ООО | W34: 46173
... A41: 0000000004 | B41: Кулешова Наталья Станиславовна | D41: 03.10.2016 | E41: 05.11.1984 | F41: Отдел материально-технического обеспечения | G41: Заместитель начальника отдела | H41: =IF(ISBLANK(B41),"-",IF(ISERROR(FIND("вич",B41,1)),"ж","м")) -> ж | I41: #REF! | J41: #REF! | K41: ЦФО Служба логистики (2 ур) | O41: 1 | P41: Основное место работы | Q41: =IF(R41="","включаем","не включаем") -> включаем | T41: Май | V41: ИП Корниенко М.В. | W41: 46173
A42: 00029 | B42: Дмитрук Оксана Александровна | D42: 14.08.2023 | E42: 21.02.1985 | F42: Отдел материально-технического обеспечения | G42: Менеджер по сопровождению | H42: =IF(ISBLANK(B42),"-",IF(ISERROR(FIND("вич",B42,1)),"ж","м")) -> ж | I42: #REF! | J42: #REF! | K42: ЦФО Служба логистики (2 ур) | O42: 1 | P42: Основное место работы | Q42: =IF(R42="","включаем","не включаем") -> не включаем | R42: отпуск по беременности и родам (Декрет) | T42: Май | V42: ИП Корниенко М.В. | W42: 46173
A43: 00043 | B43: Ковалева Вера Александровна | D43: 02.02.2026 | E43: 13.05.1997 | F43: Отдел материально-технического обеспечения | G43: Менеджер по сопровождению | H43: =IF(ISBLANK(B43),"-",IF(ISERROR(FIND("вич",B43,1)),"ж","м")) -> ж | I43: #REF! | J43: #REF! | K43: ЦФО Служба логистики (2 ур) | O43: 1 | P43: Основное место работы | Q43: =IF(R43="","включаем","не включаем") -> включаем | T43: Май | V43: ИП Корниенко М.В. | W43: 46173
A44: 00044 | B44: Любченко Оксана Николаевна | D44: 18.05.2026 | E44: 26.03.1976 | F44: Отдел материально-технического обеспечения | G44: Менеджер по сопровождению | H44: =IF(ISBLANK(B44),"-",IF(ISERROR(FIND("вич",B44,1)),"ж","м")) -> ж | I44: #REF! | J44: #REF! | K44: ЦФО Служба логистики (2 ур) | O44: 1 | P44: Основное место работы | Q44: =IF(R44="","включаем","не включаем") -> включаем | T44: Май | V44: ИП Корниенко М.В. | W44: 46173
A45: 00041 | B45: Нижерадзе Алина Геноевна | D45: 10.09.2025 | E45: 18.06.2003 | F45: Отдел материально-технического обеспечения | G45: Менеджер по сопровождению | H45: =IF(ISBLANK(B45),"-",IF(ISERROR(FIND("вич",B45,1)),"ж","м")) -> ж | I45: #REF! | J45: #REF! | K45: ЦФО Служба логистики (2 ур) | O45: 1 | P45: Основное место работы | Q45: =IF(R45="","включаем","не включаем") -> включаем | T45: Май | V45: ИП Корниенко М.В. | W45: 46173
A46: 00013 | B46: Пожидаева Марина Васильевна | D46: 19.04.2021 | E46: 21.10.1981 | F46: Отдел материально-технического обеспечения | G46: Менеджер по сопровождению | H46: =IF(ISBLANK(B46),"-",IF(ISERROR(FIND("вич",B46,1)),"ж","м")) -> ж | I46: #REF! | J46: #REF! | K46: ЦФО Служба логистики (2 ур) | O46: 1 | P46: Основное место работы | Q46: =IF(R46="","включаем","не включаем") -> включаем | T46: Май | V46: ИП Корниенко М.В. | W46: 46173
A47: 00038 | B47: Коваленко Артемий Олегович | D47: 05.11.2024 | E47: 09.08.1979 | F47: Отдел материально-технического обеспечения | G47: Начальник отдела материально-технического обеспечения | H47: =IF(ISBLANK(B47),"-",IF(ISERROR(FIND("вич",B47,1)),"ж","м")) -> м | I47: #REF! | J47: #REF! | K47: ЦФО Служба логистики (2 ур) | O47: 1 | P47: Основное место работы | Q47: =IF(R47="","включаем","не включаем") -> включаем | T47: Май | V47: ИП Корниенко М.В. | W47: 46173
A48: 00006 | B48: Ершова Ирина Лаврентьевна | D48: 26.11.2018 | E48: 21.10.1967 | F48: Отдел материально-технического обеспечения | G48: Ведущий менеджер | H48: =IF(ISBLANK(B48),"-",IF(ISERROR(FIND("вич",B48,1)),"ж","м")) -> ж | I48: #REF! | J48: #REF! | K48: ЦФО Служба логистики (2 ур) | O48: 1 | P48: Основное место работы | Q48: =IF(R48="","включаем","не включаем") -> включаем | T48: Май | V48: ИП Корниенко М.В. | W48: 46173
A49: 0000000003 | B49: Коржов Дмитрий Владимирович | D49: 03.10.2016 | E49: 27.03.1977 | F49: Отдел материально-технического обеспечения | G49: Ведущий менеджер | H49: =IF(ISBLANK(B49),"-",IF(ISERROR(FIND("вич",B49,1)),"ж","м")) -> м | I49: #REF! | J49: #REF! | K49: ЦФО Служба логистики (2 ур) | O49: 1 | P49: Основное место работы | Q49: =IF(R49="","включаем","не включаем") -> включаем | T49: Май | V49: ИП Корниенко М.В. | W49: 46173
A50: 00034 | B50: Короткова Валентина Викторовна | D50: 22.09.2023 | E50: 18.05.1985 | F50: Отдел материально-технического обеспечения | G50: Ведущий менеджер | H50: =IF(ISBLANK(B50),"-",IF(ISERROR(FIND("вич",B50,1)),"ж","м")) -> ж | I50: #REF! | J50: #REF! | K50: ЦФО Служба логистики (2 ур) | O50: 1 | P50: Основное место работы | Q50: =IF(R50="","включаем","не включаем") -> включаем | T50: Май | V50: ИП Корниенко М.В. | W50: 46173
A51: 00026 | B51: Мозговая Вероника Викторовна | D51: 10.07.2023 | E51: 17.09.1999 | F51: Отдел материально-технического обеспечения | G51: Ведущий менеджер | H51: =IF(ISBLANK(B51),"-",IF(ISERROR(FIND("вич",B51,1)),"ж","м")) -> ж | I51: #REF! | J51: #REF! | K51: ЦФО Служба логистики (2 ур) | O51: 1 | P51: Основное место работы | Q51: =IF(R51="","включаем","не включаем") -> включаем | T51: Май | V51: ИП Корниенко М.В. | W51: 46173
A52: 00028 | B52: Стародубова Инна Юрьевна | D52: 10.08.2023 | E52: 29.05.1987 | F52: Отдел материально-технического обеспечения | G52: Ведущий менеджер | H52: =IF(ISBLANK(B52),"-",IF(ISERROR(FIND("вич",B52,1)),"ж","м")) -> ж | I52: #REF! | J52: #REF! | K52: ЦФО Служба логистики (2 ур) | O52: 1 | P52: Основное место работы | Q52: =IF(R52="","включаем","не включаем") -> включаем | T52: Май | V52: ИП Корниенко М.В. | W52: 46173
A53: МГС000109 | B53: Чепурин Роман Алексеевич | D53: 20.06.2016 | E53: 06.12.1991 | F53: Азовский СЦ | G53: Начальник сервисного центра | H53: =IF(ISBLANK(B53),"-",IF(ISERROR(FIND("вич",B53,1)),"ж","м")) -> м | I53: #REF! | J53: #REF! | K53: ЦФО МГС (1 ур) | O53: 1 | P53: Основное место работы | Q53: =IF(R53="","включаем","не включаем") -> включаем | T53: Май | V53: Метрогазсервис ООО | W53: 46173
A54: 00138 | B54: Григорьева Яна Павловна | D54: 06.05.2026 | E54: 29.07.1986 | F54: Азовский СЦ | G54: Кассир-приемщик | H54: =IF(ISBLANK(B54),"-",IF(ISERROR(FIND("вич",B54,1)),"ж","м")) -> ж | I54: #REF! | J54: #REF! | K54: ЦФО МГС (1 ур) | O54: 1 | P54: Основное место работы | Q54: =IF(R54="","включаем","не включаем") -> включаем | T54: Май | V54: Метрогазсервис ООО | W54: 46173
A55: 00087 | B55: Романенко Виктория Игоревна | D55: 10.06.2021 | E55: 26.03.1988 | F55: Азовский СЦ | G55: Кассир-приемщик | H55: =IF(ISBLANK(B55),"-",IF(ISERROR(FIND("вич",B55,1)),"ж","м")) -> ж | I55: #REF! | J55: #REF! | K55: ЦФО МГС (1 ур) | O55: 1 | P55: Основное место работы | Q55: =IF(R55="","включаем","не включаем") -> не включаем | R55: отпуск по уходу за ребенком до 1,5 и 3-х лет | T55: Май | V55: Метрогазсервис ООО | W55: 46173
A56: 00025 | B56: Калинин Тимур Эдуардович | D56: 20.08.2018 | E56: 28.05.1992 | F56: Азовский СЦ | G56: Техник | H56: =IF(ISBLANK(B56),"-",IF(ISERROR(FIND("вич",B56,1)),"ж","м")) -> м | I56: #REF! | J56: #REF! | K56: ЦФО МГС (1 ур) | O56: 1 | P56: Основное место работы | Q56: =IF(R56="","включаем","не включаем") -> включаем | T56: Май | V56: Метрогазсервис ООО | W56: 46173
A57: 00073 | B57: Батюков Николай Сергеевич | D57: 16.07.2020 | E57: 01.04.1984 | F57: Батайский СЦ | G57: Начальник сервисного центра | H57: =IF(ISBLANK(B57),"-",IF(ISERROR(FIND("вич",B57,1)),"ж","м")) -> м | I57: #REF! | J57: #REF! | K57: ЦФО МГС (1 ур) | O57: 1 | P57: Основное место работы | Q57: =IF(R57="","включаем","не включаем") -> включаем | T57: Май | V57: Метрогазсервис ООО | W57: 46173
A58: 00028 | B58: Шитухина Наталья Федоровна | D58: 29.08.2018 | E58: 21.06.1989 | F58: Батайский СЦ | G58: Кассир-приемщик | H58: =IF(ISBLANK(B58),"-",IF(ISERROR(FIND("вич",B58,1)),"ж","м")) -> ж | I58: #REF! | J58: #REF! | K58: ЦФО МГС (1 ур) | O58: 1 | P58: Основное место работы | Q58: =IF(R58="","включаем","не включаем") -> включаем | T58: Май | V58: Метрогазсервис ООО | W58: 46173
A59: МГС0000097 | B59: Плещенко Сергей Сергеевич | D59: 27.11.2015 | E59: 01.10.1988 | F59: Волгодонской СЦ | G59: Начальник сервисного центра | H59: =IF(ISBLANK(B59),"-",IF(ISERROR(FIND("вич",B59,1)),"ж","м")) -> м | I59: #REF! | J59: #REF! | K59: ЦФО МГС (1 ур) | O59: 1 | P59: Основное место работы | Q59: =IF(R59="","включаем","не включаем") -> включаем | T59: Май | V59: Метрогазсервис ООО | W59: 46173
A60: 00094 | B60: Рожкова Светлана Ивановна | D60: 25.05.2022 | E60: 18.05.1970 | F60: Волгодонской СЦ | G60: Кассир-приемщик | H60: =IF(ISBLANK(B60),"-",IF(ISERROR(FIND("вич",B60,1)),"ж","м")) -> ж | I60: #REF! | J60: #REF! | K60: ЦФО МГС (1 ур) | O60: 1 | P60: Основное место работы | Q60: =IF(R60="","включаем","не включаем") -> включаем | T60: Май | V60: Метрогазсервис ООО | W60: 46173
A61: 00055 | B61: Болдырев Игорь Васильевич | D61: 05.08.2019 | E61: 10.12.1964 | F61: Каменск-Шахтинский СЦ | G61: Начальник сервисного центра | H61: =IF(ISBLANK(B61),"-",IF(ISERROR(FIND("вич",B61,1)),"ж","м")) -> м | I61: #REF! | J61: #REF! | K61: ЦФО МГС (1 ур) | O61: 1 | P61: Основное место работы | Q61: =IF(R61="","включаем","не включаем") -> включаем | T61: Май | V61: Метрогазсервис ООО | W61: 46173
A62: 00081 | B62: Бодрова Элеонора Геннадьевна | D62: 22.10.2020 | E62: 11.08.1968 | F62: Каменск-Шахтинский СЦ | G62: Кассир-приемщик | H62: =IF(ISBLANK(B62),"-",IF(ISERROR(FIND("вич",B62,1)),"ж","м")) -> ж | I62: #REF! | J62: #REF! | K62: ЦФО МГС (1 ур) | O62: 1 | P62: Основное место работы | Q62: =IF(R62="","включаем","не включаем") -> включаем | T62: Май | V62: Метрогазсервис ООО | W62: 46173
A63: МГС0000066 | B63: Беспалов Александр Сергеевич | D63: 07.07.2015 | E63: 06.05.1973 | F63: Каменск-Шахтинский СЦ | G63: Техник | H63: =IF(ISBLANK(B63),"-",IF(ISERROR(FIND("вич",B63,1)),"ж","м")) -> м | I63: #REF! | J63: #REF! | K63: ЦФО МГС (1 ур) | O63: 1 | P63: Основное место работы | Q63: =IF(R63="","включаем","не включаем") -> включаем | T63: Май | V63: Метрогазсервис ООО | W63: 46173
A64: МГС000103 | B64: Моганов Александр Борисович | D64: 30.03.2016 | E64: 03.12.1979 | F64: Новочеркасский СЦ | G64: Начальник сервисного центра | H64: =IF(ISBLANK(B64),"-",IF(ISERROR(FIND("вич",B64,1)),"ж","м")) -> м | I64: #REF! | J64: #REF! | K64: ЦФО МГС (1 ур) | O64: 1 | P64: Основное место работы | Q64: =IF(R64="","включаем","не включаем") -> включаем | T64: Май | V64: Метрогазсервис ООО | W64: 46173
A65: 00007 | B65: Калитвинцева Виктория Викторовна | D65: 19.02.2018 | E65: 29.07.1989 | F65: Новочеркасский СЦ | G65: Кассир-приемщик | H65: =IF(ISBLANK(B65),"-",IF(ISERROR(FIND("вич",B65,1)),"ж","м")) -> ж | I65: #REF! | J65: #REF! | K65: ЦФО МГС (1 ур) | O65: 1 | P65: Основное место работы | Q65: =IF(R65="","включаем","не включаем") -> включаем | T65: Май | V65: Метрогазсервис ООО | W65: 46173
A66: МГС0000012 | B66: Кущев Вячеслав Юрьевич | D66: 01.03.2010 | E66: 03.08.1985 | F66: Ростов (Нагибина) СЦ | G66: Начальник сервисного центра | H66: =IF(ISBLANK(B66),"-",IF(ISERROR(FIND("вич",B66,1)),"ж","м")) -> м | I66: #REF! | J66: #REF! | K66: ЦФО МГС (1 ур) | O66: 1 | P66: Основное место работы | Q66: =IF(R66="","включаем","не включаем") -> включаем | T66: Май | V66: Метрогазсервис ООО | W66: 46173
A67: 00011 | B67: Боровикова Виктория Ричардовна | D67: 02.04.2018 | E67: 13.07.1968 | F67: Ростов (Нагибина) СЦ | G67: Кассир-приемщик | H67: =IF(ISBLANK(B67),"-",IF(ISERROR(FIND("вич",B67,1)),"ж","м")) -> ж | I67: #REF! | J67: #REF! | K67: ЦФО МГС (1 ур) | O67: 1 | P67: Основное место работы | Q67: =IF(R67="","включаем","не включаем") -> включаем | T67: Май | V67: Метрогазсервис ООО | W67: 46173
... A79: 00091 | B79: Махлин Константин Романович | D79: 01.04.2022 | E79: 16.02.1978 | F79: Основное подразделение (Промзона) | G79: Директор | H79: =IF(ISBLANK(B79),"-",IF(ISERROR(FIND("вич",B79,1)),"ж","м")) -> м | I79: #REF! | J79: #REF! | K79: ЦФО МГС (1 ур) | O79: 1 | P79: Основное место работы | Q79: =IF(R79="","включаем","не включаем") -> включаем | T79: Май | V79: Метрогазсервис ООО | W79: 46173
A80: МГС000102 | B80: Махлин Роман Ильич | D80: 01.04.2016 | E80: 15.05.1951 | F80: Основное подразделение (Промзона) | G80: Ведущий специалист по физической культуре и спорту | H80: =IF(ISBLANK(B80),"-",IF(ISERROR(FIND("вич",B80,1)),"ж","м")) -> ж | I80: #REF! | J80: #REF! | K80: ЦФО МГС (1 ур) | O80: 1 | P80: Основное место работы | Q80: =IF(R80="","включаем","не включаем") -> не включаем | R80: длительное отсутствие по невыясненным причинам | T80: Май | V80: Метрогазсервис ООО | W80: 46173
A81: 00097 | B81: Мостовая Екатерина Валерьевна | D81: 01.09.2022 | E81: 01.08.1987 | F81: Основное подразделение (Промзона) | G81: Бухгалтер | H81: =IF(ISBLANK(B81),"-",IF(ISERROR(FIND("вич",B81,1)),"ж","м")) -> ж | I81: #REF! | J81: #REF! | K81: ЦФО МГС (1 ур) | O81: 1 | P81: Основное место работы | Q81: =IF(R81="","включаем","не включаем") -> включаем | T81: Май | V81: Метрогазсервис ООО | W81: 46173
A82: 00070 | B82: Яценко Максим Викторович | D82: 19.05.2020 | E82: 06.11.1983 | F82: Основное подразделение (Промзона) | G82: Начальник отдела снабжения | H82: =IF(ISBLANK(B82),"-",IF(ISERROR(FIND("вич",B82,1)),"ж","м")) -> м | I82: #REF! | J82: #REF! | K82: ЦФО МГС (1 ур) | O82: 1 | P82: Основное место работы | Q82: =IF(R82="","включаем","не включаем") -> включаем | T82: Май | V82: Метрогазсервис ООО | W82: 46173
A83: 00122 | B83: Вартаньянц Артем Гариевич | D83: 22.05.2024 | E83: 06.09.2001 | F83: Основное подразделение (Промзона) | G83: Менеджер по работе с маркетплейсами | H83: =IF(ISBLANK(B83),"-",IF(ISERROR(FIND("вич",B83,1)),"ж","м")) -> м | I83: #REF! | J83: #REF! | K83: ЦФО МГС (1 ур) | O83: 1 | P83: Основное место работы | Q83: =IF(R83="","включаем","не включаем") -> включаем | T83: Май | V83: Метрогазсервис ООО | W83: 46173
A84: 00137 | B84: Сафарян Валерий Роланович | D84: 30.03.2026 | E84: 19.02.1999 | F84: Основное подразделение (Промзона) | G84: Менеджер по продаже промышленного оборудования | H84: =IF(ISBLANK(B84),"-",IF(ISERROR(FIND("вич",B84,1)),"ж","м")) -> м | I84: #REF! | J84: #REF! | K84: ЦФО МГС (1 ур) | O84: 1 | P84: Основное место работы | Q84: =IF(R84="","включаем","не включаем") -> включаем | T84: Май | V84: Метрогазсервис ООО | W84: 46173
A85: 00129 | B85: Рыков Роман Иванович | D85: 26.12.2024 | E85: 08.10.1982 | F85: Семикаракорский СЦ | G85: Начальник сервисного центра | H85: =IF(ISBLANK(B85),"-",IF(ISERROR(FIND("вич",B85,1)),"ж","м")) -> м | I85: #REF! | J85: #REF! | K85: ЦФО МГС (1 ур) | O85: 1 | P85: Основное место работы | Q85: =IF(R85="","включаем","не включаем") -> включаем | T85: Май | V85: Метрогазсервис ООО | W85: 46173
A86: 00105 | B86: Семионова Оксана Михайловна | D86: 06.06.2023 | E86: 27.12.1975 | F86: Семикаракорский СЦ | G86: Кассир-приемщик | H86: =IF(ISBLANK(B86),"-",IF(ISERROR(FIND("вич",B86,1)),"ж","м")) -> ж | I86: #REF! | J86: #REF! | K86: ЦФО МГС (1 ур) | O86: 1 | P86: Основное место работы | Q86: =IF(R86="","включаем","не включаем") -> включаем | T86: Май | V86: Метрогазсервис ООО | W86: 46173
A87: 00059 | B87: Беседин Евгений Сергеевич | D87: 20.12.2019 | E87: 01.09.1975 | F87: Сальский СЦ | G87: Начальник сервисного центра | H87: =IF(ISBLANK(B87),"-",IF(ISERROR(FIND("вич",B87,1)),"ж","м")) -> м | I87: #REF! | J87: #REF! | K87: ЦФО МГС (1 ур) | O87: 1/2 | P87: Внешнее совместительство | Q87: =IF(R87="","включаем","не включаем") -> включаем | T87: Май | V87: Метрогазсервис ООО | W87: 46173
A88: 00060 | B88: Гориславская Татьяна Викторовна | D88: 20.12.2019 | E88: 13.09.1970 | F88: Сальский СЦ | G88: Кассир-приемщик | H88: =IF(ISBLANK(B88),"-",IF(ISERROR(FIND("вич",B88,1)),"ж","м")) -> ж | I88: #REF! | J88: #REF! | K88: ЦФО МГС (1 ур) | O88: 1 | P88: Основное место работы | Q88: =IF(R88="","включаем","не включаем") -> включаем | T88: Май | V88: Метрогазсервис ООО | W88: 46173
A89: 00132 | B89: Недвига Игорь Николаевич | D89: 12.02.2025 | E89: 20.08.1970 | F89: Миллеровский СЦ | G89: Начальник сервисного центра | H89: =IF(ISBLANK(B89),"-",IF(ISERROR(FIND("вич",B89,1)),"ж","м")) -> м | I89: #REF! | J89: #REF! | K89: ЦФО МГС (1 ур) | O89: 1 | P89: Основное место работы | Q89: =IF(R89="","включаем","не включаем") -> включаем | T89: Май | V89: Метрогазсервис ООО | W89: 46173
A90: 00128 | B90: Манифат Елена Николаевна | D90: 26.11.2024 | E90: 10.03.1979 | F90: Миллеровский СЦ | G90: Кассир-приемщик | H90: =IF(ISBLANK(B90),"-",IF(ISERROR(FIND("вич",B90,1)),"ж","м")) -> ж | I90: #REF! | J90: #REF! | K90: ЦФО МГС (1 ур) | O90: 1 | P90: Основное место работы | Q90: =IF(R90="","включаем","не включаем") -> включаем | T90: Май | V90: Метрогазсервис ООО | W90: 46173
A91: 00100 | B91: Губайдулин Андрей Раисович | D91: 09.01.2023 | E91: 27.10.1965 | F91: Зерноградский СЦ | G91: Начальник сервисного центра | H91: =IF(ISBLANK(B91),"-",IF(ISERROR(FIND("вич",B91,1)),"ж","м")) -> м | I91: #REF! | J91: #REF! | K91: ЦФО МГС (1 ур) | O91: 1/2 | P91: Внешнее совместительство | Q91: =IF(R91="","включаем","не включаем") -> включаем | T91: Май | V91: Метрогазсервис ООО | W91: 46173
A92: 00123 | B92: Донцова Наталья Сергеевна | D92: 28.05.2024 | E92: 05.03.1982 | F92: Зерноградский СЦ | G92: Кассир-приемщик | H92: =IF(ISBLANK(B92),"-",IF(ISERROR(FIND("вич",B92,1)),"ж","м")) -> ж | I92: #REF! | J92: #REF! | K92: ЦФО МГС (1 ур) | O92: 1 | P92: Основное место работы | Q92: =IF(R92="","включаем","не включаем") -> включаем | T92: Май | V92: Метрогазсервис ООО | W92: 46173
A93: 00111 | B93: Дегтярь Виталий Григорьевич | D93: 24.10.2023 | E93: 20.01.1979 | F93: Новошахтинский СЦ | G93: Начальник сервисного центра | H93: =IF(ISBLANK(B93),"-",IF(ISERROR(FIND("вич",B93,1)),"ж","м")) -> м | I93: #REF! | J93: #REF! | K93: ЦФО МГС (1 ур) | O93: 1 | P93: Основное место работы | Q93: =IF(R93="","включаем","не включаем") -> включаем | T93: Май | V93: Метрогазсервис ООО | W93: 46173
A94: 00130 | B94: Еремеева Мария Сергеевна | D94: 24.01.2025 | E94: 12.11.1985 | F94: Новошахтинский СЦ | G94: Кассир-приемщик | H94: =IF(ISBLANK(B94),"-",IF(ISERROR(FIND("вич",B94,1)),"ж","м")) -> ж | I94: #REF! | J94: #REF! | K94: ЦФО МГС (1 ур) | O94: 1 | P94: Основное место работы | Q94: =IF(R94="","включаем","не включаем") -> включаем | T94: Май | V94: Метрогазсервис ООО | W94: 46173
A95: 00134 | B95: Ряжских Виталий Витальевич | D95: 01.08.2025 | E95: 03.01.1998 | F95: Вешенский СЦ | G95: Начальник сервисного центра | H95: =IF(ISBLANK(B95),"-",IF(ISERROR(FIND("вич",B95,1)),"ж","м")) -> м | I95: #REF! | J95: #REF! | K95: ЦФО МГС (1 ур) | O95: 1/2 | P95: Внешнее совместительство | Q95: =IF(R95="","включаем","не включаем") -> не включаем | R95: внешний совместитель | T95: Май | V95: Метрогазсервис ООО | W95: 46173
A96: 00135 | B96: Михеева Маргарита Александровна | D96: 01.08.2025 | E96: 10.11.1990 | F96: Вешенский СЦ | G96: Кассир-приемщик | H96: =IF(ISBLANK(B96),"-",IF(ISERROR(FIND("вич",B96,1)),"ж","м")) -> ж | I96: #REF! | J96: #REF! | K96: ЦФО МГС (1 ур) | O96: 1 | P96: Основное место работы | Q96: =IF(R96="","включаем","не включаем") -> включаем | T96: Май | V96: Метрогазсервис ООО | W96: 46173
A97: 00090 | B97: Боброва Анастасия Викторовна | D97: 01.01.2020 | E97: 15.10.1980 | F97: Руководство | G97: Директор | H97: =IF(ISBLANK(B97),"-",IF(ISERROR(FIND("вич",B97,1)),"ж","м")) -> ж | I97: #REF! | J97: #REF! | K97: ЦФО Руководство (2 ур) | O97: 1/10 | P97: Внешнее совместительство | Q97: =IF(R97="","включаем","не включаем") -> не включаем | R97: внешний совместитель | T97: Май | V97: ТУРБУЛЕНТНОСТЬ-ДОН ООО НПО | W97: 46173
A98: 00714 | B98: Донцова Анна Егоровна | D98: 06.09.2023 | E98: 13.02.1981 | F98: Руководство ГК | G98: Директор | H98: =IF(ISBLANK(B98),"-",IF(ISERROR(FIND("вич",B98,1)),"ж","м")) -> ж | I98: #REF! | J98: #REF! | K98: ЦФО Руководство (2 ур) | O98: 1 | P98: Основное место работы | Q98: =IF(R98="","включаем","не включаем") -> включаем | T98: Май | V98: ТУРБУЛЕНТНОСТЬ-ДОН ООО НПО | W98: 46173
A99: 0000000698 | B99: Амураль Игорь Борисович | D99: 01.04.2016 | E99: 16.09.1967 | F99: Руководство ГК | G99: Председатель совета директоров | H99: =IF(ISBLANK(B99),"-",IF(ISERROR(FIND("вич",B99,1)),"ж","м")) -> м | I99: #REF! | J99: #REF! | K99: ЦФО Руководство (2 ур) | O99: 1/2 | P99: Внутреннее совместительство | Q99: =IF(R99="","включаем","не включаем") -> не включаем | R99: внутренний соместитель | T99: Май | V99: ТУРБУЛЕНТНОСТЬ-ДОН ООО НПО | W99: 46173
A100: 00958 | B100: Акинина Татьяна Владимировна | D100: 24.03.2025 | E100: 21.06.2003 | F100: Управление делами | G100: Помощник руководителя | H100: =IF(ISBLANK(B100),"-",IF(ISERROR(FIND("вич",B100,1)),"ж","м")) -> ж | I100: #REF! | J100: #REF! | K100: ЦФО Руководство (2 ур) | O100: 1 | P100: Основное место работы | Q100: =IF(R100="","включаем","не включаем") -> включаем | T100: Май | V100: ТУРБУЛЕНТНОСТЬ-ДОН ООО НПО | W100: 46173
A101: 00184 | B101: Некрас Кристина Игоревна | D101: 18.03.2019 | E101: 05.08.1996 | F101: Управление делами | G101: Помощник руководителя | H101: =IF(ISBLANK(B101),"-",IF(ISERROR(FIND("вич",B101,1)),"ж","м")) -> ж | I101: #REF! | J101: #REF! | K101: ЦФО Руководство (2 ур) | O101: 1 | P101: Основное место работы | Q101: =IF(R101="","включаем","не включаем") -> не включаем | R101: длительный отпуск без сохранения з/п | T101: Май | V101: ТУРБУЛЕНТНОСТЬ-ДОН ООО НПО | W101: 46173
A102: 00845 | B102: Ильченко Екатерина Александровна | D102: 07.08.2024 | E102: 13.03.1979 | F102: Управление делами | G102: Помощник Председателя совета директоров | H102: =IF(ISBLANK(B102),"-",IF(ISERROR(FIND("вич",B102,1)),"ж","м")) -> ж | I102: #REF! | J102: #REF! | K102: ЦФО Руководство (2 ур) | O102: 1 | P102: Основное место работы | Q102: =IF(R102="","включаем","не включаем") -> включаем | T102: Май | V102: ТУРБУЛЕНТНОСТЬ-ДОН ООО НПО | W102: 46173
A103: 0000000873 | B103: Черепахина Елена Алексеевна | D103: 01.09.2017 | E103: 05.01.1993 | F103: Управление делами | G103: Офис-менеджер | H103: =IF(ISBLANK(B103),"-",IF(ISERROR(FIND("вич",B103,1)),"ж","м")) -> ж | I103: #REF! | J103: #REF! | K103: ЦФО Руководство (2 ур) | O103: 1 | P103: Основное место работы | Q103: =IF(R103="","включаем","не включаем") -> не включаем | R103: отпуск по уходу за ребенком до 1,5 и 3-х лет | T103: Май | V103: ТУРБУЛЕНТНОСТЬ-ДОН ООО НПО | W103: 46173
A104: 01106 | B104: Липкина Анна Викторовна | D104: 01.04.2026 | E104: 13.03.1987 | F104: Управление делами | G104: Архивариус | H104: =IF(ISBLANK(B104),"-",IF(ISERROR(FIND("вич",B104,1)),"ж","м")) -> ж | I104: #REF! | J104: #REF! | K104: ЦФО Руководство (2 ур) | O104: 1 | P104: Основное место работы | Q104: =IF(R104="","включаем","не включаем") -> включаем | T104: Май | V104: ТУРБУЛЕНТНОСТЬ-ДОН ООО НПО | W104: 46173
A105: 0000000599 | B105: Свистун Сергей Николаевич | D105: 26.12.2013 | E105: 03.05.1966 | F105: Служба экономической безопасности | G105: Заместитель директора по экономической безопасности | H105: =IF(ISBLANK(B105),"-",IF(ISERROR(FIND("вич",B105,1)),"ж","м")) -> м | I105: #REF! | J105: #REF! | K105: ЦФО Служба безопасности (2 ур) | O105: 1 | P105: Основное место работы | Q105: =IF(R105="","включаем","не включаем") -> включаем | T105: Май | V105: ТУРБУЛЕНТНОСТЬ-ДОН ООО НПО | W105: 46173
A106: 01116 | B106: Колганов Александр Юрьевич | D106: 07.05.2026 | E106: 25.11.1975 | F106: Служба безопасности | G106: Начальник службы безопасности | H106: =IF(ISBLANK(B106),"-",IF(ISERROR(FIND("вич",B106,1)),"ж","м")) -> м | I106: #REF! | J106: #REF! | K106: ЦФО Служба безопасности (2 ур) | O106: 1 | P106: Основное место работы | Q106: =IF(R106="","включаем","не включаем") -> включаем | T106: Май | V106: ТУРБУЛЕНТНОСТЬ-ДОН ООО НПО | W106: 46173
A107: 01084 | B107: Алимов Евгений Юрьевич | D107: 23.01.2026 | E107: 10.02.1963 | F107: Служба безопасности | G107: Контролер поста контроля | H107: =IF(ISBLANK(B107),"-",IF(ISERROR(FIND("вич",B107,1)),"ж","м")) -> м | I107: #REF! | J107: #REF! | K107: ЦФО Служба безопасности (2 ур) | O107: 1 | P107: Основное место работы | Q107: =IF(R107="","включаем","не включаем") -> включаем | T107: Май | V107: ТУРБУЛЕНТНОСТЬ-ДОН ООО НПО | W107: 46173
A108: 0000000643 | B108: Аразов Надир Сефединович | D108: 01.09.2014 | E108: 27.04.1964 | F108: Служба безопасности | G108: Контролер поста контроля | H108: =IF(ISBLANK(B108),"-",IF(ISERROR(FIND("вич",B108,1)),"ж","м")) -> м | I108: #REF! | J108: #REF! | K108: ЦФО Служба безопасности (2 ур) | O108: 1 | P108: Основное место работы | Q108: =IF(R108="","включаем","не включаем") -> включаем | T108: Май | V108: ТУРБУЛЕНТНОСТЬ-ДОН ООО НПО | W108: 46173
A109: 01031 | B109: Берсанов Руслан Абдрахманович | D109: 12.08.2025 | E109: 25.11.1960 | F109: Служба безопасности | G109: Контролер поста контроля | H109: =IF(ISBLANK(B109),"-",IF(ISERROR(FIND("вич",B109,1)),"ж","м")) -> м | I109: #REF! | J109: #REF! | K109: ЦФО Служба безопасности (2 ур) | O109: 1 | P109: Основное место работы | Q109: =IF(R109="","включаем","не включаем") -> включаем | T109: Май | V109: ТУРБУЛЕНТНОСТЬ-ДОН ООО НПО | W109: 46173
A110: 00538 | B110: Брушкевич Леонид Владимирович | D110: 08.07.2022 | E110: 23.07.1958 | F110: Служба безопасности | G110: Контролер поста контроля | H110: =IF(ISBLANK(B110),"-",IF(ISERROR(FIND("вич",B110,1)),"ж","м")) -> м | I110: #REF! | J110: #REF! | K110: ЦФО Служба безопасности (2 ур) | O110: 1 | P110: Основное место работы | Q110: =IF(R110="","включаем","не включаем") -> включаем | T110: Май | V110: ТУРБУЛЕНТНОСТЬ-ДОН ООО НПО | W110: 46173
A111: 0000000126 | B111: Гасанов Абдулгамид Османович | D111: 02.03.2011 | E111: 05.09.1961 | F111: Служба безопасности | G111: Контролер поста контроля | H111: =IF(ISBLANK(B111),"-",IF(ISERROR(FIND("вич",B111,1)),"ж","м")) -> м | I111: #REF! | J111: #REF! | K111: ЦФО Служба безопасности (2 ур) | O111: 1 | P111: Основное место работы | Q111: =IF(R111="","включаем","не включаем") -> включаем | T111: Май | V111: ТУРБУЛЕНТНОСТЬ-ДОН ООО НПО | W111: 46173
A112: 00511 | B112: Дутов Александр Федорович | D112: 19.04.2022 | E112: 31.12.1961 | F112: Служба безопасности | G112: Контролер поста контроля | H112: =IF(ISBLANK(B112),"-",IF(ISERROR(FIND("вич",B112,1)),"ж","м")) -> м | I112: #REF! | J112: #REF! | K112: ЦФО Служба безопасности (2 ур) | O112: 1 | P112: Основное место работы | Q112: =IF(R112="","включаем","не включаем") -> включаем | T112: Май | V112: ТУРБУЛЕНТНОСТЬ-ДОН ООО НПО | W112: 46173
A113: 00705 | B113: Дьяков Валерий Иванович | D113: 29.08.2023 | E113: 01.05.1967 | F113: Служба безопасности | G113: Контролер поста контроля | H113: =IF(ISBLANK(B113),"-",IF(ISERROR(FIND("вич",B113,1)),"ж","м")) -> м | I113: #REF! | J113: #REF! | K113: ЦФО Служба безопасности (2 ур) | O113: 1 | P113: Основное место работы | Q113: =IF(R113="","включаем","не включаем") -> включаем | T113: Май | V113: ТУРБУЛЕНТНОСТЬ-ДОН ООО НПО | W113: 46173
A114: 0000000125 | B114: Есартия Рамин Гурамович | D114: 02.03.2011 | E114: 25.04.1959 | F114: Служба безопасности | G114: Контролер поста контроля | H114: =IF(ISBLANK(B114),"-",IF(ISERROR(FIND("вич",B114,1)),"ж","м")) -> м | I114: #REF! | J114: #REF! | K114: ЦФО Служба безопасности (2 ур) | O114: 1 | P114: Основное место работы | Q114: =IF(R114="","включаем","не включаем") -> включаем | T114: Май | V114: ТУРБУЛЕНТНОСТЬ-ДОН ООО НПО | W114: 46173
A115: 01094 | B115: Кривенко Грациан Эрикович | D115: 03.03.2026 | E115: 10.12.1965 | F115: Служба безопасности | G115: Контролер поста контроля | H115: =IF(ISBLANK(B115),"-",IF(ISERROR(FIND("вич",B115,1)),"ж","м")) -> м | I115: #REF! | J115: #REF! | K115: ЦФО Служба безопасности (2 ур) | O115: 1 | P115: Основное место работы | Q115: =IF(R115="","включаем","не включаем") -> включаем | T115: Май | V115: ТУРБУЛЕНТНОСТЬ-ДОН ООО НПО | W115: 46173
... A152: 01059 | B152: Кривцова Светлана Николаевна | D152: 21.10.2025 | E152: 26.09.1997 | F152: Отдел продаж эталонного оборудования и услуг | G152: Менеджер по сопровождению | H152: =IF(ISBLANK(B152),"-",IF(ISERROR(FIND("вич",B152,1)),"ж","м")) -> ж | I152: #REF! | J152: #REF! | K152: ЦФО Ком.служба (2 ур) | O152: 1 | P152: Основное место работы | Q152: =IF(R152="","включаем","не включаем") -> включаем | T152: Май | V152: ТУРБУЛЕНТНОСТЬ-ДОН ООО НПО | W152: 46173
A153: 00894 | B153: Малиновская Юлия Владимировна | D153: 18.11.2024 | E153: 28.05.1999 | F153: Отдел продаж эталонного оборудования и услуг | G153: Менеджер по сопровождению | H153: =IF(ISBLANK(B153),"-",IF(ISERROR(FIND("вич",B153,1)),"ж","м")) -> ж | I153: #REF! | J153: #REF! | K153: ЦФО Ком.служба (2 ур) | O153: 1 | P153: Основное место работы | Q153: =IF(R153="","включаем","не включаем") -> не включаем | R153: отпуск по беременности и родам (Декрет) | T153: Май | V153: ТУРБУЛЕНТНОСТЬ-ДОН ООО НПО | W153: 46173
A154: 00895 | B154: Шевякова Анастасия Андреевна | D154: 18.11.2024 | E154: 10.06.1997 | F154: Отдел продаж эталонного оборудования и услуг | G154: Менеджер по сопровождению | H154: =IF(ISBLANK(B154),"-",IF(ISERROR(FIND("вич",B154,1)),"ж","м")) -> ж | I154: #REF! | J154: #REF! | K154: ЦФО Ком.служба (2 ур) | O154: 1 | P154: Основное место работы | Q154: =IF(R154="","включаем","не включаем") -> не включаем | R154: отпуск по беременности и родам (Декрет) | T154: Май | V154: ТУРБУЛЕНТНОСТЬ-ДОН ООО НПО | W154: 46173
A155: 01020 | B155: Прокопчук Лидия Александровна | D155: 17.07.2025 | E155: 16.02.1984 | F155: Отдел продаж эталонного оборудования и услуг | G155: Начальник отдела | H155: =IF(ISBLANK(B155),"-",IF(ISERROR(FIND("вич",B155,1)),"ж","м")) -> ж | I155: #REF! | J155: #REF! | K155: ЦФО Ком.служба (2 ур) | O155: 1 | P155: Основное место работы | Q155: =IF(R155="","включаем","не включаем") -> включаем | T155: Май | V155: ТУРБУЛЕНТНОСТЬ-ДОН ООО НПО | W155: 46173
A156: 00723 | B156: Мулявка Виктория Викторовна | D156: 18.09.2023 | E156: 07.04.1985 | F156: Отдел продаж эталонного оборудования и услуг | G156: Ведущий менеджер | H156: =IF(ISBLANK(B156),"-",IF(ISERROR(FIND("вич",B156,1)),"ж","м")) -> ж | I156: #REF! | J156: #REF! | K156: ЦФО Ком.служба (2 ур) | O156: 1 | P156: Основное место работы | Q156: =IF(R156="","включаем","не включаем") -> включаем | T156: Май | V156: ТУРБУЛЕНТНОСТЬ-ДОН ООО НПО | W156: 46173
...

Sheet Реальные причины увольнения
A1: Реальные причины увольнения
A2: 1. Предложили более высокую позицию, нет карьерного роста в Компании
A3: 1. Недовольство руководством, непосредственным руководителем, общим стилем управления, отношениями в отделе
A4: 1. Другая сфера деятельности, открытие собственного дела и т.п.
A5: 1. Предложили более высокую зарплату на аналогичной должности, неудовлетворенность текущей з/платой
A6: 1. Неудобный график работы
A7: 1. Неудобное расположение, далеко от дома
A8: 1. Плохие условия труда
A9: 1. Состояние здоровья
A10: 1. Учеба/поступление в учебное заведение
A11: 1. Семейные обстоятельства
A12: 1. Переезд офиса/смена адреса
... A29: 3. Уход на пенсию: досрочный/регулярный

Sheet Расшифровка статей увольнения
A1: Расшифровка статей увольнения
A2: п. 1 части 1 ст. 77 ТК РФ | B2: Соглашение сторон
A3: п. 2 части 1 ст. 77 ТК РФ | B3: Истечение срока трудового договора
A4: п. 3 части 1 ст. 77 ТК РФ | B4: Расторжение трудового договора по инициативе работника
A5: п. 5 части 1 ст. 77 ТК РФ | B5: В порядке перевода
A6: п. 6 части 1 ст. 77 ТК РФ | B6: Отказ работника от продолжения работы в связи с изменением подведомственности (подчиненности) организации
A7: п. 6 части 1 ст. 77 ТК РФ | B7: Отказ работника от продолжения работы в связи с реорганизацией организации
A8: п. 6 части 1 ст. 77 ТК РФ | B8: Отказ работника от продолжения работы в связи со сменой собственника имущества организации
A9: п. 7 части 1 ст. 77 ТК РФ | B9: Отказ работника от продолжения работы в связи с изменением определенных сторонами условий трудового договора
A10: п. 8 части 1 ст. 77 ТК РФ | B10: Отсутствие у работодателя работы, необходимой работнику в соответствии с мед. Заключением
A11: п. 9 части 1 ст. 77 ТК РФ | B11: Отказ работника от перевода на работу в другую местность вместе с работодателем
A12: п. 11 части 1 ст. 77 ТК РФ | B12: Нарушение установленных ТК РФ или иным ФЗ правил заключения трудового договора
A13: п. 8 части 1 ст. 77 ТК РФ | B13: Отказ работника от перевода на другую работу, необходимую ему в соответствии с мед. заключением
... A36: ст. 288 ТК РФ | B36: Прием на работу работника, для которого эта работа будет являться основной

Sheet Включаем не включаем
A1: Причина увольнения
A2: Увольнение по собственному желанию | B2: включаем
A3: 1. Предложили более высокую позицию, нет карьерного роста в Компании | B3: включаем
A4: 1. Недовольство руководством, непосредственным руководителем, общим стилем управления, отношениями в отделе | B4: включаем
A5: 1. Другая сфера деятельности, открытие собственного дела и т.п. | B5: включаем
A6: 1. Предложили более высокую зарплату на аналогичной должности, неудовлетворенность текущей з/платой | B6: включаем
A7: 1. Неудобный график работы | B7: включаем
A8: 1. Неудобное расположение, далеко от дома | B8: включаем
A9: 1. Плохие условия труда | B9: включаем
A10: 1. Состояние здоровья | B10: включаем
A11: 1. Учеба/поступление в учебное заведение | B11: включаем
A12: 1. Семейные обстоятельства | B12: включаем
A13: 1. Переезд офиса/смена адреса | B13: включаем
... A32: 3. Уход на пенсию: досрочный/регулярный | B32: не включаем

Sheet Свод по списку
A3: Месяц | B3: (Все)
A4: Включаем \ не включаем в отчет | B4: (несколько элементов)
A5: Причина невключения сотрудника в отчет | B5: (Все)
A7: Количество по полю Юридическое лицо
A8: ЦФО | B8: Подразделение | C8: Итог
A9: ЦФО Амурская легенда (1 ур) | B9: Администрация | C9: 1
B10: Бухгалтерия | C10: 3
B11: ОП Розничная торговая сеть: водный павильон "Западный" | C11: 2
B12: Отдел по работе с клиентами | C12: 1
B13: Отдел продаж | C13: 7
B14: Производственный отдел | C14: 9
B15: Транспортный отдел | C15: 14
A16: ЦФО Амурская легенда (1 ур) Итог | C16: 37
A17: ЦФО Главный метролог (1 ур) | B17: Метрологическая служба | C17: 11
B18: Отдел метрологии и сертификации | C18: 5
B19: Участок ремонта промышленного оборудования | C19: 5
A20: ЦФО Главный метролог (1 ур) Итог | C20: 21
A21: ЦФО Директор НПО (2 ур) | B21: Бухгалтерия | C21: 5
B22: Отдел ценообразования и экономического планирования | C22: 4
B23: Служба управления персоналом | C23: 6
A24: ЦФО Директор НПО (2 ур) Итог | C24: 15
A25: ЦФО КБ (2 ур) | B25: Конструкторское бюро | C25: 10
B26: Конструкторско-технологический отдел | C26: 3
B27: Отдел разработки ПО и АСУ | C27: 2
A28: ЦФО КБ (2 ур) Итог | C28: 15
A29: ЦФО Ком.служба (2 ур) | B29: Отдел внешнеэкономической деятельности | C29: 4
B30: Отдел дилерских продаж | C30: 9
B31: Отдел по продаже БМИ | C31: 4
B32: Отдел по работе с ключевыми клиентами | C32: 5
B33: Отдел по работе с ПАО Газпром | C33: 3
B34: Отдел продаж эталонного оборудования и услуг | C34: 5
B35: Сектор рекламы и PR | C35: 2
B36: Тендерный офис | C36: 4
A37: ЦФО Ком.служба (2 ур) Итог | C37: 36
A38: ЦФО МГС (1 ур) | B38: Азовский СЦ | C38: 3
B39: Батайский СЦ | C39: 2
B40: Вешенский СЦ | C40: 1
B41: Волгодонской СЦ | C41: 2
B42: Зерноградский СЦ | C42: 2
B43: Каменск-Шахтинский СЦ | C43: 3
B44: Миллеровский СЦ | C44: 2
B45: Новочеркасский СЦ | C45: 2
B46: Новошахтинский СЦ | C46: 2
B47: Основное подразделение (Промзона) | C47: 6
B48: Ростов (Нагибина) СЦ | C48: 8
B49: Сальский СЦ | C49: 2
B50: Семикаракорский СЦ | C50: 2
... B52: Шахтинский СЦ | C52: 2
A53: ЦФО МГС (1 ур) Итог | C53: 41
A54: ЦФО Милака (1 ур) | B54: Администрация | C54: 3
B55: Служба безопасности | C55: 4
B56: Служба приема и размещения | C56: 6
B57: Хозяйственная служба | C57: 4
A58: ЦФО Милака (1 ур) Итог | C58: 17
A59: ЦФО Производство №1 (1 ур) | B59: Группа сопровождения продаж и производства | C59: 1
B60: Малярно-слесарный участок | C60: 6
B61: Механический цех | C61: 3
B62: Планово-диспетчерская служба | C62: 3
B63: Производственный цех №1 | C63: 3
B64: Производство №1 | C64: 2
B65: Производство несерийных изделий | C65: 2
B66: Сборочный участок №2 | C66: 7
B67: Сварочный участок | C67: 5
B68: Сектор доработки и улучшения серийной продукции | C68: 5
B69: Сектор постановки на производство и несерийной продукции | C69: 4
B70: Сектор сопровождения продаж | C70: 5
B71: Сектор сопровождения производства и продаж | C71: 6
... B78: Участок ЧПУ и плазмы | C78: 9
A79: ЦФО Производство №1 (1 ур) Итог | C79: 106
A80: ЦФО Производство №2 (1 ур) | B80: Отдел по работе с рекламациями | C80: 3
B81: Производство №2 | C81: 3
B82: Руководство | C82: 1
B83: Складской комплекс | C83: 2
B84: Участок монтажа радиоэлектронной аппаратуры | C84: 1
B85: Участок ремонта гарантийных приборов | C85: 2
B86: Участок ремонта и обслуживания оборудования | C86: 3
B87: Участок сборки счетчиков | C87: 15
B88: Участок СПУ-5 | C88: 2
B89: Участок упаковки | C89: 2
A90: ЦФО Производство №2 (1 ур) Итог | C90: 34
A91: ЦФО Производство БМИ (1 ур) | B91: Цех БМИ | C91: 4
A92: ЦФО Производство БМИ (1 ур) Итог | C92: 4
A93: ЦФО Руководство (2 ур) | B93: Производство №1 | C93: 1
B94: Ревизионная комиссия | C94: 2
B95: Руководство ГК | C95: 1
B96: Руководство конструкторского бюро | C96: 1
B97: Управление делами | C97: 3
B98: Финансовая служба | C98: 2
B99: Юридический отдел | C99: 2
A100: ЦФО Руководство (2 ур) Итог | C100: 12
A101: ЦФО Сервисная служба (1+2 ур) | B101: Отдел технической поддержки | C101: 5
B102: Сервисная служба | C102: 5
A103: ЦФО Сервисная служба (1+2 ур) Итог | C103: 10
A104: ЦФО Служба автоматизации (2 ур) | B104: Отдел внедрения | C104: 1
B105: Отдел информационных технологий | C105: 2
B106: Отдел сопровождения 1С | C106: 3
A107: ЦФО Служба автоматизации (2 ур) Итог | C107: 6
A108: ЦФО Служба безопасности (2 ур) | B108: Служба безопасности | C108: 18
B109: Служба экономической безопасности | C109: 1
A110: ЦФО Служба безопасности (2 ур) Итог | C110: 19
...

Sheet Список уволенных
A1: Выгрузка из 1С | B1: Выгрузка из 1С | C1: Выгрузка из 1С | D1: Выгрузка из 1С | E1: Заполняем вручную, настроен выпадающий список | F1: Выгрузка из 1С | G1: Заполняем вручную, настроен выпадающий список | H1: Заполняем вручную, настроен выпадающий список | I1: Автоматическое заполнение | J1: Заполняем вручную, настроен выпадающий список | K1: Заполняем вручную, настроен выпадающий список | L1: Автоматическое заполнение, если заполнена колонка "К" | M1: Выгрузка из 1С | N1: Заполняем вручную, настроен выпадающий список | O1: Заполняем вручную, настроен выпадающий список | P1: Автоматическое заполнение | Q1: Автоматическое заполнение | R1: Автоматическое заполнение | S1: Выгрузка из 1С | T1: Заполняем вручную, настроен выпадающий список | U1: Заполняем вручную | V1: Заполняем вручную, настроен выпадающий список | W1: Заполняем вручную
A2: Таб. № | B2: ФИО | C2: Подразделение | D2: Должность | E2: Основное место работы/Совместительство | F2: Дата увольнения | G2: Категории персонала | H2: Статья ТК РФ | I2: Расшифровка статьи увольнения | J2: Месяц увольнения | K2: Реальные причины увольнения | L2: включаем \ не включаем | M2: Дата начала работы в ГК | N2: Город, фактическое место работы | O2: Тип договора | P2: Длительность работы в компании | Q2: Увольнение в течении испытательного срока | R2: Пол | S2: Дата рождения | T2: Юридическое лицо | U2: Непосредственный руководитель | V2: ЦФО | W2: ФИО рекрутера
A3: 00482 | B3: Махлин Константин Романович | C3: Руководство (основное) | D3: Директор | E3: Внешнее совместительство | F3: 28.01.2026 | H3: п. 3 части 1 ст. 77 ТК РФ | J3: Январь | K3: 3. Оптимизация структуры Компании | L3: =IF(O3="Постоянный",VLOOKUP(K3,'Включаем не включаем'!$A$1:$B$65536,2,0),"не включаем") -> не включаем | M3: 20.05.2025 | N3: Ростов-на-Дону | O3: постоянный | P3: =DAYS360(M3,F3,TRUE)/30 -> 8.2666667 | Q3: =IF(DAYS360(M3,F3,TRUE)>120,"-","увольнение в течении испытательного срока") -> - | R3: =IF(ISBLANK(B3),"-",IF(ISERROR(FIND("вич",B3,1)),"ж","м")) -> м | S3: 16.02.1978 | T3: АЛМАЗ ООО | U3: Амураль И.Б. | V3: ЦФО Производство №2 (1 ур)
A4: 01000 | B4: Пахомов Александр Борисович | C4: Сектор доработки и улучшения серийной продукции | D4: Инженер-программист 2 категории | E4: Основное место работы | F4: 26.02.2026 | H4: п. 3 части 1 ст. 77 ТК РФ | J4: Февраль | K4: 1. Предложили более высокую зарплату на аналогичной должности, неудовлетворенность текущей з/платой | L4: не включаем | M4: 05.06.2025 | N4: Ростов-на-Дону | O4: постоянный | P4: =DAYS360(M4,F4,TRUE)/30 -> 8.7 | Q4: =IF(DAYS360(M4,F4,TRUE)>120,"-","увольнение в течении испытательного срока") -> - | R4: =IF(ISBLANK(B4),"-",IF(ISERROR(FIND("вич",B4,1)),"ж","м")) -> м | S4: 10.03.1982 | T4: ТУРБУЛЕНТНОСТЬ-ДОН ООО НПО | U4: Асланян | V4: ЦФО Производство №1 (1 ур)
A5: 01078 | B5: Веровенко Юрий Александрович | C5: Сервисная служба | D5: Инженер КИПиА | E5: Основное место работы | F5: 24.02.2026 | H5: п. 3 части 1 ст. 77 ТК РФ | J5: Февраль | K5: 1. Предложили более высокую зарплату на аналогичной должности, неудовлетворенность текущей з/платой | L5: =IF(O5="Постоянный",VLOOKUP(K5,'Включаем не включаем'!$A$1:$B$65536,2,0),"не включаем") -> не включаем | M5: 08.12.2025 | N5: Ростов-на-Дону | O5: постоянный | P5: =DAYS360(M5,F5,TRUE)/30 -> 2.5333333 | Q5: =IF(DAYS360(M5,F5,TRUE)>120,"-","увольнение в течении испытательного срока") -> увольнение в течении испытательного срока | R5: =IF(ISBLANK(B5),"-",IF(ISERROR(FIND("вич",B5,1)),"ж","м")) -> м | S5: 09.12.1998 | T5: ТУРБУЛЕНТНОСТЬ-ДОН ООО НПО | U5: Гайфулин Д.А. | V5: ЦФО Сервисная служба (1+2 ур)
A6: 01071 | B6: Коротун Сергей Леонидович | C6: Служба безопасности | D6: Контролер поста контроля | E6: Основное место работы | F6: 20.02.2026 | H6: п. 3 части 1 ст. 77 ТК РФ | J6: Февраль | K6: 2. Неадекватное поведение, поступки и т.п. | L6: не включаем | M6: 24.11.2025 | N6: Ростов-на-Дону | O6: постоянный | P6: =DAYS360(M6,F6,TRUE)/30 -> 2.8666667 | Q6: =IF(DAYS360(M6,F6,TRUE)>120,"-","увольнение в течении испытательного срока") -> увольнение в течении испытательного срока | R6: =IF(ISBLANK(B6),"-",IF(ISERROR(FIND("вич",B6,1)),"ж","м")) -> м | S6: 25.01.1960 | T6: ТУРБУЛЕНТНОСТЬ-ДОН ООО НПО | U6: Гриппа Г.А. | V6: ЦФО Служба безопасности (2 ур)
A7: 01052 | B7: Чернов Александр Евгеньевич | C7: Коммерческая служба | D7: Коммерческий директор | E7: Основное место работы | F7: 26.01.2026 | H7: п. 3 части 1 ст. 77 ТК РФ | J7: Январь | K7: 1. Предложили более высокую позицию, нет карьерного роста в Компании | L7: не включаем | M7: 13.10.2025 | N7: Ростов-на-Дону | O7: постоянный | P7: =DAYS360(M7,F7,TRUE)/30 -> 3.4333333 | Q7: =IF(DAYS360(M7,F7,TRUE)>120,"-","увольнение в течении испытательного срока") -> увольнение в течении испытательного срока | R7: =IF(ISBLANK(B7),"-",IF(ISERROR(FIND("вич",B7,1)),"ж","м")) -> м | S7: 23.08.1983 | T7: ТУРБУЛЕНТНОСТЬ-ДОН ООО НПО | U7: Донцова А.Е. | V7: ЦФО Ком.служба (2 ур)
A8: 00103 | B8: Кузнецов Сергей Сергеевич | C8: Группа сопровождения продаж и производства | D8: Начальник отдела | E8: Основное место работы | F8: 20.01.2026 | H8: п. 3 части 1 ст. 77 ТК РФ | J8: Январь | K8: 2. Низкие результаты, не справляется с основными обязанностями | L8: не включаем | M8: 03.12.2018 | N8: Ростов-на-Дону | O8: постоянный | P8: =DAYS360(M8,F8,TRUE)/30 -> 85.566667 | Q8: =IF(DAYS360(M8,F8,TRUE)>120,"-","увольнение в течении испытательного срока") -> - | R8: =IF(ISBLANK(B8),"-",IF(ISERROR(FIND("вич",B8,1)),"ж","м")) -> м | S8: 08.10.1982 | T8: ТУРБУЛЕНТНОСТЬ-ДОН ООО НПО | U8: Ермаков И. | V8: ЦФО Производство №1 (1 ур)
A9: 00567 | B9: Хайрулин Михаил Шаукатович | C9: Сектор доработки и улучшения серийной продукции | D9: Инженер-конструктор 1 категории | E9: Основное место работы | F9: 11.02.2026 | H9: п. 3 части 1 ст. 77 ТК РФ | J9: Февраль | K9: 1. Предложили более высокую зарплату на аналогичной должности, неудовлетворенность текущей з/платой | L9: =IF(O9="Постоянный",VLOOKUP(K9,'Включаем не включаем'!$A$1:$B$65536,2,0),"не включаем") -> не включаем | M9: 29.08.2022 | N9: Ростов-на-Дону | O9: постоянный | P9: =DAYS360(M9,F9,TRUE)/30 -> 41.4 | Q9: =IF(DAYS360(M9,F9,TRUE)>120,"-","увольнение в течении испытательного срока") -> - | R9: =IF(ISBLANK(B9),"-",IF(ISERROR(FIND("вич",B9,1)),"ж","м")) -> м | S9: 02.11.1983 | T9: ТУРБУЛЕНТНОСТЬ-ДОН ООО НПО | U9: Емельяненко | V9: ЦФО Производство №1 (1 ур)
A10: 00837 | B10: Мальцев Дмитрий Алексеевич | C10: Экспериментальный производственный цех | D10: Слесарь КИПиА | E10: Основное место работы | F10: 28.01.2026 | H10: п. 3 части 1 ст. 77 ТК РФ | J10: Январь | K10: 1. Другая сфера деятельности, открытие собственного дела и т.п. | L10: =IF(O10="Постоянный",VLOOKUP(K10,'Включаем не включаем'!$A$1:$B$65536,2,0),"не включаем") -> не включаем | M10: 29.07.2024 | N10: Ростов-на-Дону | O10: постоянный | P10: =DAYS360(M10,F10,TRUE)/30 -> 17.966667 | Q10: =IF(DAYS360(M10,F10,TRUE)>120,"-","увольнение в течении испытательного срока") -> - | R10: =IF(ISBLANK(B10),"-",IF(ISERROR(FIND("вич",B10,1)),"ж","м")) -> м | S10: 27.10.2000 | T10: ТУРБУЛЕНТНОСТЬ-ДОН ООО НПО | U10: Зайцев Г.Н. | V10: ЦФО Производство №1 (1 ур)
A11: 00503 | B11: Матофонов Андрей Николаевич | C11: Участок монтажа радиоэлектронной аппаратуры | D11: Монтажник РЭА | E11: Основное место работы | F11: 13.01.2026 | H11: п. 3 части 1 ст. 77 ТК РФ | J11: Январь | K11: 1. Предложили более высокую зарплату на аналогичной должности, неудовлетворенность текущей з/платой | L11: =IF(O11="Постоянный",VLOOKUP(K11,'Включаем не включаем'!$A$1:$B$65536,2,0),"не включаем") -> не включаем | M11: 09.12.2025 | N11: Ростов-на-Дону | O11: постоянный | P11: =DAYS360(M11,F11,TRUE)/30 -> 1.1333333 | Q11: =IF(DAYS360(M11,F11,TRUE)>120,"-","увольнение в течении испытательного срока") -> увольнение в течении испытательного срока | R11: =IF(ISBLANK(B11),"-",IF(ISERROR(FIND("вич",B11,1)),"ж","м")) -> м | S11: 06.06.1984 | T11: АЛМАЗ ООО | U11: Зайцев Г.Н. | V11: ЦФО Производство №2 (1 ур)
A12: 00042 | B12: Сенькина Марина Александровна | C12: Отдел материально-технического обеспечения | D12: Менеджер по сопровождению | E12: Основное место работы | F12: 30.01.2026 | H12: п. 3 части 1 ст. 77 ТК РФ | J12: Январь | K12: 3. Переезд на другое место жительства | L12: =IF(O12="Постоянный",VLOOKUP(K12,'Включаем не включаем'!$A$1:$B$65536,2,0),"не включаем") -> не включаем | M12: 01.11.2025 | N12: Ростов-на-Дону | O12: постоянный | P12: =DAYS360(M12,F12,TRUE)/30 -> 2.9666667 | Q12: =IF(DAYS360(M12,F12,TRUE)>120,"-","увольнение в течении испытательного срока") -> увольнение в течении испытательного срока | R12: =IF(ISBLANK(B12),"-",IF(ISERROR(FIND("вич",B12,1)),"ж","м")) -> ж | S12: 02.09.1979 | T12: ИП Корниенко М.В. | U12: Коваленко А.О. | V12: ЦФО Служба логистики (2 ур)
A13: 00207 | B13: Будиловская Олеся Викторовна | C13: Отдел продаж | D13: Менеджер по работе с клиентами | E13: Основное место работы | F13: 09.02.2026 | H13: п. 3 части 1 ст. 77 ТК РФ | J13: Февраль | K13: 3. Перевод работника с его согласия в другое юридическое лицо в рамках Группы компаний | L13: =IF(O13="Постоянный",VLOOKUP(K13,'Включаем не включаем'!$A$1:$B$65536,2,0),"не включаем") -> не включаем | M13: 10.03.2025 | N13: Ростов-на-Дону | O13: постоянный | P13: =DAYS360(M13,F13,TRUE)/30 -> 10.966667 | Q13: =IF(DAYS360(M13,F13,TRUE)>120,"-","увольнение в течении испытательного срока") -> - | R13: =IF(ISBLANK(B13),"-",IF(ISERROR(FIND("вич",B13,1)),"ж","м")) -> ж | S13: 26.01.1984 | T13: ТД Амурская легенда | U13: Кузнецова Л.Г. | V13: ЦФО Амурская легенда (1 ур)
A14: 00243 | B14: Задорожняя Ольга Владимировна | C14: Производственный отдел | D14: Уборщик помещений | E14: Основное место работы | F14: 09.02.2026 | H14: п. 3 части 1 ст. 77 ТК РФ | J14: Февраль | K14: 1. Плохие условия труда | L14: =IF(O14="Постоянный",VLOOKUP(K14,'Включаем не включаем'!$A$1:$B$65536,2,0),"не включаем") -> не включаем | M14: 04.02.2026 | N14: Ростов-на-Дону | O14: постоянный | P14: =DAYS360(M14,F14,TRUE)/30 -> 0.16666667 | Q14: =IF(DAYS360(M14,F14,TRUE)>120,"-","увольнение в течении испытательного срока") -> увольнение в течении испытательного срока | R14: =IF(ISBLANK(B14),"-",IF(ISERROR(FIND("вич",B14,1)),"ж","м")) -> ж | S14: 22.11.1974 | T14: ТД Амурская легенда | U14: Кузнецова Л.Г. | V14: ЦФО Амурская легенда (1 ур)
A15: 00214 | B15: Адекола Фейт Адейеми | C15: Производственный отдел | D15: Упаковщик | E15: Основное место работы | F15: 02.02.2026 | H15: п. 3 части 1 ст. 77 ТК РФ | J15: Февраль | K15: 3. Переезд на другое место жительства | L15: =IF(O15="Постоянный",VLOOKUP(K15,'Включаем не включаем'!$A$1:$B$65536,2,0),"не включаем") -> не включаем | M15: 02.04.2025 | N15: Ростов-на-Дону | O15: постоянный | P15: =DAYS360(M15,F15,TRUE)/30 -> 10 | Q15: =IF(DAYS360(M15,F15,TRUE)>120,"-","увольнение в течении испытательного срока") -> - | R15: =IF(ISBLANK(B15),"-",IF(ISERROR(FIND("вич",B15,1)),"ж","м")) -> ж | S15: 27.06.1997 | T15: ТД Амурская легенда | U15: Кузнецова Л.Г. | V15: ЦФО Амурская легенда (1 ур)
A16: 00925 | B16: Литвинов Антон Викторович | C16: Склад БМИ | D16: Начальник склада | E16: Основное место работы | F16: 20.02.2026 | H16: п. 3 части 1 ст. 77 ТК РФ | J16: Февраль | K16: 1. Семейные обстоятельства | L16: =IF(O16="Постоянный",VLOOKUP(K16,'Включаем не включаем'!$A$1:$B$65536,2,0),"не включаем") -> не включаем | M16: 06.02.2025 | N16: Ростов-на-Дону | O16: постоянный | P16: =DAYS360(M16,F16,TRUE)/30 -> 12.466667 | Q16: =IF(DAYS360(M16,F16,TRUE)>120,"-","увольнение в течении испытательного срока") -> - | R16: =IF(ISBLANK(B16),"-",IF(ISERROR(FIND("вич",B16,1)),"ж","м")) -> м | S16: 14.08.1990 | T16: ТУРБУЛЕНТНОСТЬ-ДОН ООО НПО | U16: Кургин Ф.В. | V16: ЦФО Служба логистики (2 ур)
A17: 00481 | B17: Агарков Алексей Валерьевич | C17: Складской комплекс | D17: Кладовщик | E17: Основное место работы | F17: 16.02.2026 | H17: п. 3 части 1 ст. 77 ТК РФ | J17: Февраль | K17: 1. Предложили более высокую зарплату на аналогичной должности, неудовлетворенность текущей з/платой | L17: =IF(O17="Постоянный",VLOOKUP(K17,'Включаем не включаем'!$A$1:$B$65536,2,0),"не включаем") -> не включаем | M17: 01.02.2022 | N17: Ростов-на-Дону | O17: постоянный | P17: =DAYS360(M17,F17,TRUE)/30 -> 48.5 | Q17: =IF(DAYS360(M17,F17,TRUE)>120,"-","увольнение в течении испытательного срока") -> - | R17: =IF(ISBLANK(B17),"-",IF(ISERROR(FIND("вич",B17,1)),"ж","м")) -> м | S17: 29.09.1986 | T17: ТУРБУЛЕНТНОСТЬ-ДОН ООО НПО | U17: Кургин Ф.В. | V17: ЦФО Служба логистики (2 ур)
A18: 00828 | B18: Бондарь Сергей Викторович | C18: Складской комплекс | D18: Кладовщик | E18: Основное место работы | F18: 06.02.2026 | H18: п. 3 части 1 ст. 77 ТК РФ | J18: Февраль | K18: 1. Недовольство руководством, непосредственным руководителем, общим стилем управления, отношениями в отделе | L18: =IF(O18="Постоянный",VLOOKUP(K18,'Включаем не включаем'!$A$1:$B$65536,2,0),"не включаем") -> не включаем | M18: 27.06.2024 | N18: Ростов-на-Дону | O18: постоянный | P18: =DAYS360(M18,F18,TRUE)/30 -> 19.3 | Q18: =IF(DAYS360(M18,F18,TRUE)>120,"-","увольнение в течении испытательного срока") -> - | R18: =IF(ISBLANK(B18),"-",IF(ISERROR(FIND("вич",B18,1)),"ж","м")) -> м | S18: 22.01.1985 | T18: ТУРБУЛЕНТНОСТЬ-ДОН ООО НПО | U18: Кургин Ф.В. | V18: ЦФО Служба логистики (2 ур)
A19: 00120 | B19: Кондаков Михаил Михайлович | C19: Азовский СЦ | D19: Техник | E19: Основное место работы | F19: 27.01.2026 | H19: п. 3 части 1 ст. 77 ТК РФ | J19: Январь | K19: 3. Оптимизация структуры Компании | L19: =IF(O19="Постоянный",VLOOKUP(K19,'Включаем не включаем'!$A$1:$B$65536,2,0),"не включаем") -> не включаем | M19: 08.04.2024 | N19: Ростов-на-Дону | O19: постоянный | P19: =DAYS360(M19,F19,TRUE)/30 -> 21.633333 | Q19: =IF(DAYS360(M19,F19,TRUE)>120,"-","увольнение в течении испытательного срока") -> - | R19: =IF(ISBLANK(B19),"-",IF(ISERROR(FIND("вич",B19,1)),"ж","м")) -> м | S19: 03.06.1994 | T19: Метрогазсервис ООО | U19: Махлин К.Р. | V19: ЦФО МГС (1 ур)
A20: 00036 | B20: Самарина Светлана Федоровна | C20: Таганрогский СЦ | D20: Кассир-приемщик | E20: Основное место работы | F20: 04.02.2026 | H20: п. 3 части 1 ст. 77 ТК РФ | J20: Февраль | K20: 1. Недовольство руководством, непосредственным руководителем, общим стилем управления, отношениями в отделе | L20: =IF(O20="Постоянный",VLOOKUP(K20,'Включаем не включаем'!$A$1:$B$65536,2,0),"не включаем") -> не включаем | M20: 06.11.2018 | N20: Ростов-на-Дону | O20: постоянный | P20: =DAYS360(M20,F20,TRUE)/30 -> 86.933333 | Q20: =IF(DAYS360(M20,F20,TRUE)>120,"-","увольнение в течении испытательного срока") -> - | R20: =IF(ISBLANK(B20),"-",IF(ISERROR(FIND("вич",B20,1)),"ж","м")) -> ж | S20: 23.12.1970 | T20: Метрогазсервис ООО | U20: Махлин К.Р. | V20: ЦФО МГС (1 ур)
... A24: 00505 | B24: Боброва Оксана Александровна | C24: Участок сборки UFG-H | D24: Сборщик | E24: Основное место работы | F24: 27.02.2026 | H24: п. 3 части 1 ст. 77 ТК РФ | J24: Февраль | K24: 2. Низкие результаты, не справляется с основными обязанностями | L24: =IF(O24="Постоянный",VLOOKUP(K24,'Включаем не включаем'!$A$1:$B$65536,2,0),"не включаем") -> не включаем | M24: 17.12.2025 | N24: Ростов-на-Дону | O24: постоянный | P24: =DAYS360(M24,F24,TRUE)/30 -> 2.3333333 | Q24: =IF(DAYS360(M24,F24,TRUE)>120,"-","увольнение в течении испытательного срока") -> увольнение в течении испытательного срока | R24: =IF(ISBLANK(B24),"-",IF(ISERROR(FIND("вич",B24,1)),"ж","м")) -> ж | S24: 06.02.1981 | T24: АЛМАЗ ООО | U24: Сафронов И.А. | V24: ЦФО Производство №2 (1 ур)
A25: 00010 | B25: Кучер Роман Витальевич | C25: Транспортный отдел | D25: Водитель автомобиля | E25: Основное место работы | F25: 22.01.2026 | H25: п. 3 части 1 ст. 77 ТК РФ | J25: Январь | K25: 1. Предложили более высокую зарплату на аналогичной должности, неудовлетворенность текущей з/платой | L25: не включаем | M25: 02.09.2025 | N25: Ростов-на-Дону | O25: постоянный | P25: =DAYS360(M25,F25,TRUE)/30 -> 4.6666667 | Q25: =IF(DAYS360(M25,F25,TRUE)>120,"-","увольнение в течении испытательного срока") -> - | R25: =IF(ISBLANK(B25),"-",IF(ISERROR(FIND("вич",B25,1)),"ж","м")) -> м | S25: 12.11.1992 | T25: ТД Амурская легенда | U25: Сефиханов Р.И. | V25: ЦФО Амурская легенда (1 ур)
A26: 00239 | B26: Игнатенко Никита Александрович | C26: Транспортный отдел | D26: Водитель автомобиля | E26: Основное место работы | F26: 13.01.2026 | H26: п. 3 части 1 ст. 77 ТК РФ | J26: Январь | K26: 1. Предложили более высокую зарплату на аналогичной должности, неудовлетворенность текущей з/платой | L26: не включаем | M26: 15.10.2025 | N26: Ростов-на-Дону | O26: постоянный | P26: =DAYS360(M26,F26,TRUE)/30 -> 2.9333333 | Q26: =IF(DAYS360(M26,F26,TRUE)>120,"-","увольнение в течении испытательного срока") -> увольнение в течении испытательного срока | R26: =IF(ISBLANK(B26),"-",IF(ISERROR(FIND("вич",B26,1)),"ж","м")) -> м | S26: 08.01.1995 | T26: ТД Амурская легенда | U26: Сефиханов Р.И. | V26: ЦФО Амурская легенда (1 ур)
A27: 01056 | B27: Ставицкий Николай Николаевич | C27: Транспортная служба | D27: Водитель автомобиля | E27: Основное место работы | F27: 10.02.2026 | H27: п. 3 части 1 ст. 77 ТК РФ | J27: Февраль | K27: 2. Пьянство | L27: не включаем | M27: 16.10.2025 | N27: Ростов-на-Дону | O27: постоянный | P27: =DAYS360(M27,F27,TRUE)/30 -> 3.8 | Q27: =IF(DAYS360(M27,F27,TRUE)>120,"-","увольнение в течении испытательного срока") -> увольнение в течении испытательного срока | R27: =IF(ISBLANK(B27),"-",IF(ISERROR(FIND("вич",B27,1)),"ж","м")) -> м | S27: 18.10.1976 | T27: ТУРБУЛЕНТНОСТЬ-ДОН ООО НПО | U27: Сефиханов Р.И. | V27: ЦФО Служба логистики (2 ур)
A28: 00683 | B28: Иликаев Алексей Валерьевич | C28: Лаборатория неразрушающего контроля | D28: Специалист по неразрушающему контролю | E28: Основное место работы | F28: 27.02.2026 | H28: п. 3 части 1 ст. 77 ТК РФ | J28: Февраль | K28: 1. Предложили более высокую зарплату на аналогичной должности, неудовлетворенность текущей з/платой | L28: =IF(O28="Постоянный",VLOOKUP(K28,'Включаем не включаем'!$A$1:$B$65536,2,0),"не включаем") -> не включаем | M28: 17.07.2023 | N28: Ростов-на-Дону | O28: постоянный | P28: =DAYS360(M28,F28,TRUE)/30 -> 31.333333 | Q28: =IF(DAYS360(M28,F28,TRUE)>120,"-","увольнение в течении испытательного срока") -> - | R28: =IF(ISBLANK(B28),"-",IF(ISERROR(FIND("вич",B28,1)),"ж","м")) -> м | S28: 24.02.1996 | T28: ТУРБУЛЕНТНОСТЬ-ДОН ООО НПО | U28: Сливков П.Е. | V28: ЦФО Служба технического директора (2 ур)
A29: 01022 | B29: Беспалов Кирилл Алексеевич | C29: Отдел внешнеэкономической деятельности | D29: Ведущий менеджер | E29: Основное место работы | F29: 13.02.2026 | H29: п. 3 части 1 ст. 77 ТК РФ | J29: Февраль | K29: 1. Другая сфера деятельности, открытие собственного дела и т.п. | L29: =IF(O29="Постоянный",VLOOKUP(K29,'Включаем не включаем'!$A$1:$B$65536,2,0),"не включаем") -> не включаем | M29: 23.07.2025 | N29: Ростов-на-Дону | O29: постоянный | P29: =DAYS360(M29,F29,TRUE)/30 -> 6.6666667 | Q29: =IF(DAYS360(M29,F29,TRUE)>120,"-","увольнение в течении испытательного срока") -> - | R29: =IF(ISBLANK(B29),"-",IF(ISERROR(FIND("вич",B29,1)),"ж","м")) -> м | S29: 24.04.2004 | T29: ТУРБУЛЕНТНОСТЬ-ДОН ООО НПО | U29: Титова Я.В. | V29: ЦФО Ком.служба (2 ур)
A30: 00788 | B30: Елагина Мария Геннадьевна | C30: Сектор промышленной безопасности | D30: Специалист по промышленной безопасности | E30: Основное место работы | F30: 06.02.2026 | H30: п. 3 части 1 ст. 77 ТК РФ | J30: Февраль | K30: 1. Недовольство руководством, непосредственным руководителем, общим стилем управления, отношениями в отделе | L30: =IF(O30="Постоянный",VLOOKUP(K30,'Включаем не включаем'!$A$1:$B$65536,2,0),"не включаем") -> не включаем | M30: 25.03.2024 | N30: Ростов-на-Дону | O30: постоянный | P30: =DAYS360(M30,F30,TRUE)/30 -> 22.366667 | Q30: =IF(DAYS360(M30,F30,TRUE)>120,"-","увольнение в течении испытательного срока") -> - | R30: =IF(ISBLANK(B30),"-",IF(ISERROR(FIND("вич",B30,1)),"ж","м")) -> ж | S30: 16.06.1999 | T30: ТУРБУЛЕНТНОСТЬ-ДОН ООО НПО | U30: Улановский К.В. | V30: ЦФО Служба технического директора (2 ур)
A31: 00809 | B31: Федоров Юрий Робертович | C31: Сектор разработки технических решений | D31: Ведущий инженер-проектировщик АСУТП | E31: Основное место работы | F31: 03.02.2026 | H31: п. 3 части 1 ст. 77 ТК РФ | J31: Февраль | K31: 1. Предложили более высокую зарплату на аналогичной должности, неудовлетворенность текущей з/платой | L31: =IF(O31="Постоянный",VLOOKUP(K31,'Включаем не включаем'!$A$1:$B$65536,2,0),"не включаем") -> не включаем | M31: 21.05.2024 | N31: Ростов-на-Дону | O31: постоянный | P31: =DAYS360(M31,F31,TRUE)/30 -> 20.4 | Q31: =IF(DAYS360(M31,F31,TRUE)>120,"-","увольнение в течении испытательного срока") -> - | R31: =IF(ISBLANK(B31),"-",IF(ISERROR(FIND("вич",B31,1)),"ж","м")) -> м | S31: 29.01.1973 | T31: ТУРБУЛЕНТНОСТЬ-ДОН ООО НПО | U31: Улановский К.В. | V31: ЦФО Служба технического директора (2 ур)
A32: 00917 | B32: Никитаев Алексей Вячеславович | C32: Сектор по внедрению искусственного интеллекта | D32: Промт-инженер 2 категории | E32: Основное место работы | F32: 03.02.2026 | H32: п. 3 части 1 ст. 77 ТК РФ | J32: Февраль | K32: 1. Предложили более высокую зарплату на аналогичной должности, неудовлетворенность текущей з/платой | L32: не включаем | M32: 29.01.2025 | N32: Ростов-на-Дону | O32: постоянный | P32: =DAYS360(M32,F32,TRUE)/30 -> 12.133333 | Q32: =IF(DAYS360(M32,F32,TRUE)>120,"-","увольнение в течении испытательного срока") -> - | R32: =IF(ISBLANK(B32),"-",IF(ISERROR(FIND("вич",B32,1)),"ж","м")) -> м | S32: 15.04.1979 | T32: ТУРБУЛЕНТНОСТЬ-ДОН ООО НПО | U32: Ясыров Б. | V32: ЦФО Служба развития (2 ур)
A33: 00838 | B33: Белан Дмитрий Александрович | C33: Участок ЧПУ и плазмы | D33: Оператор станков с программным управлением | E33: Основное место работы | F33: 31.03.2026 | H33: п. 3 части 1 ст. 77 ТК РФ | J33: Март | K33: 2. Неадекватное поведение, поступки и т.п. | L33: не включаем | M33: 29.07.2024 | N33: Ростов-на-Дону | O33: постоянный | P33: =DAYS360(M33,F33,TRUE)/30 -> 20.033333 | Q33: =IF(DAYS360(M33,F33,TRUE)>120,"-","увольнение в течении испытательного срока") -> - | R33: =IF(ISBLANK(B33),"-",IF(ISERROR(FIND("вич",B33,1)),"ж","м")) -> м | S33: 05.05.1985 | T33: ТУРБУЛЕНТНОСТЬ-ДОН ООО НПО | U33: Князев Д. | V33: ЦФО Производство №1 (1 ур)
A34: 00824 | B34: Ткаченко Людмила Викторовна | C34: Отдел ценообразования и экономического планирования | D34: Начальник отдела | E34: Основное место работы | F34: 26.03.2026 | H34: п. 3 части 1 ст. 77 ТК РФ | J34: Март | K34: 2. Низкие результаты, не справляется с основными обязанностями | L34: не включаем | M34: 24.06.2024 | N34: Ростов-на-Дону | O34: постоянный | P34: =DAYS360(M34,F34,TRUE)/30 -> 21.066667 | Q34: =IF(DAYS360(M34,F34,TRUE)>120,"-","увольнение в течении испытательного срока") -> - | R34: =IF(ISBLANK(B34),"-",IF(ISERROR(FIND("вич",B34,1)),"ж","м")) -> ж | S34: 28.05.1977 | T34: ТУРБУЛЕНТНОСТЬ-ДОН ООО НПО | U34: Донцова А.Е. | V34: ЦФО Директор НПО (2 ур)
A35: 00682 | B35: Бабенкова Ирина Сергеевна | C35: Сектор обучения и развития | D35: Ведущий разработчик электронных курсов | E35: Основное место работы | F35: 24.03.2026 | H35: п. 3 части 1 ст. 77 ТК РФ | J35: Март | K35: 1. Неудобное расположение, далеко от дома | L35: =IF(O35="Постоянный",VLOOKUP(K35,'Включаем не включаем'!$A$1:$B$65536,2,0),"не включаем") -> не включаем | M35: 14.07.2023 | N35: Ростов-на-Дону | O35: постоянный | P35: =DAYS360(M35,F35,TRUE)/30 -> 32.333333 | Q35: =IF(DAYS360(M35,F35,TRUE)>120,"-","увольнение в течении испытательного срока") -> - | R35: =IF(ISBLANK(B35),"-",IF(ISERROR(FIND("вич",B35,1)),"ж","м")) -> ж | S35: 13.06.1987 | T35: ТУРБУЛЕНТНОСТЬ-ДОН ООО НПО | U35: Соломичева С.В. | V35: ЦФО Служба развития (2 ур)
A36: 01038 | B36: Газизов Денис Андреевич | C36: Метрологическая служба | D36: Инженер-метролог | E36: Основное место работы | F36: 23.03.2026 | H36: п. 3 части 1 ст. 77 ТК РФ | J36: Март | K36: 2. Низкие результаты, не справляется с основными обязанностями | L36: не включаем | M36: 01.09.2025 | N36: Ростов-на-Дону | O36: постоянный | P36: =DAYS360(M36,F36,TRUE)/30 -> 6.7333333 | Q36: =IF(DAYS360(M36,F36,TRUE)>120,"-","увольнение в течении испытательного срока") -> - | R36: =IF(ISBLANK(B36),"-",IF(ISERROR(FIND("вич",B36,1)),"ж","м")) -> м | S36: 26.06.1996 | T36: ТУРБУЛЕНТНОСТЬ-ДОН ООО НПО | U36: Хозуян И.В. | V36: ЦФО Главный метролог (1 ур)
A37: 00875 | B37: Шинкаренко Евгений Андреевич | C37: Производственный цех №1 | D37: Мастер участка | E37: Основное место работы | F37: 23.03.2026 | H37: п. 3 части 1 ст. 77 ТК РФ | J37: Март | K37: 2. Низкие результаты, не справляется с основными обязанностями | L37: не включаем | M37: 02.10.2024 | N37: Ростов-на-Дону | O37: постоянный | P37: =DAYS360(M37,F37,TRUE)/30 -> 17.7 | Q37: =IF(DAYS360(M37,F37,TRUE)>120,"-","увольнение в течении испытательного срока") -> - | R37: =IF(ISBLANK(B37),"-",IF(ISERROR(FIND("вич",B37,1)),"ж","м")) -> м | S37: 18.10.1989 | T37: ТУРБУЛЕНТНОСТЬ-ДОН ООО НПО | U37: Макеев А.С. | V37: ЦФО Производство №1 (1 ур)
A38: 00415 | B38: Гриппа Георгий Александрович | C38: Служба безопасности | D38: Начальник службы безопасности | E38: Основное место работы | F38: 23.03.2026 | H38: п. 3 части 1 ст. 77 ТК РФ | J38: Март | K38: 2. Низкие результаты, не справляется с основными обязанностями | L38: =IF(O38="Постоянный",VLOOKUP(K38,'Включаем не включаем'!$A$1:$B$65536,2,0),"не включаем") -> не включаем | M38: 28.04.2021 | N38: Ростов-на-Дону | O38: постоянный | P38: =DAYS360(M38,F38,TRUE)/30 -> 58.833333 | Q38: =IF(DAYS360(M38,F38,TRUE)>120,"-","увольнение в течении испытательного срока") -> - | R38: =IF(ISBLANK(B38),"-",IF(ISERROR(FIND("вич",B38,1)),"ж","м")) -> м | S38: 03.08.1984 | T38: ТУРБУЛЕНТНОСТЬ-ДОН ООО НПО | U38: Свистун С.Н. | V38: ЦФО Служба безопасности (2 ур)
A39: 00886 | B39: Камышанова Мария Витальевна | C39: Служба управления персоналом | D39: Менеджер по персоналу | E39: Основное место работы | F39: 20.03.2026 | H39: п. 3 части 1 ст. 77 ТК РФ | J39: Март | K39: 1. Семейные обстоятельства | L39: не включаем | M39: 01.11.2024 | N39: Ростов-на-Дону | O39: постоянный | P39: =DAYS360(M39,F39,TRUE)/30 -> 16.633333 | Q39: =IF(DAYS360(M39,F39,TRUE)>120,"-","увольнение в течении испытательного срока") -> - | R39: =IF(ISBLANK(B39),"-",IF(ISERROR(FIND("вич",B39,1)),"ж","м")) -> ж | S39: 16.09.1998 | T39: ТУРБУЛЕНТНОСТЬ-ДОН ООО НПО | U39: Ворончихина Е.Н. | V39: ЦФО Директор НПО (2 ур)
A40: 01040 | B40: Савицкий Евгений Эдуардович | C40: Участок монтажа электронных плат | D40: Наладчик линии автоматической пайки | E40: Основное место работы | F40: 20.03.2026 | H40: п. 3 части 1 ст. 77 ТК РФ | J40: Март | K40: 1. Другая сфера деятельности, открытие собственного дела и т.п. | L40: =IF(O40="Постоянный",VLOOKUP(K40,'Включаем не включаем'!$A$1:$B$65536,2,0),"не включаем") -> не включаем | M40: 10.09.2025 | N40: Ростов-на-Дону | O40: постоянный | P40: =DAYS360(M40,F40,TRUE)/30 -> 6.3333333 | Q40: =IF(DAYS360(M40,F40,TRUE)>120,"-","увольнение в течении испытательного срока") -> - | R40: =IF(ISBLANK(B40),"-",IF(ISERROR(FIND("вич",B40,1)),"ж","м")) -> м | S40: 05.09.2000 | T40: ТУРБУЛЕНТНОСТЬ-ДОН ООО НПО | U40: Клименко Е. | V40: ЦФО Производство №1 (1 ур)
A41: 00548 | B41: Мирзоян Кристина Владимировна | C41: Конструкторское бюро | D41: Менеджер по управлению проектами | E41: Основное место работы | F41: 17.03.2026 | H41: п. 3 части 1 ст. 77 ТК РФ | J41: Март | K41: 1. Предложили более высокую зарплату на аналогичной должности, неудовлетворенность текущей з/платой | L41: =IF(O41="Постоянный",VLOOKUP(K41,'Включаем не включаем'!$A$1:$B$65536,2,0),"не включаем") -> не включаем | M41: 01.08.2022 | N41: Ростов-на-Дону | O41: постоянный | P41: =DAYS360(M41,F41,TRUE)/30 -> 43.533333 | Q41: =IF(DAYS360(M41,F41,TRUE)>120,"-","увольнение в течении испытательного срока") -> - | R41: =IF(ISBLANK(B41),"-",IF(ISERROR(FIND("вич",B41,1)),"ж","м")) -> ж | S41: 20.12.1991 | T41: ТУРБУЛЕНТНОСТЬ-ДОН ООО НПО | U41: Гончаров С.Д. | V41: ЦФО КБ (2 ур)
A42: 01018 | B42: Морозова Елена Юрьевна | C42: Управление делами | D42: Архивариус | E42: Основное место работы | F42: 16.03.2026 | H42: п. 3 части 1 ст. 77 ТК РФ | J42: Март | K42: 1. Недовольство руководством, непосредственным руководителем, общим стилем управления, отношениями в отделе | L42: включаем | M42: 10.07.2025 | N42: Ростов-на-Дону | O42: постоянный | P42: =DAYS360(M42,F42,TRUE)/30 -> 8.2 | Q42: =IF(DAYS360(M42,F42,TRUE)>120,"-","увольнение в течении испытательного срока") -> - | R42: =IF(ISBLANK(B42),"-",IF(ISERROR(FIND("вич",B42,1)),"ж","м")) -> ж | S42: 14.03.1978 | T42: ТУРБУЛЕНТНОСТЬ-ДОН ООО НПО | U42: Тищенко М.Н. | V42: ЦФО Руководство (2 ур)
A43: 01051 | B43: Харыбин Александр Викторович | C43: Конструкторское бюро | D43: Заместитель главного конструктора по проектной деятельности | E43: Основное место работы | F43: 13.03.2026 | H43: п. 3 части 1 ст. 77 ТК РФ | J43: Март | K43: 1. Недовольство руководством, непосредственным руководителем, общим стилем управления, отношениями в отделе | L43: не включаем | M43: 09.10.2025 | N43: Ростов-на-Дону | O43: постоянный | P43: =DAYS360(M43,F43,TRUE)/30 -> 5.1333333 | Q43: =IF(DAYS360(M43,F43,TRUE)>120,"-","увольнение в течении испытательного срока") -> - | R43: =IF(ISBLANK(B43),"-",IF(ISERROR(FIND("вич",B43,1)),"ж","м")) -> м | S43: 26.07.1981 | T43: ТУРБУЛЕНТНОСТЬ-ДОН ООО НПО | U43: Гончаров С.Д. | V43: ЦФО КБ (2 ур)
A44: 00991 | B44: Булатова Татьяна Ивановна | C44: Административно-хозяйственный отдел | D44: Уборщик помещений | E44: Основное место работы | F44: 11.03.2026 | H44: п. 3 части 1 ст. 77 ТК РФ | J44: Март | K44: 3. Переезд на другое место жительства | L44: =IF(O44="Постоянный",VLOOKUP(K44,'Включаем не включаем'!$A$1:$B$65536,2,0),"не включаем") -> не включаем | M44: 22.05.2025 | N44: Ростов-на-Дону | O44: постоянный | P44: =DAYS360(M44,F44,TRUE)/30 -> 9.6333333 | Q44: =IF(DAYS360(M44,F44,TRUE)>120,"-","увольнение в течении испытательного срока") -> - | R44: =IF(ISBLANK(B44),"-",IF(ISERROR(FIND("вич",B44,1)),"ж","м")) -> ж | S44: 04.05.1959 | T44: ТУРБУЛЕНТНОСТЬ-ДОН ООО НПО | U44: Улановский К.В. | V44: ЦФО Служба технического директора (2 ур)
A45: 00121 | B45: Сапелкин Александр Николаевич | C45: Основное подразделение (Промзона) | D45: Менеджер по продаже промышленного оборудования | E45: Основное место работы | F45: 06.03.2026 | H45: п. 3 части 1 ст. 77 ТК РФ | J45: Март | K45: 2. Низкие результаты, не справляется с основными обязанностями | L45: включаем | M45: 22.04.2024 | N45: Ростов-на-Дону | O45: постоянный | P45: =DAYS360(M45,F45,TRUE)/30 -> 22.466667 | Q45: =IF(DAYS360(M45,F45,TRUE)>120,"-","увольнение в течении испытательного срока") -> - | R45: =IF(ISBLANK(B45),"-",IF(ISERROR(FIND("вич",B45,1)),"ж","м")) -> м | S45: 01.07.1978 | T45: Метрогазсервис ООО | U45: Махлин К.Р. | V45: ЦФО МГС (1 ур)
A46: 00500 | B46: Макарова Людмила Игоревна | C46: Участок сборки счетчиков | D46: Сборщик | E46: Основное место работы | F46: 05.03.2026 | H46: п. 3 части 1 ст. 77 ТК РФ | J46: Март | K46: 3. Перевод работника с его согласия в другое юридическое лицо в рамках Группы компаний | L46: =IF(O46="Постоянный",VLOOKUP(K46,'Включаем не включаем'!$A$1:$B$65536,2,0),"не включаем") -> не включаем | M46: 27.10.2025 | N46: Ростов-на-Дону | O46: постоянный | P46: =DAYS360(M46,F46,TRUE)/30 -> 4.2666667 | Q46: =IF(DAYS360(M46,F46,TRUE)>120,"-","увольнение в течении испытательного срока") -> - | R46: =IF(ISBLANK(B46),"-",IF(ISERROR(FIND("вич",B46,1)),"ж","м")) -> ж | S46: 17.03.1998 | T46: АЛМАЗ ООО | U46: Сафронов И.А. | V46: ЦФО Производство №2 (1 ур)
A47: 00219 | B47: Бордоносенко Ольга Андреевна | C47: Отдел продаж | D47: Менеджер по сопровождению клиентов | E47: Основное место работы | F47: 27.03.2026 | H47: п. 3 части 1 ст. 77 ТК РФ | J47: Март | K47: 1. Предложили более высокую зарплату на аналогичной должности, неудовлетворенность текущей з/платой | L47: =IF(O47="Постоянный",VLOOKUP(K47,'Включаем не включаем'!$A$1:$B$65536,2,0),"не включаем") -> не включаем | M47: 05.05.2025 | N47: Ростов-на-Дону | O47: постоянный | P47: =DAYS360(M47,F47,TRUE)/30 -> 10.733333 | Q47: =IF(DAYS360(M47,F47,TRUE)>120,"-","увольнение в течении испытательного срока") -> - | R47: =IF(ISBLANK(B47),"-",IF(ISERROR(FIND("вич",B47,1)),"ж","м")) -> ж | S47: 27.02.2004 | T47: ТД Амурская легенда | U47: Кузнецова Л.Г. | V47: ЦФО Амурская легенда (1 ур)
A48: 00011 | B48: Горлачев Егор Николаевич | C48: Транспортный отдел | D48: Водитель автомобиля | E48: Основное место работы | F48: 27.03.2026 | H48: п. 3 части 1 ст. 77 ТК РФ | J48: Март | K48: 1. Другая сфера деятельности, открытие собственного дела и т.п. | L48: =IF(O48="Постоянный",VLOOKUP(K48,'Включаем не включаем'!$A$1:$B$65536,2,0),"не включаем") -> не включаем | M48: 09.02.2026 | N48: Ростов-на-Дону | O48: временный | P48: =DAYS360(M48,F48,TRUE)/30 -> 1.6 | Q48: =IF(DAYS360(M48,F48,TRUE)>120,"-","увольнение в течении испытательного срока") -> увольнение в течении испытательного срока | R48: =IF(ISBLANK(B48),"-",IF(ISERROR(FIND("вич",B48,1)),"ж","м")) -> м | S48: 14.01.2001 | T48: ТД Амурская легенда | U48: Кузнецова Л.Г. | V48: ЦФО Амурская легенда (1 ур)
A49: 00161 | B49: Зеленко Дмитрий Анатольевич | C49: Транспортный отдел | D49: Менеджер по логистике | E49: Основное место работы | F49: 18.03.2026 | H49: п. 3 части 1 ст. 77 ТК РФ | J49: Март | K49: 1. Плохие условия труда | L49: =IF(O49="Постоянный",VLOOKUP(K49,'Включаем не включаем'!$A$1:$B$65536,2,0),"не включаем") -> не включаем | M49: 28.05.2024 | N49: Ростов-на-Дону | O49: постоянный | P49: =DAYS360(M49,F49,TRUE)/30 -> 21.666667 | Q49: =IF(DAYS360(M49,F49,TRUE)>120,"-","увольнение в течении испытательного срока") -> - | R49: =IF(ISBLANK(B49),"-",IF(ISERROR(FIND("вич",B49,1)),"ж","м")) -> м | S49: 16.05.1995 | T49: ТД Амурская легенда | U49: Кузнецова Л.Г. | V49: ЦФО Амурская легенда (1 ур)
A50: 00104 | B50: Корниенко Дмитрий Сергеевич | C50: Участок ремонта гарантийных приборов | D50: Бригадир участка | E50: Основное место работы | F50: 27.04.2026 | H50: п. 3 части 1 ст. 77 ТК РФ | J50: Апрель | K50: 2. Низкие результаты, не справляется с основными обязанностями | L50: не включаем | M50: 14.08.2018 | N50: Ростов-на-Дону | O50: постоянный | P50: =DAYS360(M50,F50,TRUE)/30 -> 92.433333 | Q50: =IF(DAYS360(M50,F50,TRUE)>120,"-","увольнение в течении испытательного срока") -> - | R50: =IF(ISBLANK(B50),"-",IF(ISERROR(FIND("вич",B50,1)),"ж","м")) -> м | S50: 25.10.1991 | T50: АЛМАЗ ООО | U50: Сафронов И.А. | V50: ЦФО Производство №2 (1 ур)
A51: 00479 | B51: Ткаченко Николай Николаевич | C51: Участок сборки счетчиков | D51: Сборщик | E51: Основное место работы | F51: 24.04.2026 | H51: п. 3 части 1 ст. 77 ТК РФ | J51: Апрель | K51: 1. Другая сфера деятельности, открытие собственного дела и т.п. | L51: не включаем | M51: 12.05.2025 | N51: Ростов-на-Дону | O51: постоянный | P51: =DAYS360(M51,F51,TRUE)/30 -> 11.4 | Q51: =IF(DAYS360(M51,F51,TRUE)>120,"-","увольнение в течении испытательного срока") -> - | R51: =IF(ISBLANK(B51),"-",IF(ISERROR(FIND("вич",B51,1)),"ж","м")) -> м | S51: 20.06.1975 | T51: АЛМАЗ ООО | U51: Сафронов И.А. | V51: ЦФО Производство №2 (1 ур)
A52: 00463 | B52: Подгорная Виктория Романовна | C52: Участок сборки счетчиков | D52: Сборщик | E52: Основное место работы | F52: 22.04.2026 | H52: п. 3 части 1 ст. 77 ТК РФ | J52: Апрель | K52: 1. Другая сфера деятельности, открытие собственного дела и т.п. | L52: =IF(O52="Постоянный",VLOOKUP(K53,'Включаем не включаем'!$A$1:$B$65536,2,0),"не включаем") -> не включаем | M52: 12.11.2024 | N52: Ростов-на-Дону | O52: постоянный | P52: =DAYS360(M52,F52,TRUE)/30 -> 17.333333 | Q52: =IF(DAYS360(M52,F52,TRUE)>120,"-","увольнение в течении испытательного срока") -> - | R52: =IF(ISBLANK(B52),"-",IF(ISERROR(FIND("вич",B52,1)),"ж","м")) -> ж | S52: 22.09.2004 | T52: АЛМАЗ ООО | U52: Сафронов И.А. | V52: ЦФО Производство №2 (1 ур)
A53: 00989 | B53: Марченко Марина Васильевна | C53: Служба технического директора | D53: Менеджер по снабжению | E53: Основное место работы | F53: 21.04.2026 | H53: п. 3 части 1 ст. 77 ТК РФ | J53: Апрель | K53: 1. Семейные обстоятельства | L53: не включаем | M53: 19.05.2025 | N53: Ростов-на-Дону | O53: постоянный | P53: =DAYS360(M53,F53,TRUE)/30 -> 11.066667 | Q53: =IF(DAYS360(M53,F53,TRUE)>120,"-","увольнение в течении испытательного срока") -> - | R53: =IF(ISBLANK(B53),"-",IF(ISERROR(FIND("вич",B53,1)),"ж","м")) -> ж | S53: 23.07.2004 | T53: ТУРБУЛЕНТНОСТЬ-ДОН ООО НПО | U53: Улановский К.В. | V53: ЦФО Служба технического директора (2 ур)
A54: 01093 | B54: Ульшин Иван Александрович | C54: Сектор рекламы и PR | D54: Бренд-менеджер | E54: Основное место работы | F54: 20.04.2026 | H54: п. 3 части 1 ст. 77 ТК РФ | J54: Апрель | K54: 2. Низкие результаты, не справляется с основными обязанностями | L54: не включаем | M54: 24.02.2026 | N54: Ростов-на-Дону | O54: постоянный | P54: =DAYS360(M54,F54,TRUE)/30 -> 1.8666667 | Q54: =IF(DAYS360(M54,F54,TRUE)>120,"-","увольнение в течении испытательного срока") -> увольнение в течении испытательного срока | R54: =IF(ISBLANK(B54),"-",IF(ISERROR(FIND("вич",B54,1)),"ж","м")) -> м | S54: 26.05.1988 | T54: ТУРБУЛЕНТНОСТЬ-ДОН ООО НПО | U54: Беккер А.В. | V54: ЦФО Ком.служба (2 ур)
A55: 00504 | B55: Милютенко Ольга Николаевна | C55: Отдел по продаже БМИ | D55: Директор по продажам БМИ | E55: Основное место работы | F55: 14.04.2026 | H55: п. 3 части 1 ст. 77 ТК РФ | J55: Апрель | K55: 3. Перевод работника с его согласия в другое юридическое лицо в рамках Группы компаний | L55: =IF(O55="Постоянный",VLOOKUP(K55,'Включаем не включаем'!$A$1:$B$65536,2,0),"не включаем") -> не включаем | M55: 01.04.2022 | N55: Ростов-на-Дону | O55: постоянный | P55: =DAYS360(M55,F55,TRUE)/30 -> 48.433333 | Q55: =IF(DAYS360(M55,F55,TRUE)>120,"-","увольнение в течении испытательного срока") -> - | R55: =IF(ISBLANK(B55),"-",IF(ISERROR(FIND("вич",B55,1)),"ж","м")) -> ж | S55: 17.12.1983 | T55: ТУРБУЛЕНТНОСТЬ-ДОН ООО НПО | U55: Донцова А.Е. | V55: ЦФО Ком.служба (2 ур)
A56: 01015 | B56: Семенихина Алина Владимировна | C56: Участок ультразвуковых датчиков | D56: Слесарь-сборщик радиоэлектронной аппаратуры | E56: Основное место работы | F56: 13.04.2026 | H56: п. 3 части 1 ст. 77 ТК РФ | J56: Апрель | K56: 3. Перевод работника с его согласия в другое юридическое лицо в рамках Группы компаний | L56: =IF(O56="Постоянный",VLOOKUP(K56,'Включаем не включаем'!$A$1:$B$65536,2,0),"не включаем") -> не включаем | M56: 11.07.2025 | N56: Ростов-на-Дону | O56: постоянный | P56: =DAYS360(M56,F56,TRUE)/30 -> 9.0666667 | Q56: =IF(DAYS360(M56,F56,TRUE)>120,"-","увольнение в течении испытательного срока") -> - | R56: =IF(ISBLANK(B56),"-",IF(ISERROR(FIND("вич",B56,1)),"ж","м")) -> ж | S56: 14.06.1998 | T56: ТУРБУЛЕНТНОСТЬ-ДОН ООО НПО | U56: Иващенко Н.А. | V56: ЦФО Производство №1 (1 ур)
A57: 01016 | B57: Калюжная Татьяна Юрьевна | C57: Участок ультразвуковых датчиков | D57: Слесарь-сборщик радиоэлектронной аппаратуры | E57: Основное место работы | F57: 13.04.2026 | H57: п. 3 части 1 ст. 77 ТК РФ | J57: Апрель | K57: 3. Перевод работника с его согласия в другое юридическое лицо в рамках Группы компаний | L57: =IF(O57="Постоянный",VLOOKUP(K57,'Включаем не включаем'!$A$1:$B$65536,2,0),"не включаем") -> не включаем | M57: 11.07.2025 | N57: Ростов-на-Дону | O57: постоянный | P57: =DAYS360(M57,F57,TRUE)/30 -> 9.0666667 | Q57: =IF(DAYS360(M57,F57,TRUE)>120,"-","увольнение в течении испытательного срока") -> - | R57: =IF(ISBLANK(B57),"-",IF(ISERROR(FIND("вич",B57,1)),"ж","м")) -> ж | S57: 22.03.1974 | T57: ТУРБУЛЕНТНОСТЬ-ДОН ООО НПО | U57: Иващенко Н.А. | V57: ЦФО Производство №1 (1 ур)
A58: 01017 | B58: Куркова Марина Юрьевна | C58: Участок ультразвуковых датчиков | D58: Слесарь-сборщик радиоэлектронной аппаратуры | E58: Основное место работы | F58: 13.04.2026 | H58: п. 3 части 1 ст. 77 ТК РФ | J58: Апрель | K58: 3. Перевод работника с его согласия в другое юридическое лицо в рамках Группы компаний | L58: =IF(O58="Постоянный",VLOOKUP(K58,'Включаем не включаем'!$A$1:$B$65536,2,0),"не включаем") -> не включаем | M58: 11.07.2025 | N58: Ростов-на-Дону | O58: постоянный | P58: =DAYS360(M58,F58,TRUE)/30 -> 9.0666667 | Q58: =IF(DAYS360(M58,F58,TRUE)>120,"-","увольнение в течении испытательного срока") -> - | R58: =IF(ISBLANK(B58),"-",IF(ISERROR(FIND("вич",B58,1)),"ж","м")) -> ж | S58: 28.06.1994 | T58: ТУРБУЛЕНТНОСТЬ-ДОН ООО НПО | U58: Иващенко Н.А. | V58: ЦФО Производство №1 (1 ур)
A59: 01034 | B59: Шеханова Вероника Игоревна | C59: Участок ультразвуковых датчиков | D59: Слесарь-сборщик радиоэлектронной аппаратуры | E59: Основное место работы | F59: 13.04.2026 | H59: п. 3 части 1 ст. 77 ТК РФ | J59: Апрель | K59: 3. Перевод работника с его согласия в другое юридическое лицо в рамках Группы компаний | L59: =IF(O59="Постоянный",VLOOKUP(K59,'Включаем не включаем'!$A$1:$B$65536,2,0),"не включаем") -> не включаем | M59: 15.08.2025 | N59: Ростов-на-Дону | O59: постоянный | P59: =DAYS360(M59,F59,TRUE)/30 -> 7.9333333 | Q59: =IF(DAYS360(M59,F59,TRUE)>120,"-","увольнение в течении испытательного срока") -> - | R59: =IF(ISBLANK(B59),"-",IF(ISERROR(FIND("вич",B59,1)),"ж","м")) -> ж | S59: 10.12.1991 | T59: ТУРБУЛЕНТНОСТЬ-ДОН ООО НПО | U59: Иващенко Н.А. | V59: ЦФО Производство №1 (1 ур)
A60: 00124 | B60: Мантач Татьяна Игоновна | C60: Азовский СЦ | D60: Кассир-приемщик | E60: Основное место работы | F60: 09.04.2026 | H60: п. 3 части 1 ст. 77 ТК РФ | J60: Апрель | K60: 2. Низкие результаты, не справляется с основными обязанностями | L60: =IF(O60="Постоянный",VLOOKUP(K60,'Включаем не включаем'!$A$1:$B$65536,2,0),"не включаем") -> не включаем | M60: 17.07.2024 | N60: Ростов-на-Дону | O60: постоянный | P60: =DAYS360(M60,F60,TRUE)/30 -> 20.733333 | Q60: =IF(DAYS360(M60,F60,TRUE)>120,"-","увольнение в течении испытательного срока") -> - | R60: =IF(ISBLANK(B60),"-",IF(ISERROR(FIND("вич",B60,1)),"ж","м")) -> ж | S60: 26.01.1996 | T60: Метрогазсервис ООО | U60: Махлин К.Р. | V60: ЦФО МГС (1 ур)
A61: 01053 | B61: Амирханян Гоарик Эдвардовна | C61: Управление делами | D61: Офис-менеджер | E61: Основное место работы | F61: 09.04.2026 | H61: п. 3 части 1 ст. 77 ТК РФ | J61: Апрель | K61: 1. Предложили более высокую зарплату на аналогичной должности, неудовлетворенность текущей з/платой | L61: =IF(O61="Постоянный",VLOOKUP(K61,'Включаем не включаем'!$A$1:$B$65536,2,0),"не включаем") -> не включаем | M61: 13.10.2025 | N61: Ростов-на-Дону | O61: постоянный | P61: =DAYS360(M61,F61,TRUE)/30 -> 5.8666667 | Q61: =IF(DAYS360(M61,F61,TRUE)>120,"-","увольнение в течении испытательного срока") -> - | R61: =IF(ISBLANK(B61),"-",IF(ISERROR(FIND("вич",B61,1)),"ж","м")) -> ж | S61: 10.05.1993 | T61: ТУРБУЛЕНТНОСТЬ-ДОН ООО НПО | U61: Тищенко М.Н. | V61: ЦФО Руководство (2 ур)
A62: 00208 | B62: Быстров Иван Сергеевич | C62: Отдел технического контроля №2 | D62: Ведущий инженер по качеству | E62: Основное место работы | F62: 09.04.2026 | H62: п. 3 части 1 ст. 77 ТК РФ | J62: Апрель | K62: 1. Предложили более высокую зарплату на аналогичной должности, неудовлетворенность текущей з/платой | L62: =IF(O62="Постоянный",VLOOKUP(K62,'Включаем не включаем'!$A$1:$B$65536,2,0),"не включаем") -> не включаем | M62: 13.01.2021 | N62: Ростов-на-Дону | O62: постоянный | P62: =DAYS360(M62,F62,TRUE)/30 -> 62.866667 | Q62: =IF(DAYS360(M62,F62,TRUE)>120,"-","увольнение в течении испытательного срока") -> - | R62: =IF(ISBLANK(B62),"-",IF(ISERROR(FIND("вич",B62,1)),"ж","м")) -> м | S62: 12.02.1996 | T62: АЛМАЗ ООО | U62: Арсуноев М.М. | V62: ЦФО Служба технического директора (2 ур)
A63: 01095 | B63: Попов Павел Юрьевич | C63: Отдел по продаже БМИ | D63: Ведущий менеджер | E63: Основное место работы | F63: 08.04.2026 | H63: п. 3 части 1 ст. 77 ТК РФ | J63: Апрель | K63: 2. Неадекватное поведение, поступки и т.п. | L63: не включаем | M63: 03.03.2026 | N63: Ростов-на-Дону | O63: постоянный | P63: =DAYS360(M63,F63,TRUE)/30 -> 1.1666667 | Q63: =IF(DAYS360(M63,F63,TRUE)>120,"-","увольнение в течении испытательного срока") -> увольнение в течении испытательного срока | R63: =IF(ISBLANK(B63),"-",IF(ISERROR(FIND("вич",B63,1)),"ж","м")) -> м | S63: 06.01.2002 | T63: ТУРБУЛЕНТНОСТЬ-ДОН ООО НПО | U63: Билас А.В. | V63: ЦФО Ком.служба (2 ур)
A64: 00980 | B64: Самойлов Александр Иванович | C64: Сектор качества разработки | D64: Инженер-тестировщик 2 категории | E64: Основное место работы | F64: 06.04.2026 | H64: п. 3 части 1 ст. 77 ТК РФ | J64: Апрель | K64: 1. Предложили более высокую позицию, нет карьерного роста в Компании | L64: =IF(O64="Постоянный",VLOOKUP(K64,'Включаем не включаем'!$A$1:$B$65536,2,0),"не включаем") -> не включаем | M64: 28.04.2025 | N64: Ростов-на-Дону | O64: постоянный | P64: =DAYS360(M64,F64,TRUE)/30 -> 11.266667 | Q64: =IF(DAYS360(M64,F64,TRUE)>120,"-","увольнение в течении испытательного срока") -> - | R64: =IF(ISBLANK(B64),"-",IF(ISERROR(FIND("вич",B64,1)),"ж","м")) -> м | S64: 11.08.1982 | T64: ТУРБУЛЕНТНОСТЬ-ДОН ООО НПО | U64: Улановский К.В. | V64: ЦФО Служба технического директора (2 ур)
A65: 01069 | B65: Хомюк Валерия Васильевна | C65: Отдел продаж эталонного оборудования и услуг | D65: Ведущий менеджер | E65: Основное место работы | F65: 02.04.2026 | H65: п. 3 части 1 ст. 77 ТК РФ | J65: Апрель | K65: 1. Предложили более высокую позицию, нет карьерного роста в Компании | L65: =IF(O65="Постоянный",VLOOKUP(K65,'Включаем не включаем'!$A$1:$B$65536,2,0),"не включаем") -> не включаем | M65: 11.11.2025 | N65: Ростов-на-Дону | O65: постоянный | P65: =DAYS360(M65,F65,TRUE)/30 -> 4.7 | Q65: =IF(DAYS360(M65,F65,TRUE)>120,"-","увольнение в течении испытательного срока") -> - | R65: =IF(ISBLANK(B65),"-",IF(ISERROR(FIND("вич",B65,1)),"ж","м")) -> ж | S65: 30.01.1996 | T65: ТУРБУЛЕНТНОСТЬ-ДОН ООО НПО | U65: Прокопчук Л.А. | V65: ЦФО Ком.служба (2 ур)
A66: 00246 | B66: Иович Егор Сергеевич | C66: Транспортный отдел | D66: Водитель автомобиля | E66: Основное место работы | F66: 21.04.2026 | H66: п. 3 части 1 ст. 77 ТК РФ | J66: Апрель | K66: 3. Перевод работника с его согласия в другое юридическое лицо в рамках Группы компаний | L66: =IF(O66="Постоянный",VLOOKUP(K66,'Включаем не включаем'!$A$1:$B$65536,2,0),"не включаем") -> не включаем | M66: 18.02.2026 | N66: Ростов-на-Дону | O66: временный | P66: =DAYS360(M66,F66,TRUE)/30 -> 2.1 | Q66: =IF(DAYS360(M66,F66,TRUE)>120,"-","увольнение в течении испытательного срока") -> увольнение в течении испытательного срока | R66: =IF(ISBLANK(B66),"-",IF(ISERROR(FIND("вич",B66,1)),"ж","м")) -> м | S66: 01.08.1998 | T66: ТД Амурская легенда | U66: Кузнецова Л.Г. | V66: ЦФО Амурская легенда (1 ур)
A67: 00013 | B67: Арцыбашев Никита Алексеевич | C67: Транспортный отдел | D67: Водитель автомобиля | E67: Основное место работы | F67: 20.04.2026 | H67: п. 3 части 1 ст. 77 ТК РФ | J67: Апрель | K67: 1. Недовольство руководством, непосредственным руководителем, общим стилем управления, отношениями в отделе | L67: =IF(O67="Постоянный",VLOOKUP(K67,'Включаем не включаем'!$A$1:$B$65536,2,0),"не включаем") -> не включаем | M67: 06.04.2026 | N67: Ростов-на-Дону | O67: временный | P67: =DAYS360(M67,F67,TRUE)/30 -> 0.46666667 | Q67: =IF(DAYS360(M67,F67,TRUE)>120,"-","увольнение в течении испытательного срока") -> увольнение в течении испытательного срока | R67: =IF(ISBLANK(B67),"-",IF(ISERROR(FIND("вич",B67,1)),"ж","м")) -> м | S67: 11.08.2001 | T67: ТД Амурская легенда | U67: Кузнецова Л.Г. | V67: ЦФО Амурская легенда (1 ур)
A68: 00009 | B68: Чахалов Ислам Исфандиярович | C68: Транспортный отдел | D68: Водитель автомобиля | E68: Основное место работы | F68: 20.04.2026 | H68: п. 3 части 1 ст. 77 ТК РФ | J68: Апрель | K68: 1. Плохие условия труда | L68: =IF(O68="Постоянный",VLOOKUP(K68,'Включаем не включаем'!$A$1:$B$65536,2,0),"не включаем") -> не включаем | M68: 30.05.2025 | N68: Ростов-на-Дону | O68: временный | P68: =DAYS360(M68,F68,TRUE)/30 -> 10.666667 | Q68: =IF(DAYS360(M68,F68,TRUE)>120,"-","увольнение в течении испытательного срока") -> - | R68: =IF(ISBLANK(B68),"-",IF(ISERROR(FIND("вич",B68,1)),"ж","м")) -> м | S68: 10.09.1998 | T68: ТД Амурская легенда | U68: Кузнецова Л.Г. | V68: ЦФО Амурская легенда (1 ур)
A69: 00197 | B69: Арахамия Лаша Мириянович | C69: Транспортный отдел | D69: Водитель автомобиля | E69: Основное место работы | F69: 20.04.2026 | H69: п. 3 части 1 ст. 77 ТК РФ | J69: Апрель | K69: 3. Перевод работника с его согласия в другое юридическое лицо в рамках Группы компаний | L69: =IF(O69="Постоянный",VLOOKUP(K69,'Включаем не включаем'!$A$1:$B$65536,2,0),"не включаем") -> не включаем | M69: 27.01.2025 | N69: Ростов-на-Дону | O69: временный | P69: =DAYS360(M69,F69,TRUE)/30 -> 14.766667 | Q69: =IF(DAYS360(M69,F69,TRUE)>120,"-","увольнение в течении испытательного срока") -> - | R69: =IF(ISBLANK(B69),"-",IF(ISERROR(FIND("вич",B69,1)),"ж","м")) -> м | S69: 07.02.1976 | T69: ТД Амурская легенда | U69: Кузнецова Л.Г. | V69: ЦФО Амурская легенда (1 ур)
A70: 00249 | B70: Пономарева Ольга Викторовна | C70: Отдел продаж | D70: Менеджер по сопровождению клиентов | E70: Основное место работы | F70: 03.04.2026 | H70: п. 3 части 1 ст. 77 ТК РФ | J70: Апрель | K70: 2. Низкие результаты, не справляется с основными обязанностями | L70: =IF(O70="Постоянный",VLOOKUP(K70,'Включаем не включаем'!$A$1:$B$65536,2,0),"не включаем") -> не включаем | M70: 30.03.2026 | N70: Ростов-на-Дону | O70: постоянный | P70: =DAYS360(M70,F70,TRUE)/30 -> 0.1 | Q70: =IF(DAYS360(M70,F70,TRUE)>120,"-","увольнение в течении испытательного срока") -> увольнение в течении испытательного срока | R70: =IF(ISBLANK(B70),"-",IF(ISERROR(FIND("вич",B70,1)),"ж","м")) -> ж | S70: 12.10.1967 | T70: ТД Амурская легенда | U70: Кузнецова Л.Г. | V70: ЦФО Амурская легенда (1 ур)
A71: 00134 | B71: Ряжских Виталий Витальевич | C71: Вешенский СЦ | D71: Начальник сервисного центра | E71: Внешнее совместительство | F71: 29.05.2026 | H71: п. 3 части 1 ст. 77 ТК РФ | J71: Май | K71: 3. Переезд на другое место жительства | L71: =IF(O71="Постоянный",VLOOKUP(K71,'Включаем не включаем'!$A$1:$B$65536,2,0),"не включаем") -> не включаем | M71: 01.08.2025 | N71: Ростов-на-Дону | O71: постоянный | P71: =DAYS360(M71,F71,TRUE)/30 -> 9.9333333 | Q71: =IF(DAYS360(M71,F71,TRUE)>120,"-","увольнение в течении испытательного срока") -> - | R71: =IF(ISBLANK(B71),"-",IF(ISERROR(FIND("вич",B71,1)),"ж","м")) -> м | S71: 03.01.1998 | T71: Метрогазсервис ООО
A72: 01097 | B72: Гуреев Александр Михайлович | C72: Складской комплекс | D72: Кладовщик | E72: Основное место работы | F72: 29.05.2026 | H72: п. 3 части 1 ст. 77 ТК РФ | J72: Май | K72: 1. Предложили более высокую зарплату на аналогичной должности, неудовлетворенность текущей з/платой | L72: =IF(O72="Постоянный",VLOOKUP(K72,'Включаем не включаем'!$A$1:$B$65536,2,0),"не включаем") -> не включаем | M72: 10.03.2026 | N72: Ростов-на-Дону | O72: постоянный | P72: =DAYS360(M72,F72,TRUE)/30 -> 2.6333333 | Q72: =IF(DAYS360(M72,F72,TRUE)>120,"-","увольнение в течении испытательного срока") -> увольнение в течении испытательного срока | R72: =IF(ISBLANK(B72),"-",IF(ISERROR(FIND("вич",B72,1)),"ж","м")) -> м | S72: 01.10.2001 | T72: ТУРБУЛЕНТНОСТЬ-ДОН ООО НПО | U72: Кургин Ф.В. | V72: ЦФО Служба логистики (2 ур)
A73: 01067 | B73: Ван-Сен-Дю Марина Константиновна | C73: Участок монтажа электронных плат | D73: Монтажник РЭА | E73: Основное место работы | F73: 29.05.2026 | H73: п. 3 части 1 ст. 77 ТК РФ | J73: Май | K73: 1. Состояние здоровья | L73: =IF(O73="Постоянный",VLOOKUP(K73,'Включаем не включаем'!$A$1:$B$65536,2,0),"не включаем") -> не включаем | M73: 10.11.2025 | N73: Ростов-на-Дону | O73: постоянный | P73: =DAYS360(M73,F73,TRUE)/30 -> 6.6333333 | Q73: =IF(DAYS360(M73,F73,TRUE)>120,"-","увольнение в течении испытательного срока") -> - | R73: =IF(ISBLANK(B73),"-",IF(ISERROR(FIND("вич",B73,1)),"ж","м")) -> ж | S73: 12.08.1982 | T73: ТУРБУЛЕНТНОСТЬ-ДОН ООО НПО | U73: Иващенко Н.А. | V73: ЦФО Производство №1 (1 ур)
A74: 00129 | B74: Стржемеская Юлия Александровна | C74: Отдел информационных технологий | D74: Помощник системного администратора | E74: Внешнее совместительство | F74: 29.05.2026 | H74: п. 3 части 1 ст. 77 ТК РФ | J74: Май | K74: 1. Семейные обстоятельства | L74: =IF(O74="Постоянный",VLOOKUP(K74,'Включаем не включаем'!$A$1:$B$65536,2,0),"не включаем") -> не включаем | M74: 09.01.2019 | N74: Ростов-на-Дону | O74: постоянный | P74: =DAYS360(M74,F74,TRUE)/30 -> 88.666667 | Q74: =IF(DAYS360(M74,F74,TRUE)>120,"-","увольнение в течении испытательного срока") -> - | R74: =IF(ISBLANK(B74),"-",IF(ISERROR(FIND("вич",B74,1)),"ж","м")) -> ж | S74: 28.09.1988 | T74: ТУРБУЛЕНТНОСТЬ-ДОН ООО НПО | U74: Горбатенко С.А. | V74: ЦФО Служба автоматизации (2 ур)
A75: 0000000756 | B75: Шатилова Татьяна Юрьевна | C75: Складской комплекс | D75: Оператор склада | E75: Основное место работы | F75: 29.05.2026 | H75: п. 3 части 1 ст. 77 ТК РФ | J75: Май | K75: 1. Состояние здоровья | L75: =IF(O75="Постоянный",VLOOKUP(K75,'Включаем не включаем'!$A$1:$B$65536,2,0),"не включаем") -> не включаем | M75: 01.11.2016 | N75: Ростов-на-Дону | O75: постоянный | P75: =DAYS360(M75,F75,TRUE)/30 -> 114.93333 | Q75: =IF(DAYS360(M75,F75,TRUE)>120,"-","увольнение в течении испытательного срока") -> - | R75: =IF(ISBLANK(B75),"-",IF(ISERROR(FIND("вич",B75,1)),"ж","м")) -> ж | S75: 30.05.1966 | T75: ТУРБУЛЕНТНОСТЬ-ДОН ООО НПО | U75: Кургин Ф.В. | V75: ЦФО Служба логистики (2 ур)
A76: 00736 | B76: Шамирян Альберт Варужанович | C76: Служба логистики | D76: Специалист по управлению товарными запасами | E76: Основное место работы | F76: 29.05.2026 | H76: п. 3 части 1 ст. 77 ТК РФ | J76: Май | K76: 1. Недовольство руководством, непосредственным руководителем, общим стилем управления, отношениями в отделе | L76: =IF(O76="Постоянный",VLOOKUP(K76,'Включаем не включаем'!$A$1:$B$65536,2,0),"не включаем") -> не включаем | M76: 01.11.2023 | N76: Ростов-на-Дону | O76: постоянный | P76: =DAYS360(M76,F76,TRUE)/30 -> 30.933333 | Q76: =IF(DAYS360(M76,F76,TRUE)>120,"-","увольнение в течении испытательного срока") -> - | R76: =IF(ISBLANK(B76),"-",IF(ISERROR(FIND("вич",B76,1)),"ж","м")) -> м | S76: 26.04.1999 | T76: ТУРБУЛЕНТНОСТЬ-ДОН ООО НПО | U76: Коваленко А.О. | V76: ЦФО Служба логистики (2 ур)
A77: 00127 | B77: Крапковская Наталья Валерьевна | C77: Отдел внедрения | D77: Архитектор программного обеспечения | E77: Основное место работы | F77: 29.05.2026 | H77: п. 3 части 1 ст. 77 ТК РФ | J77: Май | K77: 3. Перевод работника с его согласия в другое юридическое лицо в рамках Группы компаний | L77: =IF(O77="Постоянный",VLOOKUP(K77,'Включаем не включаем'!$A$1:$B$65536,2,0),"не включаем") -> не включаем | M77: 09.01.2019 | N77: Ростов-на-Дону | O77: постоянный | P77: =DAYS360(M77,F77,TRUE)/30 -> 88.666667 | Q77: =IF(DAYS360(M77,F77,TRUE)>120,"-","увольнение в течении испытательного срока") -> - | R77: =IF(ISBLANK(B77),"-",IF(ISERROR(FIND("вич",B77,1)),"ж","м")) -> ж | S77: 05.01.1965 | T77: ТУРБУЛЕНТНОСТЬ-ДОН ООО НПО | U77: Мегрелишвили М.Э. | V77: ЦФО Служба автоматизации (2 ур)
A78: 00947 | B78: Коваленко Максим Александрович | C78: Конструкторско-технологический отдел | D78: Ведущий инженер-конструктор | E78: Основное место работы | F78: 27.05.2026 | H78: п. 3 части 1 ст. 77 ТК РФ | J78: Май | K78: 1. Недовольство руководством, непосредственным руководителем, общим стилем управления, отношениями в отделе | L78: =IF(O78="Постоянный",VLOOKUP(K78,'Включаем не включаем'!$A$1:$B$65536,2,0),"не включаем") -> не включаем | M78: 10.03.2025 | N78: Ростов-на-Дону | O78: постоянный | P78: =DAYS360(M78,F78,TRUE)/30 -> 14.566667 | Q78: =IF(DAYS360(M78,F78,TRUE)>120,"-","увольнение в течении испытательного срока") -> - | R78: =IF(ISBLANK(B78),"-",IF(ISERROR(FIND("вич",B78,1)),"ж","м")) -> м | S78: 07.12.1983 | T78: ТУРБУЛЕНТНОСТЬ-ДОН ООО НПО | U78: Гончаров С.Д. | V78: ЦФО КБ (2 ур)
A79: 00973 | B79: Ефремов Алексей Петрович | C79: Конструкторское бюро | D79: Заместитель главного конструктора по изделию | E79: Основное место работы | F79: 25.05.2026 | H79: п. 3 части 1 ст. 77 ТК РФ | J79: Май | K79: 3. Оптимизация структуры Компании | L79: =IF(O79="Постоянный",VLOOKUP(K79,'Включаем не включаем'!$A$1:$B$65536,2,0),"не включаем") -> не включаем | M79: 17.04.2025 | N79: Ростов-на-Дону | O79: постоянный | P79: =DAYS360(M79,F79,TRUE)/30 -> 13.266667 | Q79: =IF(DAYS360(M79,F79,TRUE)>120,"-","увольнение в течении испытательного срока") -> - | R79: =IF(ISBLANK(B79),"-",IF(ISERROR(FIND("вич",B79,1)),"ж","м")) -> м | S79: 19.08.1975 | T79: ТУРБУЛЕНТНОСТЬ-ДОН ООО НПО | U79: Гончаров С.Д. | V79: ЦФО КБ (2 ур)
A80: 00655 | B80: Арушанян Артем Артурович | C80: Служба ремонта и обслуживания оборудования | D80: Слесарь-ремонтник | E80: Основное место работы | F80: 12.05.2026 | H80: п. 3 части 1 ст. 77 ТК РФ | J80: Май | K80: 1. Недовольство руководством, непосредственным руководителем, общим стилем управления, отношениями в отделе | L80: =IF(O80="Постоянный",VLOOKUP(K80,'Включаем не включаем'!$A$1:$B$65536,2,0),"не включаем") -> не включаем | M80: 27.04.2023 | N80: Ростов-на-Дону | O80: постоянный | P80: =DAYS360(M80,F80,TRUE)/30 -> 36.5 | Q80: =IF(DAYS360(M80,F80,TRUE)>120,"-","увольнение в течении испытательного срока") -> - | R80: =IF(ISBLANK(B80),"-",IF(ISERROR(FIND("вич",B80,1)),"ж","м")) -> м | S80: 11.11.1994 | T80: ТУРБУЛЕНТНОСТЬ-ДОН ООО НПО | U80: Карпенко А.В. | V80: ЦФО Производство №1 (1 ур)
A81: 00180 | B81: Лихов Евгений Викторович | C81: Участок монтажа радиоэлектронной аппаратуры | D81: Монтажник РЭА | E81: Основное место работы | F81: 08.05.2026 | H81: п. 3 части 1 ст. 77 ТК РФ | J81: Май | K81: 1. Предложили более высокую зарплату на аналогичной должности, неудовлетворенность текущей з/платой | L81: =IF(O81="Постоянный",VLOOKUP(K81,'Включаем не включаем'!$A$1:$B$65536,2,0),"не включаем") -> не включаем | M81: 16.03.2020 | N81: Ростов-на-Дону | O81: постоянный | P81: =DAYS360(M81,F81,TRUE)/30 -> 73.733333 | Q81: =IF(DAYS360(M81,F81,TRUE)>120,"-","увольнение в течении испытательного срока") -> - | R81: =IF(ISBLANK(B81),"-",IF(ISERROR(FIND("вич",B81,1)),"ж","м")) -> м | S81: 04.09.1976 | T81: АЛМАЗ ООО | U81: Сафронов И.А. | V81: ЦФО Производство №2 (1 ур)
A82: 00250 | B82: Атаманов Евгений Анатольевич | C82: Транспортный отдел | D82: Механик | E82: Основное место работы | F82: 15.05.2026 | H82: п. 3 части 1 ст. 77 ТК РФ | J82: Май | K82: 1. Предложили более высокую позицию, нет карьерного роста в Компании | L82: =IF(O82="Постоянный",VLOOKUP(K82,'Включаем не включаем'!$A$1:$B$65536,2,0),"не включаем") -> не включаем | M82: 13.04.2026 | N82: Ростов-на-Дону | O82: постоянный | P82: =DAYS360(M82,F82,TRUE)/30 -> 1.0666667 | Q82: =IF(DAYS360(M82,F82,TRUE)>120,"-","увольнение в течении испытательного срока") -> увольнение в течении испытательного срока | R82: =IF(ISBLANK(B82),"-",IF(ISERROR(FIND("вич",B82,1)),"ж","м")) -> м | S82: 29.09.1985 | T82: ТД Амурская легенда | U82: Кузнецова Л.Г. | V82: ЦФО Амурская легенда (1 ур)
A83: 0049 | B83: Чаловская Мария Артёмовна | C83: Служба приема и размещения | D83: Портье | E83: Основное место работы | F83: 04.05.2026 | H83: п. 3 части 1 ст. 77 ТК РФ | J83: Май | K83: 3. Переезд на другое место жительства | L83: =IF(O83="Постоянный",VLOOKUP(K83,'Включаем не включаем'!$A$1:$B$65536,2,0),"не включаем") -> не включаем | M83: 16.12.2025 | N83: Ростов-на-Дону | O83: постоянный | P83: =DAYS360(M83,F83,TRUE)/30 -> 4.6 | Q83: =IF(DAYS360(M83,F83,TRUE)>120,"-","увольнение в течении испытательного срока") -> - | R83: =IF(ISBLANK(B83),"-",IF(ISERROR(FIND("вич",B83,1)),"ж","м")) -> ж | S83: 30.07.2004 | T83: МИЛАКА | U83: Щитов И.А. | V83: ЦФО Милака (1 ур)

Sheet Свод по уволенным
A1: Список увольнений
A4: включаем \ не включаем | B4: включаем
A5: Увольнение в течении испытательного срока | B5: (Все)
A7: Количество по полю ЦФО
A8: Юридическое лицо | B8: Месяц увольнения | C8: ЦФО | D8: Итог
A9: АЛМАЗ ООО | B9: Май | C9: ЦФО Производство №2 (1 ур) | D9: 1
A10: ТД Амурская легенда | B10: Май | C10: ЦФО Амурская легенда (1 ур) | D10: 1
A11: ТУРБУЛЕНТНОСТЬ-ДОН ООО НПО | B11: Май | C11: ЦФО Производство №1 (1 ур) | D11: 2
C12: ЦФО Служба логистики (2 ур) | D12: 3
C13: ЦФО КБ (2 ур) | D13: 1
C14: ЦФО Служба автоматизации (2 ур) | D14: 1
A15: Общий итог | D15: 9

Sheet Текучесть
A1: Текучесть в разрезе компаний (общая) | B1: План на 2026 | C1: План | D1: Факт | E1: % выполнения | F1: январь | I1: февраль | L1: март | O1: апрель | R1: май | U1: июнь | X1: июль | AA1: август | AD1: сентябрь | AG1: октябрь | AJ1: ноябрь | AM1: декабрь | AP1: ГОД
A2: Компания | F2: численность | G2: увольнение | H2: текучесть | I2: численность | J2: увольнение | K2: текучесть | L2: численность | M2: увольнение | N2: текучесть | O2: численность | P2: увольнение | Q2: текучесть | R2: численность | S2: увольнение | T2: текучесть | U2: численность | V2: увольнение | W2: текучесть | X2: численность | Y2: увольнение | Z2: текучесть | AA2: численность | AB2: увольнение | AC2: текучесть | AD2: численность | AE2: увольнение | AF2: текучесть | AG2: численность | AH2: увольнение | AI2: текучесть | AJ2: численность | AK2: увольнение | AL2: текучесть | AM2: численность | AN2: увольнение | AO2: текучесть | AP2: численность | AQ2: увольнение | AR2: текучесть
A3: НПО Турбулентность-ДОН | B3: 0.2 | C3: =B3/12*$C$14 -> 0.083333333 | D3: =AR3 -> 0.08069522 | E3: =IF(D3>0%,C3/D3,100%) -> 1.0326923 | F3: 331 | G3: 2 | H3: =G3/F3 -> 0.0060422961 | I3: 321 | J3: 9 | K3: =J3/I3 -> 0.028037383 | L3: 321 | M3: 5 | N3: =M3/L3 -> 0.015576324 | O3: 318 | P3: 3 | Q3: =P3/O3 -> 0.0094339623 | R3: 320 | S3: 7 | T3: =S3/R3 -> 0.021875 | W3: =V3/U3 -> 0 | Z3: =Y3/X3 -> 0 | AC3: =AB3/AA3 -> 0 | AF3: =AE3/AD3 -> 0 | AI3: =AH3/AG3 -> 0 | AL3: =AK3/AJ3 -> 0 | AO3: =AN3/AM3 -> 0 | AP3: =AVERAGE(F3,I3,L3,O3,R3,U3,X3,AA3,AD3,AG3,AJ3,AM3) -> 322.2 | AQ3: =SUM(G3,J3,M3,P3,S3,V3,Y3,AB3,AE3,AH3,AK3,AN3) -> 26 | AR3: =AQ3/AP3 -> 0.08069522
A4: АЛМАЗ | B4: 0.25 | C4: =B4/12*$C$14 -> 0.10416667 | D4: =AR4 -> 0.11560694 | E4: =IF(D4>0%,C4/D4,100%) -> 0.90104167 | F4: 37 | G4: 1 | H4: =G4/F4 -> 0.027027027 | I4: 35 | J4: 1 | K4: =J4/I4 -> 0.028571429 | L4: 33 | N4: =M4/L4 -> 0 | O4: 33 | P4: 1 | Q4: =P4/O4 -> 0.03030303 | R4: 35 | S4: 1 | T4: =S4/R4 -> 0.028571429 | W4: =V4/U4 -> 0 | Z4: =Y4/X4 -> 0 | AC4: =AB4/AA4 -> 0 | AF4: =AE4/AD4 -> 0 | AI4: =AH4/AG4 -> 0 | AL4: =AK4/AJ4 -> 0 | AO4: =AN4/AM4 -> 0 | AP4: =AVERAGE(F4,I4,L4,O4,R4,U4,X4,AA4,AD4,AG4,AJ4,AM4) -> 34.6 | AQ4: =SUM(G4,J4,M4,P4,S4,V4,Y4,AB4,AE4,AH4,AK4,AN4) -> 4 | AR4: =AQ4/AP4 -> 0.11560694
A5: Метрогазсервис | B5: 0.165 | C5: =B5/12*$C$14 -> 0.06875 | D5: =AR5 -> 0.073170732 | E5: =IF(D5>0%,C5/D5,100%) -> 0.93958333 | F5: 41 | H5: =G5/F5 -> 0 | I5: 42 | J5: 1 | K5: =J5/I5 -> 0.023809524 | L5: 41 | M5: 1 | N5: =M5/L5 -> 0.024390244 | O5: 40 | P5: 1 | Q5: =P5/O5 -> 0.025 | R5: 41 | T5: =S5/R5 -> 0 | W5: =V5/U5 -> 0 | Z5: =Y5/X5 -> 0 | AC5: =AB5/AA5 -> 0 | AF5: =AE5/AD5 -> 0 | AI5: =AH5/AG5 -> 0 | AL5: =AK5/AJ5 -> 0 | AO5: =AN5/AM5 -> 0 | AP5: =AVERAGE(F5,I5,L5,O5,R5,U5,X5,AA5,AD5,AG5,AJ5,AM5) -> 41 | AQ5: =SUM(G5,J5,M5,P5,S5,V5,Y5,AB5,AE5,AH5,AK5,AN5) -> 3 | AR5: =AQ5/AP5 -> 0.073170732
A6: ИП Корниенко М.В. | B6: 0.1 | C6: =B6/12*$C$14 -> 0.041666667 | D6: =AR6 -> 0 | E6: =IF(D6>0%,C6/D6,100%) -> 1 | F6: 10 | H6: =G6/F6 -> 0 | I6: 11 | K6: =J6/I6 -> 0 | L6: 11 | N6: =M6/L6 -> 0 | O6: 11 | P6: 0 | Q6: =P6/O6 -> 0 | R6: 11 | T6: =S6/R6 -> 0 | W6: =V6/U6 -> 0 | Z6: =Y6/X6 -> 0 | AC6: =AB6/AA6 -> 0 | AF6: =AE6/AD6 -> 0 | AI6: =AH6/AG6 -> 0 | AL6: =AK6/AJ6 -> 0 | AO6: =AN6/AM6 -> 0 | AP6: =AVERAGE(F6,I6,L6,O6,R6,U6,X6,AA6,AD6,AG6,AJ6,AM6) -> 10.8 | AQ6: =SUM(G6,J6,M6,P6,S6,V6,Y6,AB6,AE6,AH6,AK6,AN6) -> 0 | AR6: =AQ6/AP6 -> 0
A7: Амурская легенда | B7: 0.15 | C7: =B7/12*$C$14 -> 0.0625 | D7: =AR7 -> 0.13297872 | E7: =IF(D7>0%,C7/D7,100%) -> 0.47 | F7: 36 | H7: =G7/F7 -> 0 | I7: 38 | J7: 1 | K7: =J7/I7 -> 0.026315789 | L7: 38 | M7: 2 | N7: =M7/L7 -> 0.052631579 | O7: 38 | P7: 1 | Q7: =P7/O7 -> 0.026315789 | R7: 38 | S7: 1 | T7: =S7/R7 -> 0.026315789 | W7: =V7/U7 -> 0 | Z7: =Y7/X7 -> 0 | AC7: =AB7/AA7 -> 0 | AF7: =AE7/AD7 -> 0 | AI7: =AH7/AG7 -> 0 | AL7: =AK7/AJ7 -> 0 | AO7: =AN7/AM7 -> 0 | AP7: =AVERAGE(F7,I7,L7,O7,R7,U7,X7,AA7,AD7,AG7,AJ7,AM7) -> 37.6 | AQ7: =SUM(G7,J7,M7,P7,S7,V7,Y7,AB7,AE7,AH7,AK7,AN7) -> 5 | AR7: =AQ7/AP7 -> 0.13297872
A8: Милака | B8: 0.12 | C8: =B8/12*$C$14 -> 0.05 | D8: =AR8 -> 0 | E8: =IF(D8>0%,C8/D8,100%) -> 1 | F8: 17 | H8: =G8/F8 -> 0 | I8: 17 | K8: =J8/I8 -> 0 | L8: 19 | N8: =M8/L8 -> 0 | O8: 17 | Q8: =P8/O8 -> 0 | R8: 17 | T8: =S8/R8 -> 0 | W8: =V8/U8 -> 0 | Z8: =Y8/X8 -> 0 | AC8: =AB8/AA8 -> 0 | AF8: =AE8/AD8 -> 0 | AI8: =AH8/AG8 -> 0 | AL8: =AK8/AJ8 -> 0 | AO8: =AN8/AM8 -> 0 | AP8: =AVERAGE(F8,I8,L8,O8,R8,U8,X8,AA8,AD8,AG8,AJ8,AM8) -> 17.4 | AQ8: =SUM(G8,J8,M8,P8,S8,V8,Y8,AB8,AE8,AH8,AK8,AN8) -> 0 | AR8: =AQ8/AP8 -> 0
A9: Итого | B9: 0.2 | C9: =AVERAGE(C3:C8) -> 0.068402778 | D9: =AVERAGE(D3:D8) -> 0.067075269 | E9: =IF(D9>0%,C9/D9,100%) -> 1.0197913 | F9: =SUM(F3:F8) -> 472 | G9: =SUM(G3:G8) -> 3 | H9: =G9/F9 -> 0.0063559322 | I9: =SUM(I3:I8) -> 464 | J9: =SUM(J3:J8) -> 12 | K9: =J9/I9 -> 0.025862069 | L9: =SUM(L3:L8) -> 463 | M9: =SUM(M3:M8) -> 8 | N9: =M9/L9 -> 0.017278618 | O9: =SUM(O3:O8) -> 457 | P9: =SUM(P3:P8) -> 6 | Q9: =P9/O9 -> 0.013129103 | R9: =SUM(R3:R8) -> 462 | S9: =SUM(S3:S8) -> 9 | T9: =S9/R9 -> 0.019480519 | U9: =SUM(U3:U8) -> 0 | V9: =SUM(V3:V8) -> 0 | W9: =V9/U9 -> 0 | X9: =SUM(X3:X8) -> 0 | Y9: =SUM(Y3:Y8) -> 0 | Z9: =Y9/X9 -> 0 | AA9: =SUM(AA3:AA8) -> 0 | AB9: =SUM(AB3:AB8) -> 0 | AC9: =AB9/AA9 -> 0 | AD9: =SUM(AD3:AD8) -> 0 | AE9: =SUM(AE3:AE8) -> 0 | AF9: =AE9/AD9 -> 0 | AG9: =SUM(AG3:AG8) -> 0 | AH9: =SUM(AH3:AH8) -> 0 | AI9: =AH9/AG9 -> 0 | AJ9: =SUM(AJ3:AJ8) -> 0 | AK9: =SUM(AK3:AK8) -> 0 | AL9: =AK9/AJ9 -> 0 | AM9: =SUM(AM3:AM8) -> 0 | AN9: =SUM(AN3:AN8) -> 0 | AO9: =AN9/AM9 -> 0 | AP9: =AVERAGE(F9,I9,L9,O9,R9,U9,X9,AA9,AD9,AG9,AJ9,AM9) -> 193.16667 | AQ9: =SUM(G9,J9,M9,P9,S9,V9,Y9,AB9,AE9,AH9,AK9,AN9) -> 38 | AR9: =AQ9/AP9 -> 0.19672131
A10: С накоплением | H10: =H9 -> 0.0063559322 | K10: =H9+K9 -> 0.032218001 | N10: =K10+N9 -> 0.049496619 | Q10: =N10+Q9 -> 0.062625722 | T10: =Q10+T9 -> 0.082106241 | W10: =T10+W9 -> 0 | Z10: =W10+Z9 -> 0 | AC10: =Z10+AC9 -> 0 | AF10: =AC10+AF9 -> 0 | AI10: =AF10+AI9 -> 0 | AL10: =AI10+AL9 -> 0 | AO10: =AL10+AO9 -> 0 | AR10: =AR9 -> 0.19672131
A11: План | H11: =B9/12*1 -> 0.016666667 | K11: =H11+($B$9/12) -> 0.033333333 | N11: =K11+($B$9/12) -> 0.05 | Q11: =N11+($B$9/12) -> 0.066666667 | T11: =Q11+($B$9/12) -> 0.083333333 | W11: =T11+($B$9/12) -> 0.1 | Z11: =W11+($B$9/12) -> 0.11666667 | AC11: =Z11+($B$9/12) -> 0.13333333 | AF11: =AC11+($B$9/12) -> 0.15 | AI11: =AF11+($B$9/12) -> 0.16666667 | AJ11: 0 | AL11: =AI11+($B$9/12) -> 0.18333333 | AO11: =AL11+($B$9/12) -> 0.2 | AR11: =B9 -> 0.2
A12: Выполнение | H12: =H11/H10 -> 2.6222222 | K12: =K11/K10 -> 1.0346183 | N12: =N11/N10 -> 1.01017 | Q12: =Q11/Q10 -> 1.0645253 | T12: =T11/T10 -> 1.0149452 | W12: =W11/W10 -> 0 | Z12: =Z11/Z10 -> 0 | AC12: =AC11/AC10 -> 0 | AF12: =AF11/AF10 -> 0 | AI12: =AI11/AI10 -> 0 | AL12: =AL11/AL10 -> 0 | AO12: =AO11/AO10 -> 0 | AR12: =AR11/AR10 -> 1.0166667
B14: Месяц | C14: 5
A15: Текучесть в разрезе ЦФО | B15: План на 2026 | C15: План | D15: Факт | E15: % выполнения | F15: январь | I15: февраль | L15: март | O15: апрель | R15: май | U15: июнь | X15: июль | AA15: август | AD15: сентябрь | AG15: октябрь | AJ15: ноябрь | AM15: декабрь | AP15: ГОД
A16: ЦФО | F16: численность | G16: увольнение | H16: текучесть | I16: численность | J16: увольнение | K16: текучесть | L16: численность | M16: увольнение | N16: текучесть | O16: численность | P16: увольнение | Q16: текучесть | R16: численность | S16: увольнение | T16: текучесть | U16: численность | V16: увольнение | W16: текучесть | X16: численность | Y16: увольнение | Z16: текучесть | AA16: численность | AB16: увольнение | AC16: текучесть | AD16: численность | AE16: увольнение | AF16: текучесть | AG16: численность | AH16: увольнение | AI16: текучесть | AJ16: численность | AK16: увольнение | AL16: текучесть | AM16: численность | AN16: увольнение | AO16: текучесть | AP16: численность | AQ16: увольнение | AR16: текучесть
A17: ЦФО Амурская легенда (1 ур) | B17: 0.15 | C17: =B17/12*$C$14 -> 0.0625 | D17: =C17/12*$C$14 -> 0.026041667 | E17: =IF(D17>0%,C17/D17,100%) -> 2.4 | F17: 36 | H17: =G17/F17 -> 0 | I17: 35 | J17: 1 | K17: =J17/I17 -> 0.028571429 | L17: 37 | M17: 2 | N17: =M17/L17 -> 0.054054054 | Q17: =P17/O17 -> 0 | T17: =S17/R17 -> 0 | W17: =V17/U17 -> 0 | Z17: =Y17/X17 -> 0 | AC17: =AB17/AA17 -> 0 | AF17: =AE17/AD17 -> 0 | AI17: =AH17/AG17 -> 0 | AL17: =AK17/AJ17 -> 0 | AO17: =AN17/AM17 -> 0 | AP17: =AVERAGE(F17,I17,L17,O17,R17,U17,X17,AA17,AD17,AG17,AJ17,AM17) -> 36 | AQ17: =SUM(G17,J17,M17,P17,S17,V17,Y17,AB17,AE17,AH17,AK17,AN17) -> 3 | AR17: =AQ17/AP17 -> 0.083333333
A18: ЦФО Директор НПО (2 ур) | B18: 0.18 | C18: =B18/12*$C$14 -> 0.075 | D18: 0 | E18: =IF(D18>0%,C18/D18,100%) -> 1 | F18: =F57+F26+F41+F73+F68+F92+F61+F65+F22+1+3 -> 390 | G18: =G57+G26+G41+G73+G68+G92+G61+G65+G22+1+3 -> 7 | H18: =G18/F18 -> 0.017948718 | I18: =I57+I26+I41+I73+I68+I92+I61+I65+I22+1+3 -> 376 | K18: =J18/I18 -> 0 | L18: 15 | M18: 2 | N18: =M18/L18 -> 0.13333333 | Q18: =P18/O18 -> 0 | T18: =S18/R18 -> 0 | W18: =V18/U18 -> 0 | Z18: =Y18/X18 -> 0 | AC18: =AB18/AA18 -> 0 | AF18: =AE18/AD18 -> 0 | AI18: =AH18/AG18 -> 0 | AL18: =AK18/AJ18 -> 0 | AO18: =AN18/AM18 -> 0 | AP18: =AVERAGE(F18,I18,L18,O18,R18,U18,X18,AA18,AD18,AG18,AJ18,AM18) -> 260.33333 | AQ18: =SUM(G18,J18,M18,P18,S18,V18,Y18,AB18,AE18,AH18,AK18,AN18) -> 9 | AR18: =AQ18/AP18 -> 0.034571063
A19: СУП | B19: 0.1 | C19: =B19/12*$C$14 -> 0.041666667 | D19: =AR19 -> 0 | E19: =IF(D19>0%,C19/D19,100%) -> 1 | F19: 7 | H19: =G19/F19 -> 0 | I19: 7 | K19: =J19/I19 -> 0 | L19: 6 | N19: =M19/L19 -> 0 | O19: 6 | Q19: =P19/O19 -> 0 | R19: 6 | T19: =S19/R19 -> 0 | W19: =V19/U19 -> 0 | Z19: =Y19/X19 -> 0 | AC19: =AB19/AA19 -> 0 | AF19: =AE19/AD19 -> 0 | AI19: =AH19/AG19 -> 0 | AL19: =AK19/AJ19 -> 0 | AO19: =AN19/AM19 -> 0 | AP19: =AVERAGE(F19,I19,L19,O19,R19,U19,X19,AA19,AD19,AG19,AJ19,AM19) -> 6.4 | AQ19: =SUM(G19,J19,M19,P19,S19,V19,Y19,AB19,AE19,AH19,AK19,AN19) -> 0 | AR19: =AQ19/AP19 -> 0
A20: Бухгалтерия | B20: 0.04 | C20: =B20/12*$C$14 -> 0.016666667 | D20: =AR20 -> 0 | E20: =IF(D20>0%,C20/D20,100%) -> 1 | F20: 5 | H20: =G20/F20 -> 0 | I20: 8 | K20: =J20/I20 -> 0 | L20: 5 | N20: =M20/L20 -> 0 | O20: 5 | Q20: =P20/O20 -> 0 | R20: 5 | T20: =S20/R20 -> 0 | W20: =V20/U20 -> 0 | Z20: =Y20/X20 -> 0 | AC20: =AB20/AA20 -> 0 | AF20: =AE20/AD20 -> 0 | AI20: =AH20/AG20 -> 0 | AL20: =AK20/AJ20 -> 0 | AO20: =AN20/AM20 -> 0 | AP20: =AVERAGE(F20,I20,L20,O20,R20,U20,X20,AA20,AD20,AG20,AJ20,AM20) -> 5.6 | AQ20: =SUM(G20,J20,M20,P20,S20,V20,Y20,AB20,AE20,AH20,AK20,AN20) -> 0 | AR20: =AQ20/AP20 -> 0
A21: Экономический отдел | B21: 0.03 | C21: =B21/12*$C$14 -> 0.0125 | D21: =AR21 | E21: =IF(D21>0%,C21/D21,100%) -> 1 | F21: 5 | H21: =G21/F21 -> 0 | I21: 5 | K21: =J21/I21 -> 0 | L21: 4 | N21: =M21/L21 -> 0 | O21: 4 | Q21: =P21/O21 -> 0 | R21: 4 | T21: =S21/R21 -> 0 | W21: =V21/U21 -> 0 | Z21: =Y21/X21 -> 0 | AC21: =AB21/AA21 -> 0 | AF21: =AE21/AD21 -> 0 | AI21: =AH21/AG21 -> 0 | AL21: =AK21/AJ21 -> 0 | AO21: =AN21/AM21 -> 0 | AP21: =AVERAGE(F21,I21,L21,O21,R21,U21,X21,AA21,AD21,AG21,AJ21,AM21) -> 4.4
A22: ЦФО КБ (2 ур) | B22: 0.1 | C22: =B22/12*$C$14 -> 0.041666667 | D22: =AR22 -> 0.19753086 | E22: =IF(D22>0%,C22/D22,100%) -> 0.2109375 | F22: 23 | G22: =SUM(G23:G25) -> 0 | H22: =G22/F22 -> 0 | I22: 22 | J22: =SUM(J23:J25) -> 0 | K22: =J22/I22 -> 0 | L22: 20 | M22: 2 | N22: =M22/L22 -> 0.1 | O22: =O23+O24+O25 -> 16 | P22: =SUM(P23:P25) -> 0 | Q22: =P22/O22 -> 0 | S22: =SUM(S23:S25) -> 1 | T22: =S22/R22 -> 0 | V22: 1 | W22: =V22/U22 -> 0 | Y22: =SUM(Y23:Y25) -> 0 | Z22: =Y22/X22 -> 0 | AB22: =SUM(AB23:AB25) -> 0 | AC22: =AB22/AA22 -> 0 | AE22: =SUM(AE23:AE25) -> 0 | AF22: =AE22/AD22 -> 0 | AH22: =SUM(AH23:AH25) -> 0 | AI22: =AH22/AG22 -> 0 | AK22: =SUM(AK23:AK25) -> 0 | AL22: =AK22/AJ22 -> 0 | AN22: =SUM(AN23:AN25) -> 0 | AO22: =AN22/AM22 -> 0 | AP22: =AVERAGE(F22,I22,L22,O22,R22,U22,X22,AA22,AD22,AG22,AJ22,AM22) -> 20.25 | AQ22: =SUM(G22,J22,M22,P22,S22,V22,Y22,AB22,AE22,AH22,AK22,AN22) -> 4 | AR22: =AQ22/AP22 -> 0.19753086
A23: КБ | B23: 0.04 | C23: =B23/12*$C$14 -> 0.016666667 | D23: =AR23 -> 0.086206897 | E23: =IF(D23>0%,C23/D23,100%) -> 0.19333333 | F23: 13 | H23: =G23/F23 -> 0 | I23: 13 | K23: =J23/I23 -> 0 | L23: 11 | N23: =M23/L23 -> 0 | O23: 11 | Q23: =P23/O23 -> 0 | R23: 10 | S23: 1 | T23: =S23/R23 -> 0.1 | W23: =V23/U23 -> 0 | Z23: =Y23/X23 -> 0 | AC23: =AB23/AA23 -> 0 | AF23: =AE23/AD23 -> 0 | AI23: =AH23/AG23 -> 0 | AL23: =AK23/AJ23 -> 0 | AO23: =AN23/AM23 -> 0 | AP23: =AVERAGE(F23,I23,L23,O23,R23,U23,X23,AA23,AD23,AG23,AJ23,AM23) -> 11.6 | AQ23: =SUM(G23,J23,M23,P23,S23,V23,Y23,AB23,AE23,AH23,AK23,AN23) -> 1 | AR23: =AQ23/AP23 -> 0.086206897
A24: КТО | B24: 0.02 | C24: =B24/12*$C$14 -> 0.0083333333 | D24: =AR24 -> 0 | E24: =IF(D24>0%,C24/D24,100%) -> 1 | F24: 3 | H24: =G24/F24 -> 0 | I24: 3 | K24: =J24/I24 -> 0 | L24: 3 | N24: =M24/L24 -> 0 | O24: 3 | Q24: =P24/O24 -> 0 | R24: 3 | T24: =S24/R24 -> 0 | W24: =V24/U24 -> 0 | Z24: =Y24/X24 -> 0 | AC24: =AB24/AA24 -> 0 | AF24: =AE24/AD24 -> 0 | AI24: =AH24/AG24 -> 0 | AL24: =AK24/AJ24 -> 0 | AO24: =AN24/AM24 -> 0 | AP24: =AVERAGE(F24,I24,L24,O24,R24,U24,X24,AA24,AD24,AG24,AJ24,AM24) -> 3 | AQ24: =SUM(G24,J24,M24,P24,S24,V24,Y24,AB24,AE24,AH24,AK24,AN24) -> 0 | AR24: =AQ24/AP24 -> 0
A25: ПОиАСУ | B25: 0.02 | C25: =B25/12*$C$14 -> 0.0083333333 | D25: =AR25 -> 0 | E25: =IF(D25>0%,C25/D25,100%) -> 1 | F25: 2 | H25: =G25/F25 -> 0 | I25: 2 | K25: =J25/I25 -> 0 | L25: 2 | N25: =M25/L25 -> 0 | O25: 2 | Q25: =P25/O25 -> 0 | R25: 2 | T25: =S25/R25 -> 0 | W25: =V25/U25 -> 0 | Z25: =Y25/X25 -> 0 | AC25: =AB25/AA25 -> 0 | AF25: =AE25/AD25 -> 0 | AI25: =AH25/AG25 -> 0 | AL25: =AK25/AJ25 -> 0 | AO25: =AN25/AM25 -> 0 | AP25: =AVERAGE(F25,I25,L25,O25,R25,U25,X25,AA25,AD25,AG25,AJ25,AM25) -> 2 | AQ25: =SUM(G25,J25,M25,P25,S25,V25,Y25,AB25,AE25,AH25,AK25,AN25) -> 0 | AR25: =AQ25/AP25 -> 0
A26: ЦФО Ком.служба (2 ур) | B26: 0.17 | C26: =B26/12*$C$14 -> 0.070833333 | D26: =AR26 -> 0.20338983 | E26: =IF(D26>0%,C26/D26,100%) -> 0.34826389 | F26: 33 | G26: 1 | H26: =G26/F26 -> 0.03030303 | I26: 36 | J26: =SUM(J27:J34) -> 1 | K26: =J26/I26 -> 0.027777778 | L26: 36 | M26: =SUM(M27:M34) -> 0 | N26: =M26/L26 -> 0 | O26: 36 | P26: =SUM(P27:P34) -> 1 | Q26: =P26/O26 -> 0.027777778 | R26: =SUM(R27:R34) -> 36 | S26: =SUM(S27:S34) -> 0 | T26: =S26/R26 -> 0 | U26: =SUM(U27:U34) -> 0 | V26: =SUM(V27:V34) -> 0 | W26: =V26/U26 -> 0 | X26: =SUM(X27:X34) -> 0 | Y26: =SUM(Y27:Y34) -> 0 | Z26: =Y26/X26 -> 0 | AA26: =SUM(AA27:AA34) -> 0 | AB26: =SUM(AB27:AB34) -> 0 | AC26: =AB26/AA26 -> 0 | AD26: =SUM(AD27:AD34) -> 0 | AE26: =SUM(AE27:AE34) -> 0 | AF26: =AE26/AD26 -> 0 | AG26: =SUM(AG27:AG34) -> 0 | AH26: =SUM(AH27:AH34) -> 0 | AI26: =AH26/AG26 -> 0 | AJ26: =SUM(AJ27:AJ34) -> 0 | AK26: =SUM(AK27:AK34) -> 0 | AL26: =AK26/AJ26 -> 0 | AM26: =SUM(AM27:AM34) -> 0 | AN26: =SUM(AN27:AN34) -> 0 | AO26: =AN26/AM26 -> 0 | AP26: =AVERAGE(F26,I26,L26,O26,R26,U26,X26,AA26,AD26,AG26,AJ26,AM26) -> 14.75 | AQ26: =SUM(G26,J26,M26,P26,S26,V26,Y26,AB26,AE26,AH26,AK26,AN26) -> 3 | AR26: =AQ26/AP26 -> 0.20338983
A27: ОРКК | B27: 0.06 | C27: =B27/12*$C$14 -> 0.025 | D27: =AR27 -> 0 | E27: =IF(D27>0%,C27/D27,100%) -> 1 | F27: 5 | H27: =G27/F27 -> 0 | I27: 4 | K27: =J27/I27 -> 0 | L27: 6 | N27: =M27/L27 -> 0 | O27: 5 | Q27: =P27/O27 -> 0 | R27: 5 | T27: =S27/R27 -> 0 | W27: =V27/U27 -> 0 | Z27: =Y27/X27 -> 0 | AC27: =AB27/AA27 -> 0 | AF27: =AE27/AD27 -> 0 | AI27: =AH27/AG27 -> 0 | AL27: =AK27/AJ27 -> 0 | AO27: =AN27/AM27 -> 0 | AP27: =AVERAGE(F27,I27,L27,O27,R27,U27,X27,AA27,AD27,AG27,AJ27,AM27) -> 5 | AQ27: =SUM(G27,J27,M27,P27,S27,V27,Y27,AB27,AE27,AH27,AK27,AN27) -> 0 | AR27: =AQ27/AP27 -> 0
A28: Газпром | B28: 0.03 | C28: =B28/12*$C$14 -> 0.0125 | D28: =AR28 -> 0 | E28: =IF(D28>0%,C28/D28,100%) -> 1 | F28: 3 | H28: =G28/F28 -> 0 | I28: 3 | K28: =J28/I28 -> 0 | L28: 3 | N28: =M28/L28 -> 0 | O28: 3 | Q28: =P28/O28 -> 0 | R28: 3 | T28: =S28/R28 -> 0 | W28: =V28/U28 -> 0 | Z28: =Y28/X28 -> 0 | AC28: =AB28/AA28 -> 0 | AF28: =AE28/AD28 -> 0 | AI28: =AH28/AG28 -> 0 | AL28: =AK28/AJ28 -> 0 | AO28: =AN28/AM28 -> 0 | AP28: =AVERAGE(F28,I28,L28,O28,R28,U28,X28,AA28,AD28,AG28,AJ28,AM28) -> 3 | AQ28: =SUM(G28,J28,M28,P28,S28,V28,Y28,AB28,AE28,AH28,AK28,AN28) -> 0 | AR28: =AQ28/AP28 -> 0
A29: БМИ | B29: 0.1 | C29: =B29/12*$C$14 -> 0.041666667 | D29: =AR29 -> 0 | E29: =IF(D29>0%,C29/D29,100%) -> 1 | F29: 5 | H29: =G29/F29 -> 0 | I29: 4 | K29: =J29/I29 -> 0 | L29: 5 | N29: =M29/L29 -> 0 | O29: 3 | Q29: =P29/O29 -> 0 | R29: 4 | T29: =S29/R29 -> 0 | W29: =V29/U29 -> 0 | Z29: =Y29/X29 -> 0 | AC29: =AB29/AA29 -> 0 | AF29: =AE29/AD29 -> 0 | AI29: =AH29/AG29 -> 0 | AL29: =AK29/AJ29 -> 0 | AO29: =AN29/AM29 -> 0 | AP29: =AVERAGE(F29,I29,L29,O29,R29,U29,X29,AA29,AD29,AG29,AJ29,AM29) -> 4.2 | AQ29: =SUM(G29,J29,M29,P29,S29,V29,Y29,AB29,AE29,AH29,AK29,AN29) -> 0 | AR29: =AQ29/AP29 -> 0
A30: ОДП | B30: 0.1 | C30: =B30/12*$C$14 -> 0.041666667 | D30: =AR30 -> 0 | E30: =IF(D30>0%,C30/D30,100%) -> 1 | F30: 8 | H30: =G30/F30 -> 0 | I30: 9 | K30: =J30/I30 -> 0 | L30: 9 | N30: =M30/L30 -> 0 | O30: 9 | Q30: =P30/O30 -> 0 | R30: 9 | T30: =S30/R30 -> 0 | W30: =V30/U30 -> 0 | Z30: =Y30/X30 -> 0 | AC30: =AB30/AA30 -> 0 | AF30: =AE30/AD30 -> 0 | AI30: =AH30/AG30 -> 0 | AL30: =AK30/AJ30 -> 0 | AO30: =AN30/AM30 -> 0 | AP30: =AVERAGE(F30,I30,L30,O30,R30,U30,X30,AA30,AD30,AG30,AJ30,AM30) -> 8.8 | AQ30: =SUM(G30,J30,M30,P30,S30,V30,Y30,AB30,AE30,AH30,AK30,AN30) -> 0 | AR30: =AQ30/AP30 -> 0
A31: ВЭД | B31: 0.07 | C31: =B31/12*$C$14 -> 0.029166667 | D31: =AR31 -> 0.25 | E31: =IF(D31>0%,C31/D31,100%) -> 0.11666667 | F31: 4 | H31: =G31/F31 -> 0 | I31: 4 | J31: 1 | K31: =J31/I31 -> 0.25 | L31: 4 | N31: =M31/L31 -> 0 | O31: 4 | Q31: =P31/O31 -> 0 | R31: 4 | T31: =S31/R31 -> 0 | W31: =V31/U31 -> 0 | Z31: =Y31/X31 -> 0 | AC31: =AB31/AA31 -> 0 | AF31: =AE31/AD31 -> 0 | AI31: =AH31/AG31 -> 0 | AL31: =AK31/AJ31 -> 0 | AO31: =AN31/AM31 -> 0 | AP31: =AVERAGE(F31,I31,L31,O31,R31,U31,X31,AA31,AD31,AG31,AJ31,AM31) -> 4 | AQ31: =SUM(G31,J31,M31,P31,S31,V31,Y31,AB31,AE31,AH31,AK31,AN31) -> 1 | AR31: =AQ31/AP31 -> 0.25
A32: ОПМУ | B32: 0.05 | C32: =B32/12*$C$14 -> 0.020833333 | D32: =AR32 -> 0.18518519 | E32: =IF(D32>0%,C32/D32,100%) -> 0.1125 | F32: 5 | H32: =G32/F32 -> 0 | I32: 5 | K32: =J32/I32 -> 0 | L32: 5 | N32: =M32/L32 -> 0 | O32: 7 | P32: 1 | Q32: =P32/O32 -> 0.14285714 | R32: 5 | T32: =S32/R32 -> 0 | W32: =V32/U32 -> 0 | Z32: =Y32/X32 -> 0 | AC32: =AB32/AA32 -> 0 | AF32: =AE32/AD32 -> 0 | AI32: =AH32/AG32 -> 0 | AL32: =AK32/AJ32 -> 0 | AO32: =AN32/AM32 -> 0 | AP32: =AVERAGE(F32,I32,L32,O32,R32,U32,X32,AA32,AD32,AG32,AJ32,AM32) -> 5.4 | AQ32: =SUM(G32,J32,M32,P32,S32,V32,Y32,AB32,AE32,AH32,AK32,AN32) -> 1 | AR32: =AQ32/AP32 -> 0.18518519
A33: ТО | B33: 0 | C33: =B33/12*$C$14 -> 0 | D33: =AR33 | E33: =IF(D33>0%,C33/D33,100%) -> 1 | F33: 2 | H33: =G33/F33 -> 0 | I33: 2 | K33: =J33/I33 -> 0 | L33: 2 | N33: =M33/L33 -> 0 | O33: 4 | Q33: =P33/O33 -> 0 | R33: 4 | T33: =S33/R33 -> 0 | W33: =V33/U33 -> 0 | Z33: =Y33/X33 -> 0 | AC33: =AB33/AA33 -> 0 | AF33: =AE33/AD33 -> 0 | AI33: =AH33/AG33 -> 0 | AL33: =AK33/AJ33 -> 0 | AO33: =AN33/AM33 -> 0 | AP33: =AVERAGE(F33,I33,L33,O33,R33,U33,X33,AA33,AD33,AG33,AJ33,AM33) -> 2.8
A34: Сектор рекламы и PR | B34: 0 | C34: =B34/12*$C$14 -> 0 | D34: =AR34 -> 0 | E34: =IF(D34>0%,C34/D34,100%) -> 1 | F34: 1 | H34: =G34/F34 -> 0 | I34: 2 | K34: =J34/I34 -> 0 | L34: 2 | N34: =M34/L34 -> 0 | O34: 1 | Q34: =P34/O34 -> 0 | R34: 2 | T34: =S34/R34 -> 0 | W34: =V34/U34 -> 0 | Z34: =Y34/X34 -> 0 | AC34: =AB34/AA34 -> 0 | AF34: =AE34/AD34 -> 0 | AI34: =AH34/AG34 -> 0 | AL34: =AK34/AJ34 -> 0 | AO34: =AN34/AM34 -> 0 | AP34: =AVERAGE(F34,I34,L34,O34,R34,U34,X34,AA34,AD34,AG34,AJ34,AM34) -> 1.6 | AQ34: =SUM(G34,J34,M34,P34,S34,V34,Y34,AB34,AE34,AH34,AK34,AN34) -> 0 | AR34: =AQ34/AP34 -> 0
A35: ЦФО МГС (1 ур) | B35: 0.165 | C35: =B35/12*$C$14 -> 0.06875 | D35: =AR35 -> 0.073619632 | E35: =IF(D35>0%,C35/D35,100%) -> 0.93385417 | F35: 40 | H35: =G35/F35 -> 0 | I35: 42 | J35: 1 | K35: =J35/I35 -> 0.023809524 | L35: 41 | M35: 1 | N35: =M35/L35 -> 0.024390244 | O35: 40 | P35: 1 | Q35: =P35/O35 -> 0.025 | T35: =S35/R35 -> 0 | W35: =V35/U35 -> 0 | Z35: =Y35/X35 -> 0 | AC35: =AB35/AA35 -> 0 | AF35: =AE35/AD35 -> 0 | AI35: =AH35/AG35 -> 0 | AL35: =AK35/AJ35 -> 0 | AO35: =AN35/AM35 -> 0 | AP35: =AVERAGE(F35,I35,L35,O35,R35,U35,X35,AA35,AD35,AG35,AJ35,AM35) -> 40.75 | AQ35: =SUM(G35,J35,M35,P35,S35,V35,Y35,AB35,AE35,AH35,AK35,AN35) -> 3 | AR35: =AQ35/AP35 -> 0.073619632
A36: ЦФО Милака (1 ур) | B36: 0.12 | C36: =B36/12*$C$14 -> 0.05 | D36: =AR36 -> 0 | E36: =IF(D36>0%,C36/D36,100%) -> 1 | F36: =SUM(F37:F40) -> 17 | G36: =SUM(G37:G40) -> 0 | H36: =G36/F36 -> 0 | I36: =SUM(I37:I40) -> 17 | J36: =SUM(J37:J40) -> 0 | K36: =J36/I36 -> 0 | L36: 19 | M36: =SUM(M37:M40) -> 0 | N36: =M36/L36 -> 0 | O36: 17 | P36: =SUM(P37:P40) -> 0 | Q36: =P36/O36 -> 0 | R36: =SUM(R37:R40) -> 17 | S36: =SUM(S37:S40) -> 0 | T36: =S36/R36 -> 0 | U36: =SUM(U37:U40) -> 0 | V36: =SUM(V37:V40) -> 0 | W36: =V36/U36 -> 0 | X36: =SUM(X37:X40) -> 0 | Y36: =SUM(Y37:Y40) -> 0 | Z36: =Y36/X36 -> 0 | AA36: =SUM(AA37:AA40) -> 0 | AB36: =SUM(AB37:AB40) -> 0 | AC36: =AB36/AA36 -> 0 | AD36: =SUM(AD37:AD40) -> 0 | AE36: =SUM(AE37:AE40) -> 0 | AF36: =AE36/AD36 -> 0 | AG36: =SUM(AG37:AG40) -> 0 | AH36: =SUM(AH37:AH40) -> 0 | AI36: =AH36/AG36 -> 0 | AJ36: =SUM(AJ37:AJ40) -> 0 | AK36: =SUM(AK37:AK40) -> 0 | AL36: =AK36/AJ36 -> 0 | AM36: =SUM(AM37:AM40) -> 0 | AN36: =SUM(AN37:AN40) -> 0 | AO36: =AN36/AM36 -> 0 | AP36: =AVERAGE(F36,I36,L36,O36,R36,U36,X36,AA36,AD36,AG36,AJ36,AM36) -> 7.25 | AQ36: =SUM(G36,J36,M36,P36,S36,V36,Y36,AB36,AE36,AH36,AK36,AN36) -> 0 | AR36: =AQ36/AP36 -> 0
A37: администрация | B37: 0 | C37: =B37/12*$C$14 -> 0 | D37: =AR37 -> 0 | E37: =IF(D37>0%,C37/D37,100%) -> 1 | F37: 3 | H37: =G37/F37 -> 0 | I37: 3 | K37: =J37/I37 -> 0 | L37: 3 | N37: =M37/L37 -> 0 | Q37: =P37/O37 -> 0 | R37: 3 | T37: =S37/R37 -> 0 | W37: =V37/U37 -> 0 | Z37: =Y37/X37 -> 0 | AC37: =AB37/AA37 -> 0 | AF37: =AE37/AD37 -> 0 | AI37: =AH37/AG37 -> 0 | AL37: =AK37/AJ37 -> 0 | AO37: =AN37/AM37 -> 0 | AP37: =AVERAGE(F37,I37,L37,O37,R37,U37,X37,AA37,AD37,AG37,AJ37,AM37) -> 3 | AQ37: =SUM(G37,J37,M37,P37,S37,V37,Y37,AB37,AE37,AH37,AK37,AN37) -> 0 | AR37: =AQ37/AP37 -> 0
A38: СПиР | B38: 0.3 | C38: =B38/12*$C$14 -> 0.125 | D38: =AR38 -> 0 | E38: =IF(D38>0%,C38/D38,100%) -> 1 | F38: 6 | H38: =G38/F38 -> 0 | I38: 6 | K38: =J38/I38 -> 0 | L38: 6 | N38: =M38/L38 -> 0 | Q38: =P38/O38 -> 0 | R38: 6 | T38: =S38/R38 -> 0 | W38: =V38/U38 -> 0 | Z38: =Y38/X38 -> 0 | AC38: =AB38/AA38 -> 0 | AF38: =AE38/AD38 -> 0 | AI38: =AH38/AG38 -> 0 | AL38: =AK38/AJ38 -> 0 | AO38: =AN38/AM38 -> 0 | AP38: =AVERAGE(F38,I38,L38,O38,R38,U38,X38,AA38,AD38,AG38,AJ38,AM38) -> 6 | AQ38: =SUM(G38,J38,M38,P38,S38,V38,Y38,AB38,AE38,AH38,AK38,AN38) -> 0 | AR38: =AQ38/AP38 -> 0
A39: Хозслужба | B39: 0.05 | C39: =B39/12*$C$14 -> 0.020833333 | D39: =AR39 -> 0 | E39: =IF(D39>0%,C39/D39,100%) -> 1 | F39: 4 | H39: =G39/F39 -> 0 | I39: 4 | K39: =J39/I39 -> 0 | L39: 4 | N39: =M39/L39 -> 0 | Q39: =P39/O39 -> 0 | R39: 4 | T39: =S39/R39 -> 0 | W39: =V39/U39 -> 0 | Z39: =Y39/X39 -> 0 | AC39: =AB39/AA39 -> 0 | AF39: =AE39/AD39 -> 0 | AI39: =AH39/AG39 -> 0 | AL39: =AK39/AJ39 -> 0 | AO39: =AN39/AM39 -> 0 | AP39: =AVERAGE(F39,I39,L39,O39,R39,U39,X39,AA39,AD39,AG39,AJ39,AM39) -> 4 | AQ39: =SUM(G39,J39,M39,P39,S39,V39,Y39,AB39,AE39,AH39,AK39,AN39) -> 0 | AR39: =AQ39/AP39 -> 0
A40: СБ | B40: 0.3 | C40: =B40/12*$C$14 -> 0.125 | D40: =AR40 -> 0 | E40: =IF(D40>0%,C40/D40,100%) -> 1 | F40: 4 | H40: =G40/F40 -> 0 | I40: 4 | K40: =J40/I40 -> 0 | L40: 6 | N40: =M40/L40 -> 0 | Q40: =P40/O40 -> 0 | R40: 4 | T40: =S40/R40 -> 0 | W40: =V40/U40 -> 0 | Z40: =Y40/X40 -> 0 | AC40: =AB40/AA40 -> 0 | AF40: =AE40/AD40 -> 0 | AI40: =AH40/AG40 -> 0 | AL40: =AK40/AJ40 -> 0 | AO40: =AN40/AM40 -> 0 | AP40: =AVERAGE(F40,I40,L40,O40,R40,U40,X40,AA40,AD40,AG40,AJ40,AM40) -> 4.5 | AQ40: =SUM(G40,J40,M40,P40,S40,V40,Y40,AB40,AE40,AH40,AK40,AN40) -> 0 | AR40: =AQ40/AP40 -> 0
A41: ЦФО Производство №1 (1 ур) | B41: 0.15 | C41: =B41/12*$C$14 -> 0.0625 | D41: =AR41 -> 0.14687882 | E41: =IF(D41>0%,C41/D41,100%) -> 0.42552083 | F41: =F42+F43+F48+F54+F61+F65+F68 -> 204 | G41: =G42+G43+G48+G54+G61+G65+G68 -> 2 | H41: =G41/F41 -> 0.0098039216 | I41: =I42+I43+I48+I54+I61+I65+I68 -> 196 | J41: =J42+J43+J48+J54+J61+J65 -> 3 | K41: =J41/I41 -> 0.015306122 | L41: 102 | M41: =M42+M43+M48+M54+M61+M65+M68 -> 2 | N41: =M41/L41 -> 0.019607843 | O41: 111 | P41: =P42+P43+P48+P54+P61+P65+P68 -> 1 | Q41: =P41/O41 -> 0.009009009 | R41: =R42+R43+R48+R54+R61+R65+R68 -> 204 | S41: 2 | T41: =S41/R41 -> 0.0098039216 | U41: =U42+U43+U48+U54+U61+U65+U68 -> 0 | V41: =V42+V43+V48+V54+V61+V65+V68 -> 0 | W41: =V41/U41 -> 0 | X41: =X42+X43+X48+X54+X61+X65+X68 -> 0 | Y41: =Y42+Y43+Y48+Y54+Y61+Y65+Y68 -> 0 | Z41: =Y41/X41 -> 0 | AA41: =AA42+AA43+AA48+AA54+AA61+AA65+AA68 -> 0 | AB41: =AB42+AB43+AB48+AB54+AB61+AB65+AB68 -> 0 | AC41: =AB41/AA41 -> 0 | AD41: =AD42+AD43+AD48+AD54+AD61+AD65+AD68 -> 0 | AE41: =AE42+AE43+AE48+AE54+AE61+AE65+AE68 -> 0 | AF41: =AE41/AD41 -> 0 | AG41: =AG42+AG43+AG48+AG54+AG61+AG65+AG68 -> 0 | AH41: =AH42+AH43+AH48+AH54+AH61+AH65+AH68 -> 0 | AI41: =AH41/AG41 -> 0 | AJ41: =AJ42+AJ43+AJ48+AJ54+AJ61+AJ65+AJ68 -> 0 | AK41: =AK42+AK43+AK48+AK54+AK61+AK65+AK68 -> 0 | AL41: =AK41/AJ41 -> 0 | AM41: =AM42+AM43+AM48+AM54+AM61+AM65+AM68 -> 0 | AN41: =AN42+AN43+AN48+AN54+AN61+AN65+AN68 -> 0 | AO41: =AN41/AM41 -> 0 | AP41: =AVERAGE(F41,I41,L41,O41,R41,U41,X41,AA41,AD41,AG41,AJ41,AM41) -> 68.083333 | AQ41: =SUM(G41,J41,M41,P41,S41,V41,Y41,AB41,AE41,AH41,AK41,AN41) -> 10 | AR41: =AQ41/AP41 -> 0.14687882
A42: руководство (Целищев, Ермаков, Макеев) | B42: 0 | C42: =B42/12*$C$14 -> 0 | D42: =AR42 -> 0 | E42: =IF(D42>0%,C42/D42,100%) -> 1 | F42: 3 | H42: =G42/F42 -> 0 | I42: 3 | K42: =J42/I42 -> 0 | L42: 3 | N42: =M42/L42 -> 0 | O42: 3 | Q42: =P42/O42 -> 0 | R42: 3 | T42: =S42/R42 -> 0 | W42: =V42/U42 -> 0 | Z42: =Y42/X42 -> 0 | AC42: =AB42/AA42 -> 0 | AF42: =AE42/AD42 -> 0 | AI42: =AH42/AG42 -> 0 | AL42: =AK42/AJ42 -> 0 | AO42: =AN42/AM42 -> 0 | AP42: =AVERAGE(F42,I42,L42,O42,R42,U42,X42,AA42,AD42,AG42,AJ42,AM42) -> 3 | AQ42: =SUM(G42,J42,M42,P42,S42,V42,Y42,AB42,AE42,AH42,AK42,AN42) -> 0 | AR42: =AQ42/AP42 -> 0
A43: Ермаков | B43: 0.1 | C43: =B43/12*$C$14 -> 0.041666667 | D43: =AR43 | E43: =IF(D43>0%,C43/D43,100%) -> 1 | F43: =SUM(F44:F47) -> 21 | G43: =SUM(G44:G47) -> 0 | H43: =G43/F43 -> 0 | I43: =SUM(I44:I47) -> 20 | J43: =SUM(J44:J47) -> 1 | K43: =J43/I43 -> 0.05 | L43: =SUM(L44:L47) -> 20 | M43: =SUM(M44:M47) -> 0 | N43: =M43/L43 -> 0 | O43: =SUM(O44:O47) -> 20 | P43: =SUM(P44:P47) -> 0 | Q43: =P43/O43 -> 0 | R43: =SUM(R44:R47) -> 20 | S43: =SUM(S44:S47) -> 0 | T43: =S43/R43 -> 0 | U43: =SUM(U44:U47) -> 0 | V43: =SUM(V44:V47) -> 0 | W43: =V43/U43 -> 0 | X43: =SUM(X44:X47) -> 0 | Y43: =SUM(Y44:Y47) -> 0 | Z43: =Y43/X43 -> 0 | AA43: =SUM(AA44:AA47) -> 0 | AB43: =SUM(AB44:AB47) -> 0 | AC43: =AB43/AA43 -> 0 | AD43: =SUM(AD44:AD47) -> 0 | AE43: =SUM(AE44:AE47) -> 0 | AF43: =AE43/AD43 -> 0 | AG43: =SUM(AG44:AG47) -> 0 | AH43: =SUM(AH44:AH47) -> 0 | AI43: =AH43/AG43 -> 0 | AJ43: =SUM(AJ44:AJ47) -> 0 | AK43: =SUM(AK44:AK47) -> 0 | AL43: =AK43/AJ43 -> 0 | AM43: =SUM(AM44:AM47) -> 0 | AN43: =SUM(AN44:AN47) -> 0 | AO43: =AN43/AM43 -> 0 | AP43: =AVERAGE(F43,I43,L43,O43,R43,U43,X43,AA43,AD43,AG43,AJ43,AM43) -> 8.4166667
A44: Нохаева/сектор сопровождения продаж | B44: 0.05 | C44: =B44/12*$C$14 -> 0.020833333 | D44: =AR44 | E44: =IF(D44>0%,C44/D44,100%) -> 1 | F44: 3 | H44: =G44/F44 -> 0 | I44: 3 | K44: =J44/I44 -> 0 | L44: 5 | N44: =M44/L44 -> 0 | O44: 5 | Q44: =P44/O44 -> 0 | R44: 5 | T44: =S44/R44 -> 0 | W44: =V44/U44 -> 0 | Z44: =Y44/X44 -> 0 | AC44: =AB44/AA44 -> 0 | AF44: =AE44/AD44 -> 0 | AI44: =AH44/AG44 -> 0 | AL44: =AK44/AJ44 -> 0 | AO44: =AN44/AM44 -> 0 | AP44: =AVERAGE(F44,I44,L44,O44,R44,U44,X44,AA44,AD44,AG44,AJ44,AM44) -> 4.2
A45: Тимофеев/сектор сопровождения производства и продаж | B45: 0.05 | C45: =B45/12*$C$14 -> 0.020833333 | D45: =AR45 | E45: =IF(D45>0%,C45/D45,100%) -> 1 | F45: 8 | H45: =G45/F45 -> 0 | I45: 8 | K45: =J45/I45 -> 0 | L45: 6 | N45: =M45/L45 -> 0 | O45: 6 | Q45: =P45/O45 -> 0 | R45: 6 | T45: =S45/R45 -> 0 | W45: =V45/U45 -> 0 | Z45: =Y45/X45 -> 0 | AC45: =AB45/AA45 -> 0 | AF45: =AE45/AD45 -> 0 | AI45: =AH45/AG45 -> 0 | AL45: =AK45/AJ45 -> 0 | AO45: =AN45/AM45 -> 0 | AP45: =AVERAGE(F45,I45,L45,O45,R45,U45,X45,AA45,AD45,AG45,AJ45,AM45) -> 6.8
A46: Емельяненко/сектор доработки и улучшения серийной продукции | B46: 0.05 | C46: =B46/12*$C$14 -> 0.020833333 | D46: =AR46 | E46: =IF(D46>0%,C46/D46,100%) -> 1 | F46: 6 | H46: =G46/F46 -> 0 | I46: 5 | K46: =J46/I46 -> 0 | L46: 5 | N46: =M46/L46 -> 0 | O46: 5 | Q46: =P46/O46 -> 0 | R46: 5 | T46: =S46/R46 -> 0 | W46: =V46/U46 -> 0 | Z46: =Y46/X46 -> 0 | AC46: =AB46/AA46 -> 0 | AF46: =AE46/AD46 -> 0 | AI46: =AH46/AG46 -> 0 | AL46: =AK46/AJ46 -> 0 | AO46: =AN46/AM46 -> 0 | AP46: =AVERAGE(F46,I46,L46,O46,R46,U46,X46,AA46,AD46,AG46,AJ46,AM46) -> 5.2
A47: Асланян/сектор постановки на производство и несерийной продукции | B47: 0.05 | C47: =B47/12*$C$14 -> 0.020833333 | D47: =AR47 | E47: =IF(D47>0%,C47/D47,100%) -> 1 | F47: 4 | H47: =G47/F47 -> 0 | I47: 4 | J47: 1 | K47: =J47/I47 -> 0.25 | L47: 4 | N47: =M47/L47 -> 0 | O47: 4 | Q47: =P47/O47 -> 0 | R47: 4 | T47: =S47/R47 -> 0 | W47: =V47/U47 -> 0 | Z47: =Y47/X47 -> 0 | AC47: =AB47/AA47 -> 0 | AF47: =AE47/AD47 -> 0 | AI47: =AH47/AG47 -> 0 | AL47: =AK47/AJ47 -> 0 | AO47: =AN47/AM47 -> 0
A48: Макеев | B48: 0.2 | C48: =B48/12*$C$14 -> 0.083333333 | D48: =AR48 | E48: =IF(D48>0%,C48/D48,100%) -> 1 | F48: =SUM(F49:F53) -> 111 | G48: =SUM(G49:G53) -> 1 | H48: =G48/F48 -> 0.009009009 | I48: =SUM(I49:I53) -> 111 | J48: =SUM(J49:J53) -> 1 | K48: =J48/I48 -> 0.009009009 | L48: =SUM(L49:L53) -> 128 | M48: =SUM(M49:M53) -> 1 | N48: =M48/L48 -> 0.0078125 | O48: =SUM(O49:O53) -> 127 | P48: =SUM(P49:P53) -> 1 | Q48: =P48/O48 -> 0.0078740157 | R48: =SUM(R49:R53) -> 115 | S48: =SUM(S49:S53) -> 3 | T48: =S48/R48 -> 0.026086957 | U48: =SUM(U49:U53) -> 0 | V48: =SUM(V49:V53) -> 0 | W48: =V48/U48 -> 0 | X48: =SUM(X49:X53) -> 0 | Y48: =SUM(Y49:Y53) -> 0 | Z48: =Y48/X48 -> 0 | AA48: =SUM(AA49:AA53) -> 0 | AB48: =SUM(AB49:AB53) -> 0 | AC48: =AB48/AA48 -> 0 | AD48: =SUM(AD49:AD53) -> 0 | AE48: =SUM(AE49:AE53) -> 0 | AF48: =AE48/AD48 -> 0 | AG48: =SUM(AG49:AG53) -> 0 | AH48: =SUM(AH49:AH53) -> 0 | AI48: =AH48/AG48 -> 0 | AJ48: =SUM(AJ49:AJ53) -> 0 | AK48: =SUM(AK49:AK53) -> 0 | AL48: =AK48/AJ48 -> 0 | AM48: =SUM(AM49:AM53) -> 0 | AN48: =SUM(AN49:AN53) -> 0 | AO48: =AN48/AM48 -> 0
A49: ЦФО Производство №1/ИТР | B49: 0.08 | C49: =B49/12*$C$14 -> 0.033333333 | D49: =AR49 -> 0 | E49: =IF(D49>0%,C49/D49,100%) -> 1 | F49: 12 | H49: =G49/F49 -> 0 | I49: 16 | K49: =J49/I49 -> 0 | L49: 16 | N49: =M49/L49 -> 0 | O49: 28 | Q49: =P49/O49 -> 0 | R49: 7 | T49: =S49/R49 -> 0 | W49: =V49/U49 -> 0 | Z49: =Y49/X49 -> 0 | AC49: =AB49/AA49 -> 0 | AF49: =AE49/AD49 -> 0 | AI49: =AH49/AG49 -> 0 | AL49: =AK49/AJ49 -> 0 | AO49: =AN49/AM49 -> 0 | AP49: =AVERAGE(F49,I49,L49,O49,R49,U49,X49,AA49,AD49,AG49,AJ49,AM49) -> 15.8 | AQ49: =SUM(G49,J49,M49,P49,S49,V49,Y49,AB49,AE49,AH49,AK49,AN49) -> 0 | AR49: =AQ49/AP49 -> 0
A50: ЦФО Производство №1/рабочие МЦ | B50: 0.13 | C50: =B50/12*$C$14 -> 0.054166667 | D50: =AR50 -> 0.02293578 | E50: =IF(D50>0%,C50/D50,100%) -> 2.3616667 | F50: 39 | H50: =G50/F50 -> 0 | I50: 52 | K50: =J50/I50 -> 0 | L50: 52 | N50: =M50/L50 -> 0 | O50: 36 | Q50: =P50/O50 -> 0 | R50: 39 | S50: 1 | T50: =S50/R50 -> 0.025641026 | W50: =V50/U50 -> 0 | Z50: =Y50/X50 -> 0 | AC50: =AB50/AA50 -> 0 | AF50: =AE50/AD50 -> 0 | AI50: =AH50/AG50 -> 0 | AL50: =AK50/AJ50 -> 0 | AO50: =AN50/AM50 -> 0 | AP50: =AVERAGE(F50,I50,L50,O50,R50,U50,X50,AA50,AD50,AG50,AJ50,AM50) -> 43.6 | AQ50: =SUM(G50,J50,M50,P50,S50,V50,Y50,AB50,AE50,AH50,AK50,AN50) -> 1 | AR50: =AQ50/AP50 -> 0.02293578
A51: ЦФО Производство №1/рабочие ПЦ | B51: 0.13 | C51: =B51/12*$C$14 -> 0.054166667 | D51: =AR51 -> 0.070921986 | E51: =IF(D51>0%,C51/D51,100%) -> 0.76375 | F51: 29 | H51: =G51/F51 -> 0 | I51: 14 | K51: =J51/I51 -> 0 | L51: 33 | M51: 1 | N51: =M51/L51 -> 0.03030303 | O51: 30 | Q51: =P51/O51 -> 0 | R51: 35 | S51: 1 | T51: =S51/R51 -> 0.028571429 | W51: =V51/U51 -> 0 | Z51: =Y51/X51 -> 0 | AC51: =AB51/AA51 -> 0 | AF51: =AE51/AD51 -> 0 | AI51: =AH51/AG51 -> 0 | AL51: =AK51/AJ51 -> 0 | AO51: =AN51/AM51 -> 0 | AP51: =AVERAGE(F51,I51,L51,O51,R51,U51,X51,AA51,AD51,AG51,AJ51,AM51) -> 28.2 | AQ51: =SUM(G51,J51,M51,P51,S51,V51,Y51,AB51,AE51,AH51,AK51,AN51) -> 2 | AR51: =AQ51/AP51 -> 0.070921986
A52: ЦФО Производство №2 ИТР/бухгалтер | B52: 0 | C52: =B52/12*$C$14 -> 0 | D52: =AR52 | E52: =IF(D52>0%,C52/D52,100%) -> 1 | F52: 9 | H52: =G52/F52 -> 0 | I52: 2 | K52: =J52/I52 -> 0 | L52: 2 | N52: =M52/L52 -> 0 | O52: 6 | Q52: =P52/O52 -> 0 | R52: 7 | T52: =S52/R52 -> 0 | W52: =V52/U52 -> 0 | Z52: =Y52/X52 -> 0 | AC52: =AB52/AA52 -> 0 | AF52: =AE52/AD52 -> 0 | AI52: =AH52/AG52 -> 0 | AL52: =AK52/AJ52 -> 0 | AO52: =AN52/AM52 -> 0
A53: ЦФО Производство №2 Рабочие | B53: 0.2 | C53: =B53/12*$C$14 -> 0.083333333 | D53: =AR53 | E53: =IF(D53>0%,C53/D53,100%) -> 1 | F53: 22 | G53: 1 | H53: =G53/F53 -> 0.045454545 | I53: 27 | J53: 1 | K53: =J53/I53 -> 0.037037037 | L53: 25 | N53: =M53/L53 -> 0 | O53: 27 | P53: 1 | Q53: =P53/O53 -> 0.037037037 | R53: 27 | S53: 1 | T53: =S53/R53 -> 0.037037037 | W53: =V53/U53 -> 0 | Z53: =Y53/X53 -> 0 | AC53: =AB53/AA53 -> 0 | AF53: =AE53/AD53 -> 0 | AI53: =AH53/AG53 -> 0 | AL53: =AK53/AJ53 -> 0 | AO53: =AN53/AM53 -> 0
A54: Зайцев | B54: 0.15 | C54: =B54/12*$C$14 -> 0.0625 | D54: =AR54 | E54: =IF(D54>0%,C54/D54,100%) -> 1 | F54: =SUM(F55:F56) -> 15 | G54: =SUM(G55:G56) -> 1 | H54: =G54/F54 -> 0.066666667 | I54: =SUM(I55:I56) -> 13 | J54: =SUM(J55:J56) -> 1 | K54: =J54/I54 -> 0.076923077 | L54: =SUM(L55:L56) -> 17 | M54: =SUM(M55:M56) -> 0 | N54: =M54/L54 -> 0 | O54: =SUM(O55:O56) -> 17 | P54: =SUM(P55:P56) -> 0 | Q54: =P54/O54 -> 0 | R54: =SUM(R55:R56) -> 17 | S54: =SUM(S55:S56) -> 0 | T54: =S54/R54 -> 0 | U54: =SUM(U55:U56) -> 0 | V54: =SUM(V55:V56) -> 0 | W54: =V54/U54 -> 0 | X54: =SUM(X55:X56) -> 0 | Y54: =SUM(Y55:Y56) -> 0 | Z54: =Y54/X54 -> 0 | AA54: =SUM(AA55:AA56) -> 0 | AB54: =SUM(AB55:AB56) -> 0 | AC54: =AB54/AA54 -> 0 | AD54: =SUM(AD55:AD56) -> 0 | AE54: =SUM(AE55:AE56) -> 0 | AF54: =AE54/AD54 -> 0 | AG54: =SUM(AG55:AG56) -> 0 | AH54: =SUM(AH55:AH56) -> 0 | AI54: =AH54/AG54 -> 0 | AJ54: =SUM(AJ55:AJ56) -> 0 | AK54: =SUM(AK55:AK56) -> 0 | AL54: =AK54/AJ54 -> 0 | AM54: =SUM(AM55:AM56) -> 0 | AN54: =SUM(AN55:AN56) -> 0 | AO54: =AN54/AM54 -> 0 | AP54: =AVERAGE(F54,I54,L54,O54,R54,U54,X54,AA54,AD54,AG54,AJ54,AM54) -> 6.5833333
A55: несерийное производство ИТР (Гутин, Гайбарян, Сулейманова, Пелих, Кармаза) | B55: 0.05 | C55: =B55/12*$C$14 -> 0.020833333 | D55: =AR55 | E55: =IF(D55>0%,C55/D55,100%) -> 1 | F55: 6 | H55: =G55/F55 -> 0 | I55: 5 | J55: 1 | K55: =J55/I55 -> 0.2 | L55: 5 | N55: =M55/L55 -> 0 | O55: 5 | Q55: =P55/O55 -> 0 | R55: 5 | T55: =S55/R55 -> 0 | W55: =V55/U55 -> 0 | Z55: =Y55/X55 -> 0 | AC55: =AB55/AA55 -> 0 | AF55: =AE55/AD55 -> 0 | AI55: =AH55/AG55 -> 0 | AL55: =AK55/AJ55 -> 0 | AO55: =AN55/AM55 -> 0 | AP55: =AVERAGE(F55,I55,L55,O55,R55,U55,X55,AA55,AD55,AG55,AJ55,AM55) -> 5.2
A56: рабочие несерийное производство (БМИ+ЭЦ) | B56: 0.1 | C56: =B56/12*$C$14 -> 0.041666667 | D56: =AR56 | E56: =IF(D56>0%,C56/D56,100%) -> 1 | F56: 9 | G56: 1 | H56: =G56/F56 -> 0.11111111 | I56: 8 | K56: =J56/I56 -> 0 | L56: 12 | N56: =M56/L56 -> 0 | O56: 12 | Q56: =P56/O56 -> 0 | R56: 12 | T56: =S56/R56 -> 0 | W56: =V56/U56 -> 0 | Z56: =Y56/X56 -> 0 | AC56: =AB56/AA56 -> 0 | AF56: =AE56/AD56 -> 0 | AI56: =AH56/AG56 -> 0 | AL56: =AK56/AJ56 -> 0 | AO56: =AN56/AM56 -> 0 | AP56: =AVERAGE(F56,I56,L56,O56,R56,U56,X56,AA56,AD56,AG56,AJ56,AM56) -> 10.6
A57: ЦФО Главный метролог (1 ур) | B57: 0.1 | C57: =B57/12*$C$14 -> 0.041666667 | D57: =AR57 -> 0 | E57: =IF(D57>0%,C57/D57,100%) -> 1 | F57: =SUM(F58:F59) -> 17 | G57: =SUM(G58:G59) -> 0 | H57: =G57/F57 -> 0 | I57: =SUM(I58:I59) -> 17 | J57: =SUM(J58:J59) -> 0 | K57: =J57/I57 -> 0 | L57: 16 | M57: 0 | N57: =M57/L57 -> 0 | O57: =O58+O59+O60 -> 21 | P57: =SUM(P58:P59) -> 0 | Q57: =P57/O57 -> 0 | R57: =SUM(R58:R59) -> 16 | S57: =SUM(S58:S59) -> 0 | T57: =S57/R57 -> 0 | U57: =SUM(U58:U59) -> 0 | V57: =SUM(V58:V59) -> 0 | W57: =V57/U57 -> 0 | X57: =SUM(X58:X59) -> 0 | Y57: =SUM(Y58:Y59) -> 0 | Z57: =Y57/X57 -> 0 | AA57: =SUM(AA58:AA59) -> 0 | AB57: =SUM(AB58:AB59) -> 0 | AC57: =AB57/AA57 -> 0 | AD57: =SUM(AD58:AD59) -> 0 | AE57: =SUM(AE58:AE59) -> 0 | AF57: =AE57/AD57 -> 0 | AG57: =SUM(AG58:AG59) -> 0 | AH57: =SUM(AH58:AH59) -> 0 | AI57: =AH57/AG57 -> 0 | AJ57: =SUM(AJ58:AJ59) -> 0 | AK57: =SUM(AK58:AK59) -> 0 | AL57: =AK57/AJ57 -> 0 | AM57: =SUM(AM58:AM59) -> 0 | AN57: =SUM(AN58:AN59) -> 0 | AO57: =AN57/AM57 -> 0 | AP57: =AVERAGE(F57,I57,L57,O57,R57,U57,X57,AA57,AD57,AG57,AJ57,AM57) -> 7.25 | AQ57: =SUM(G57,J57,M57,P57,S57,V57,Y57,AB57,AE57,AH57,AK57,AN57) -> 0 | AR57: =AQ57/AP57 -> 0
A58: МС | B58: 0.08 | C58: =B58/12*$C$14 -> 0.033333333 | D58: =AR58 | E58: =AS58 | F58: 12 | H58: =G58/F58 -> 0 | I58: 12 | K58: =J58/I58 -> 0 | L58: 11 | N58: =M58/L58 -> 0 | O58: 11 | Q58: =P58/O58 -> 0 | R58: 11 | T58: =S58/R58 -> 0 | W58: =V58/U58 -> 0 | Z58: =Y58/X58 -> 0 | AC58: =AB58/AA58 -> 0 | AF58: =AE58/AD58 -> 0 | AI58: =AH58/AG58 -> 0 | AL58: =AK58/AJ58 -> 0 | AO58: =AN58/AM58 -> 0
A59: Рем.участок | B59: 0.02 | C59: =B59/12*$C$14 -> 0.0083333333 | D59: =AR59 | E59: =AS59 | F59: 5 | H59: =G59/F59 -> 0 | I59: 5 | K59: =J59/I59 -> 0 | L59: 5 | N59: =M59/L59 -> 0 | O59: 5 | Q59: =P59/O59 -> 0 | R59: 5 | T59: =S59/R59 -> 0 | W59: =V59/U59 -> 0 | Z59: =Y59/X59 -> 0 | AC59: =AB59/AA59 -> 0 | AF59: =AE59/AD59 -> 0 | AI59: =AH59/AG59 -> 0 | AL59: =AK59/AJ59 -> 0 | AO59: =AN59/AM59 -> 0
A60: ОМиС | B60: 0.02 | C60: =B60/12*$C$14 -> 0.0083333333 | D60: =AR60 -> 0.2173913 | E60: =IF(D60>0%,C60/D60,100%) -> 0.038333333 | F60: 5 | H60: =G60/F60 -> 0 | I60: 4 | J60: 1 | K60: =J60/I60 -> 0.25 | L60: 4 | N60: =M60/L60 -> 0 | O60: 5 | Q60: =P60/O60 -> 0 | R60: 5 | T60: =S60/R60 -> 0 | W60: =V60/U60 -> 0 | Z60: =Y60/X60 -> 0 | AC60: =AB60/AA60 -> 0 | AF60: =AE60/AD60 -> 0 | AI60: =AH60/AG60 -> 0 | AL60: =AK60/AJ60 -> 0 | AO60: =AN60/AM60 -> 0 | AP60: =AVERAGE(F60,I60,L60,O60,R60,U60,X60,AA60,AD60,AG60,AJ60,AM60) -> 4.6 | AQ60: =SUM(G60,J60,M60,P60,S60,V60,Y60,AB60,AE60,AH60,AK60,AN60) -> 1 | AR60: =AQ60/AP60 -> 0.2173913
A61: ЦФО Служба развития (2ур) | B61: 0.15 | C61: =B61/12*$C$14 -> 0.0625 | D61: =AR61 | E61: =IF(D61>0%,C61/D61,100%) -> 1 | F61: =SUM(F62:F64) -> 12 | G61: =SUM(G62:G64) -> 0 | H61: =G61/F61 -> 0 | I61: =SUM(I62:I64) -> 13 | J61: =SUM(J62:J64) -> 0 | K61: =J61/I61 -> 0 | L61: 14 | M61: 1 | N61: =M61/L61 -> 0.071428571 | O61: 12 | P61: =SUM(P62:P64) -> 0 | Q61: =P61/O61 -> 0 | R61: =SUM(R62:R64) -> 13 | S61: =SUM(S62:S64) -> 0 | T61: =S61/R61 -> 0 | U61: =SUM(U62:U64) -> 0 | V61: =SUM(V62:V64) -> 0 | W61: =V61/U61 -> 0 | X61: =SUM(X62:X64) -> 0 | Y61: =SUM(Y62:Y64) -> 0 | Z61: =Y61/X61 -> 0 | AA61: =SUM(AA62:AA64) -> 0 | AB61: =SUM(AB62:AB64) -> 0 | AC61: =AB61/AA61 -> 0 | AD61: =SUM(AD62:AD64) -> 0 | AE61: =SUM(AE62:AE64) -> 0 | AF61: =AE61/AD61 -> 0 | AG61: =SUM(AG62:AG64) -> 0 | AH61: =SUM(AH62:AH64) -> 0 | AI61: =AH61/AG61 -> 0 | AJ61: =SUM(AJ62:AJ64) -> 0 | AK61: =SUM(AK62:AK64) -> 0 | AL61: =AK61/AJ61 -> 0 | AM61: =SUM(AM62:AM64) -> 0 | AN61: =SUM(AN62:AN64) -> 0 | AO61: =AN61/AM61 -> 0
A62: Служба развития | B62: 0.09 | C62: =B62/12*$C$14 -> 0.0375 | D62: =AR62 | E62: =IF(D62>0%,C62/D62,100%) -> 1 | F62: 6 | H62: =G62/F62 -> 0 | I62: 2 | K62: =J62/I62 -> 0 | L62: 6 | N62: =M62/L62 -> 0 | O62: 6 | Q62: =P62/O62 -> 0 | R62: 6 | T62: =S62/R62 -> 0 | W62: =V62/U62 -> 0 | Z62: =Y62/X62 -> 0 | AC62: =AB62/AA62 -> 0 | AF62: =AE62/AD62 -> 0 | AI62: =AH62/AG62 -> 0 | AL62: =AK62/AJ62 -> 0 | AO62: =AN62/AM62 -> 0
A63: Сектор ИИ | B63: 0.06 | C63: =B63/12*$C$14 -> 0.025 | D63: =AR63 | E63: =IF(D63>0%,C63/D63,100%) -> 1 | F63: 4 | H63: =G63/F63 -> 0 | I63: 5 | K63: =J63/I63 -> 0 | L63: 5 | N63: =M63/L63 -> 0 | O63: 5 | Q63: =P63/O63 -> 0 | R63: 6 | T63: =S63/R63 -> 0 | W63: =V63/U63 -> 0 | Z63: =Y63/X63 -> 0 | AC63: =AB63/AA63 -> 0 | AF63: =AE63/AD63 -> 0 | AI63: =AH63/AG63 -> 0 | AL63: =AK63/AJ63 -> 0 | AO63: =AN63/AM63 -> 0
A64: Сектор обучения и развития | B64: 0 | C64: =B64/12*$C$14 -> 0 | D64: =AR64 | E64: =IF(D64>0%,C64/D64,100%) -> 1 | F64: 2 | H64: =G64/F64 -> 0 | I64: 6 | K64: =J64/I64 -> 0 | L64: 1 | M64: 1 | N64: =M64/L64 -> 1 | O64: 1 | Q64: =P64/O64 -> 0 | R64: 1 | T64: =S64/R64 -> 0 | W64: =V64/U64 -> 0 | Z64: =Y64/X64 -> 0 | AC64: =AB64/AA64 -> 0 | AF64: =AE64/AD64 -> 0 | AI64: =AH64/AG64 -> 0 | AL64: =AK64/AJ64 -> 0 | AO64: =AN64/AM64 -> 0
A65: ЦФО Служба автоматизации (2 ур) | B65: 0.1 | C65: =B65/12*$C$14 -> 0.041666667 | D65: =AR65 -> 0.4 | E65: =IF(D65>0%,C65/D65,100%) -> 0.10416667 | F65: =SUM(F66:F67) -> 6 | G65: =SUM(G66:G67) -> 0 | H65: =G65/F65 -> 0 | I65: =SUM(I66:I67) -> 6 | J65: =SUM(J66:J67) -> 0 | K65: =J65/I65 -> 0 | L65: 6 | M65: =SUM(M66:M67) -> 0 | N65: =M65/L65 -> 0 | O65: 6 | P65: =SUM(P66:P67) -> 0 | Q65: =P65/O65 -> 0 | R65: =SUM(R66:R67) -> 6 | S65: =SUM(S66:S67) -> 1 | T65: =S65/R65 -> 0.16666667 | U65: =SUM(U66:U67) -> 0 | V65: =SUM(V66:V67) -> 0 | W65: =V65/U65 -> 0 | X65: =SUM(X66:X67) -> 0 | Y65: =SUM(Y66:Y67) -> 0 | Z65: =Y65/X65 -> 0 | AA65: =SUM(AA66:AA67) -> 0 | AB65: =SUM(AB66:AB67) -> 0 | AC65: =AB65/AA65 -> 0 | AD65: =SUM(AD66:AD67) -> 0 | AE65: =SUM(AE66:AE67) -> 0 | AF65: =AE65/AD65 -> 0 | AG65: =SUM(AG66:AG67) -> 0 | AH65: =SUM(AH66:AH67) -> 0 | AI65: =AH65/AG65 -> 0 | AJ65: =SUM(AJ66:AJ67) -> 0 | AK65: =SUM(AK66:AK67) -> 0 | AL65: =AK65/AJ65 -> 0 | AM65: =SUM(AM66:AM67) -> 0 | AN65: =SUM(AN66:AN67) -> 0 | AO65: =AN65/AM65 -> 0 | AP65: =AVERAGE(F65,I65,L65,O65,R65,U65,X65,AA65,AD65,AG65,AJ65,AM65) -> 2.5 | AQ65: =SUM(G65,J65,M65,P65,S65,V65,Y65,AB65,AE65,AH65,AK65,AN65) -> 1 | AR65: =AQ65/AP65 -> 0.4
A66: 1С | B66: 0 | C66: =B66/12*$C$14 -> 0 | D66: =AR66 -> 0.25 | E66: 0.03 | F66: 4 | H66: =G66/F66 -> 0 | I66: 4 | K66: =J66/I66 -> 0 | L66: 4 | N66: =M66/L66 -> 0 | O66: 4 | Q66: =P66/O66 -> 0 | R66: 4 | S66: 1 | T66: =S66/R66 -> 0.25 | W66: =V66/U66 -> 0 | Z66: =Y66/X66 -> 0 | AC66: =AB66/AA66 -> 0 | AF66: =AE66/AD66 -> 0 | AI66: =AH66/AG66 -> 0 | AL66: =AK66/AJ66 -> 0 | AO66: =AN66/AM66 -> 0 | AP66: =AVERAGE(F66,I66,L66,O66,R66,U66,X66,AA66,AD66,AG66,AJ66,AM66) -> 4 | AQ66: =SUM(G66,J66,M66,P66,S66,V66,Y66,AB66,AE66,AH66,AK66,AN66) -> 1 | AR66: =AQ66/AP66 -> 0.25
A67: ИТ | B67: 0 | C67: =B67/12*$C$14 -> 0 | D67: =AR67 | E67: 0.03 | F67: 2 | H67: =G67/F67 -> 0 | I67: 2 | K67: =J67/I67 -> 0 | L67: 2 | N67: =M67/L67 -> 0 | O67: 2 | Q67: =P67/O67 -> 0 | R67: 2 | T67: =S67/R67 -> 0 | W67: =V67/U67 -> 0 | Z67: =Y67/X67 -> 0 | AC67: =AB67/AA67 -> 0 | AF67: =AE67/AD67 -> 0 | AI67: =AH67/AG67 -> 0 | AL67: =AK67/AJ67 -> 0 | AO67: =AN67/AM67 -> 0
A68: ЦФО Служба логистики (2 ур) | B68: 0.12 | C68: =B68/12*$C$14 -> 0.05 | D68: =AR68 -> 0.45 | E68: =IF(D68>0%,C68/D68,100%) -> 0.11111111 | F68: =SUM(F69:F72) -> 36 | G68: =SUM(G69:G72) -> 0 | H68: =G68/F68 -> 0 | I68: 30 | J68: =SUM(J69:J72) -> 3 | K68: =J68/I68 -> 0.1 | L68: 32 | M68: =SUM(M69:M72) -> 0 | N68: =M68/L68 -> 0 | O68: 32 | P68: =SUM(P69:P72) -> 0 | Q68: =P68/O68 -> 0 | R68: =SUM(R69:R72) -> 30 | S68: =SUM(S69:S72) -> 3 | T68: =S68/R68 -> 0.1 | U68: =SUM(U69:U72) -> 0 | V68: =SUM(V69:V72) -> 0 | W68: =V68/U68 -> 0 | X68: =SUM(X69:X72) -> 0 | Y68: =SUM(Y69:Y72) -> 0 | Z68: =Y68/X68 -> 0 | AA68: =SUM(AA69:AA72) -> 0 | AB68: =SUM(AB69:AB72) -> 0 | AC68: =AB68/AA68 -> 0 | AD68: =SUM(AD69:AD72) -> 0 | AE68: =SUM(AE69:AE72) -> 0 | AF68: =AE68/AD68 -> 0 | AG68: =SUM(AG69:AG72) -> 0 | AH68: =SUM(AH69:AH72) -> 0 | AI68: =AH68/AG68 -> 0 | AJ68: =SUM(AJ69:AJ72) -> 0 | AK68: =SUM(AK69:AK72) -> 0 | AL68: =AK68/AJ68 -> 0 | AM68: =SUM(AM69:AM72) -> 0 | AN68: =SUM(AN69:AN72) -> 0 | AO68: =AN68/AM68 -> 0 | AP68: =AVERAGE(F68,I68,L68,O68,R68,U68,X68,AA68,AD68,AG68,AJ68,AM68) -> 13.333333 | AQ68: =SUM(G68,J68,M68,P68,S68,V68,Y68,AB68,AE68,AH68,AK68,AN68) -> 6 | AR68: =AQ68/AP68 -> 0.45
A69: ОМТО | B69: 0.05 | C69: =B69/12*$C$14 -> 0.020833333 | D69: =AR69 -> 0.086206897 | E69: =IF(D69>0%,C69/D69,100%) -> 0.24166667 | F69: 11 | H69: =G69/F69 -> 0 | I69: 11 | K69: =J69/I69 -> 0 | L69: 12 | N69: =M69/L69 -> 0 | O69: 13 | Q69: =P69/O69 -> 0 | R69: 11 | S69: 1 | T69: =S69/R69 -> 0.090909091 | W69: =V69/U69 -> 0 | Z69: =Y69/X69 -> 0 | AC69: =AB69/AA69 -> 0 | AF69: =AE69/AD69 -> 0 | AI69: =AH69/AG69 -> 0 | AL69: =AK69/AJ69 -> 0 | AO69: =AN69/AM69 -> 0 | AP69: =AVERAGE(F69,I69,L69,O69,R69,U69,X69,AA69,AD69,AG69,AJ69,AM69) -> 11.6 | AQ69: =SUM(G69,J69,M69,P69,S69,V69,Y69,AB69,AE69,AH69,AK69,AN69) -> 1 | AR69: =AQ69/AP69 -> 0.086206897
A70: Склад | B70: 0.1 | C70: =B70/12*$C$14 -> 0.041666667 | D70: =AR70 -> 0.39215686 | E70: =IF(D70>0%,C70/D70,100%) -> 0.10625 | F70: 13 | H70: =G70/F70 -> 0 | I70: 9 | J70: 2 | K70: =J70/I70 -> 0.22222222 | L70: 10 | N70: =M70/L70 -> 0 | O70: 10 | Q70: =P70/O70 -> 0 | R70: 9 | S70: 2 | T70: =S70/R70 -> 0.22222222 | W70: =V70/U70 -> 0 | Z70: =Y70/X70 -> 0 | AC70: =AB70/AA70 -> 0 | AF70: =AE70/AD70 -> 0 | AI70: =AH70/AG70 -> 0 | AL70: =AK70/AJ70 -> 0 | AO70: =AN70/AM70 -> 0 | AP70: =AVERAGE(F70,I70,L70,O70,R70,U70,X70,AA70,AD70,AG70,AJ70,AM70) -> 10.2 | AQ70: =SUM(G70,J70,M70,P70,S70,V70,Y70,AB70,AE70,AH70,AK70,AN70) -> 4 | AR70: =AQ70/AP70 -> 0.39215686
A71: Склад БМИ | B71: 0 | C71: =B71/12*$C$14 -> 0 | D71: =AR71 -> 0.83333333 | E71: =IF(D71>0%,C71/D71,100%) -> 0 | F71: 2 | H71: =G71/F71 -> 0 | I71: 1 | J71: 1 | K71: =J71/I71 -> 1 | L71: 1 | N71: =M71/L71 -> 0 | O71: 1 | Q71: =P71/O71 -> 0 | R71: 1 | T71: =S71/R71 -> 0 | W71: =V71/U71 -> 0 | Z71: =Y71/X71 -> 0 | AC71: =AB71/AA71 -> 0 | AF71: =AE71/AD71 -> 0 | AI71: =AH71/AG71 -> 0 | AL71: =AK71/AJ71 -> 0 | AO71: =AN71/AM71 -> 0 | AP71: =AVERAGE(F71,I71,L71,O71,R71,U71,X71,AA71,AD71,AG71,AJ71,AM71) -> 1.2 | AQ71: =SUM(G71,J71,M71,P71,S71,V71,Y71,AB71,AE71,AH71,AK71,AN71) -> 1 | AR71: =AQ71/AP71 -> 0.83333333
A72: ТС | B72: 0.03 | C72: =B72/12*$C$14 -> 0.0125 | D72: =AR72 | E72: =IF(D72>0%,C72/D72,100%) -> 1 | F72: 10 | H72: =G72/F72 -> 0 | I72: 8 | K72: =J72/I72 -> 0 | L72: 9 | N72: =M72/L72 -> 0 | O72: 8 | Q72: =P72/O72 -> 0 | R72: 9 | T72: =S72/R72 -> 0 | W72: =V72/U72 -> 0 | Z72: =Y72/X72 -> 0 | AC72: =AB72/AA72 -> 0 | AF72: =AE72/AD72 -> 0 | AI72: =AH72/AG72 -> 0 | AL72: =AK72/AJ72 -> 0 | AO72: =AN72/AM72 -> 0 | AP72: =AVERAGE(F72,I72,L72,O72,R72,U72,X72,AA72,AD72,AG72,AJ72,AM72) -> 8.8
A73: ЦФО Технический директор (2 ур) | B73: 0.17 | C73: =B73/12*$C$14 -> 0.070833333 | D73: =AR73 -> 0.31168831 | E73: =IF(D73>0%,C73/D73,100%) -> 0.22725694 | F73: =SUM(F74+F80+F75+F76+F77+F78+F79+F85) -> 53 | G73: =SUM(G74+G80+G75+G76+G77+G78+G79+G85) -> 0 | H73: =G73/F73 -> 0 | I73: =SUM(I74+I80+I75+I76+I77+I78+I79+I85) -> 50 | J73: =SUM(J74+J80+J75+J76+J77+J78+J79+J85) -> 4 | K73: =J73/I73 -> 0.08 | L73: 38 | M73: =SUM(M74+M80+M75+M76+M77+M78+M79+M85) -> 0 | N73: =M73/L73 -> 0 | O73: 40 | P73: =SUM(P74+P80+P75+P76+P77+P78+P79+P85) -> 2 | Q73: =P73/O73 -> 0.05 | R73: =SUM(R74+R80+R75+R76+R77+R78+R79+R85) -> 50 | S73: =SUM(S74+S80+S75+S76+S77+S78+S79+S85) -> 0 | T73: =S73/R73 -> 0 | U73: =SUM(U74+U80+U75+U76+U77+U78+U79+U85) -> 0 | V73: =SUM(V74+V80+V75+V76+V77+V78+V79+V85) -> 0 | W73: =V73/U73 -> 0 | X73: =SUM(X74+X80+X75+X76+X77+X78+X79+X85) -> 0 | Y73: =SUM(Y74+Y80+Y75+Y76+Y77+Y78+Y79+Y85) -> 0 | Z73: =Y73/X73 -> 0 | AA73: =SUM(AA74+AA80+AA75+AA76+AA77+AA78+AA79+AA85) -> 0 | AB73: =SUM(AB74+AB80+AB75+AB76+AB77+AB78+AB79+AB85) -> 0 | AC73: =AB73/AA73 -> 0 | AD73: =SUM(AD74+AD80+AD75+AD76+AD77+AD78+AD79+AD85) -> 0 | AE73: =SUM(AE74+AE80+AE75+AE76+AE77+AE78+AE79+AE85) -> 0 | AF73: =AE73/AD73 -> 0 | AG73: =SUM(AG74+AG80+AG75+AG76+AG77+AG78+AG79+AG85) -> 0 | AH73: =SUM(AH74+AH80+AH75+AH76+AH77+AH78+AH79+AH85) -> 0 | AI73: =AH73/AG73 -> 0 | AJ73: =SUM(AJ74+AJ80+AJ75+AJ76+AJ77+AJ78+AJ79+AJ85) -> 0 | AK73: =SUM(AK74+AK80+AK75+AK76+AK77+AK78+AK79+AK85) -> 0 | AL73: =AK73/AJ73 -> 0 | AM73: =SUM(AM74+AM80+AM75+AM76+AM77+AM78+AM79+AM85) -> 0 | AN73: =SUM(AN74+AN80+AN75+AN76+AN77+AN78+AN79+AN85) -> 0 | AO73: =AN73/AM73 -> 0 | AP73: =AVERAGE(F73,I73,L73,O73,R73,U73,X73,AA73,AD73,AG73,AJ73,AM73) -> 19.25 | AQ73: =SUM(G73,J73,M73,P73,S73,V73,Y73,AB73,AE73,AH73,AK73,AN73) -> 6 | AR73: =AQ73/AP73 -> 0.31168831
A74: служба тех.дир | B74: 0 | C74: =B74/12*$C$14 -> 0 | D74: =AR74 -> 0 | E74: =IF(D74>0%,C74/D74,100%) -> 1 | F74: 3 | H74: =G74/F74 -> 0 | I74: 3 | K74: =J74/I74 -> 0 | L74: 3 | N74: =M74/L74 -> 0 | O74: 2 | Q74: =P74/O74 -> 0 | R74: 2 | T74: =S74/R74 -> 0 | W74: =V74/U74 -> 0 | Z74: =Y74/X74 -> 0 | AC74: =AB74/AA74 -> 0 | AF74: =AE74/AD74 -> 0 | AI74: =AH74/AG74 -> 0 | AL74: =AK74/AJ74 -> 0 | AO74: =AN74/AM74 -> 0 | AP74: =AVERAGE(F74,I74,L74,O74,R74,U74,X74,AA74,AD74,AG74,AJ74,AM74) -> 2.6 | AQ74: =SUM(G74,J74,M74,P74,S74,V74,Y74,AB74,AE74,AH74,AK74,AN74) -> 0 | AR74: =AQ74/AP74 -> 0
A75: ЭС | B75: 0.08 | C75: =B75/12*$C$14 -> 0.033333333 | D75: =AR75 | E75: =IF(D75>0%,C75/D75,100%) -> 1 | F75: 3 | H75: =G75/F75 -> 0 | I75: 3 | K75: =J75/I75 -> 0 | L75: 3 | N75: =M75/L75 -> 0 | O75: 3 | Q75: =P75/O75 -> 0 | R75: 3 | T75: =S75/R75 -> 0 | W75: =V75/U75 -> 0 | Z75: =Y75/X75 -> 0 | AC75: =AB75/AA75 -> 0 | AF75: =AE75/AD75 -> 0 | AI75: =AH75/AG75 -> 0 | AL75: =AK75/AJ75 -> 0 | AO75: =AN75/AM75 -> 0 | AP75: =AVERAGE(F75,I75,L75,O75,R75,U75,X75,AA75,AD75,AG75,AJ75,AM75) -> 3
A76: АХО | B76: 0.08 | C76: =B76/12*$C$14 -> 0.033333333 | D76: =AR76 | E76: =IF(D76>0%,C76/D76,100%) -> 1 | F76: 6 | H76: =G76/F76 -> 0 | I76: 7 | K76: =J76/I76 -> 0 | L76: 7 | N76: =M76/L76 -> 0 | O76: 7 | Q76: =P76/O76 -> 0 | R76: 7 | T76: =S76/R76 -> 0 | W76: =V76/U76 -> 0 | Z76: =Y76/X76 -> 0 | AC76: =AB76/AA76 -> 0 | AF76: =AE76/AD76 -> 0 | AI76: =AH76/AG76 -> 0 | AL76: =AK76/AJ76 -> 0 | AO76: =AN76/AM76 -> 0
A77: Качество разработки | B77: 0 | C77: =B77/12*$C$14 -> 0 | D77: =AR77 | E77: =IF(D77>0%,C77/D77,100%) -> 1 | F77: 2 | H77: =G77/F77 -> 0 | I77: 2 | K77: =J77/I77 -> 0 | L77: 2 | N77: =M77/L77 -> 0 | O77: 2 | P77: 1 | Q77: =P77/O77 -> 0.5 | R77: 2 | T77: =S77/R77 -> 0 | W77: =V77/U77 -> 0 | Z77: =Y77/X77 -> 0 | AC77: =AB77/AA77 -> 0 | AF77: =AE77/AD77 -> 0 | AI77: =AH77/AG77 -> 0 | AL77: =AK77/AJ77 -> 0 | AO77: =AN77/AM77 -> 0
A78: Щербина/Сектор разработки тех.решений | B78: 0.08 | C78: =B78/12*$C$14 -> 0.033333333 | D78: =AR78 | E78: =IF(D78>0%,C78/D78,100%) -> 1 | F78: 6 | H78: =G78/F78 -> 0 | I78: 5 | J78: 1 | K78: =J78/I78 -> 0.2 | L78: 5 | N78: =M78/L78 -> 0 | O78: 5 | Q78: =P78/O78 -> 0 | R78: 5 | T78: =S78/R78 -> 0 | W78: =V78/U78 -> 0 | Z78: =Y78/X78 -> 0 | AC78: =AB78/AA78 -> 0 | AF78: =AE78/AD78 -> 0 | AI78: =AH78/AG78 -> 0 | AL78: =AK78/AJ78 -> 0 | AO78: =AN78/AM78 -> 0
A79: Мещерюк/Сектор по пром.безопасности | B79: 0.05 | C79: =B79/12*$C$14 -> 0.020833333 | D79: =AR79 | E79: =IF(D79>0%,C79/D79,100%) -> 1 | F79: 3 | H79: =G79/F79 -> 0 | I79: 2 | J79: 1 | K79: =J79/I79 -> 0.5 | L79: 3 | N79: =M79/L79 -> 0 | O79: 3 | Q79: =P79/O79 -> 0 | R79: 3 | T79: =S79/R79 -> 0 | W79: =V79/U79 -> 0 | Z79: =Y79/X79 -> 0 | AC79: =AB79/AA79 -> 0 | AF79: =AE79/AD79 -> 0 | AI79: =AH79/AG79 -> 0 | AL79: =AK79/AJ79 -> 0 | AO79: =AN79/AM79 -> 0
A80: Арсуноев | B80: 0.08 | C80: =B80/12*$C$14 -> 0.033333333 | D80: =AR80 | E80: =IF(D80>0%,C80/D80,100%) -> 1 | F80: =SUM(F81:F84) -> 16 | G80: =SUM(G81:G84) -> 0 | H80: =G80/F80 -> 0 | I80: =SUM(I81:I84) -> 15 | J80: =SUM(J81:J84) -> 1 | K80: =J80/I80 -> 0.066666667 | L80: =SUM(L81:L84) -> 15 | M80: =SUM(M81:M84) -> 0 | N80: =M80/L80 -> 0 | O80: =SUM(O81:O84) -> 13 | P80: =SUM(P81:P84) -> 1 | Q80: =P80/O80 -> 0.076923077 | R80: =SUM(R81:R84) -> 15 | S80: =SUM(S81:S84) -> 0 | T80: =S80/R80 -> 0 | U80: =SUM(U81:U84) -> 0 | V80: =SUM(V81:V84) -> 0 | W80: =V80/U80 -> 0 | X80: =SUM(X81:X84) -> 0 | Y80: =SUM(Y81:Y84) -> 0 | Z80: =Y80/X80 -> 0 | AA80: =SUM(AA81:AA84) -> 0 | AB80: =SUM(AB81:AB84) -> 0 | AC80: =AB80/AA80 -> 0 | AD80: =SUM(AD81:AD84) -> 0 | AE80: =SUM(AE81:AE84) -> 0 | AF80: =AE80/AD80 -> 0 | AG80: =SUM(AG81:AG84) -> 0 | AH80: =SUM(AH81:AH84) -> 0 | AI80: =AH80/AG80 -> 0 | AJ80: =SUM(AJ81:AJ84) -> 0 | AK80: =SUM(AK81:AK84) -> 0 | AL80: =AK80/AJ80 -> 0 | AM80: =SUM(AM81:AM84) -> 0 | AN80: =SUM(AN81:AN84) -> 0 | AO80: =AN80/AM80 -> 0
A81: ОТК1 | B81: Служба | C81: =B81/12*$C$14 -> 0 | D81: =AR81 | E81: =IF(D81>0%,C81/D81,100%) -> 1 | F81: 9 | H81: =G81/F81 -> 0 | I81: 9 | K81: =J81/I81 -> 0 | L81: 9 | N81: =M81/L81 -> 0 | O81: 9 | Q81: =P81/O81 -> 0 | R81: 9 | T81: =S81/R81 -> 0 | W81: =V81/U81 -> 0 | Z81: =Y81/X81 -> 0 | AC81: =AB81/AA81 -> 0 | AF81: =AE81/AD81 -> 0 | AI81: =AH81/AG81 -> 0 | AL81: =AK81/AJ81 -> 0 | AO81: =AN81/AM81 -> 0
A82: ОТК2 | B82: 0 | C82: =B82/12*$C$14 -> 0 | D82: =AR82 | E82: =IF(D82>0%,C82/D82,100%) -> 1 | F82: 1 | H82: =G82/F82 -> 0 | I82: 1 | K82: =J82/I82 -> 0 | L82: 1 | N82: =M82/L82 -> 0 | O82: 0 | P82: 1 | Q82: =P82/O82 -> 0 | R82: 1 | T82: =S82/R82 -> 0 | W82: =V82/U82 -> 0 | Z82: =Y82/X82 -> 0 | AC82: =AB82/AA82 -> 0 | AF82: =AE82/AD82 -> 0 | AI82: =AH82/AG82 -> 0 | AL82: =AK82/AJ82 -> 0 | AO82: =AN82/AM82 -> 0
A83: ЛНК | B83: 0 | C83: =B83/12*$C$14 -> 0 | D83: =AR83 | E83: =IF(D83>0%,C83/D83,100%) -> 1 | F83: 3 | H83: =G83/F83 -> 0 | I83: 2 | J83: 1 | K83: =J83/I83 -> 0.5 | L83: 2 | N83: =M83/L83 -> 0 | O83: 2 | Q83: =P83/O83 -> 0 | R83: 2 | T83: =S83/R83 -> 0 | W83: =V83/U83 -> 0 | Z83: =Y83/X83 -> 0 | AC83: =AB83/AA83 -> 0 | AF83: =AE83/AD83 -> 0 | AI83: =AH83/AG83 -> 0 | AL83: =AK83/AJ83 -> 0 | AO83: =AN83/AM83 -> 0
A84: СК | B84: 0 | C84: =B84/12*$C$14 -> 0 | D84: =AR84 | E84: =IF(D84>0%,C84/D84,100%) -> 1 | F84: 3 | H84: =G84/F84 -> 0 | I84: 3 | K84: =J84/I84 -> 0 | L84: 3 | N84: =M84/L84 -> 0 | O84: 2 | Q84: =P84/O84 -> 0 | R84: 3 | T84: =S84/R84 -> 0 | W84: =V84/U84 -> 0 | Z84: =Y84/X84 -> 0 | AC84: =AB84/AA84 -> 0 | AF84: =AE84/AD84 -> 0 | AI84: =AH84/AG84 -> 0 | AL84: =AK84/AJ84 -> 0 | AO84: =AN84/AM84 -> 0
A85: ЦФО Сервисная служба (1+2 ур) | B85: 0.12 | C85: =B85/12*$C$14 -> 0.05 | D85: =AR85 -> 0.18181818 | E85: =IF(D85>0%,C85/D85,100%) -> 0.275 | F85: =SUM(F86:F88) -> 14 | G85: =SUM(G86:G88) -> 0 | H85: =G85/F85 -> 0 | I85: =SUM(I86:I88) -> 13 | J85: =SUM(J86:J88) -> 1 | K85: =J85/I85 -> 0.076923077 | L85: 13 | M85: =SUM(M86:M88) -> 0 | N85: =M85/L85 -> 0 | O85: 13 | P85: =SUM(P86:P88) -> 0 | Q85: =P85/O85 -> 0 | R85: =SUM(R86:R88) -> 13 | S85: =SUM(S86:S88) -> 0 | T85: =S85/R85 -> 0 | U85: =SUM(U86:U88) -> 0 | V85: =SUM(V86:V88) -> 0 | W85: =V85/U85 -> 0 | X85: =SUM(X86:X88) -> 0 | Y85: =SUM(Y86:Y88) -> 0 | Z85: =Y85/X85 -> 0 | AA85: =SUM(AA86:AA88) -> 0 | AB85: =SUM(AB86:AB88) -> 0 | AC85: =AB85/AA85 -> 0 | AD85: =SUM(AD86:AD88) -> 0 | AE85: =SUM(AE86:AE88) -> 0 | AF85: =AE85/AD85 -> 0 | AG85: =SUM(AG86:AG88) -> 0 | AH85: =SUM(AH86:AH88) -> 0 | AI85: =AH85/AG85 -> 0 | AJ85: =SUM(AJ86:AJ88) -> 0 | AK85: =SUM(AK86:AK88) -> 0 | AL85: =AK85/AJ85 -> 0 | AM85: =SUM(AM86:AM88) -> 0 | AN85: =SUM(AN86:AN88) -> 0 | AO85: =AN85/AM85 -> 0 | AP85: =AVERAGE(F85,I85,L85,O85,R85,U85,X85,AA85,AD85,AG85,AJ85,AM85) -> 5.5 | AQ85: =SUM(G85,J85,M85,P85,S85,V85,Y85,AB85,AE85,AH85,AK85,AN85) -> 1 | AR85: =AQ85/AP85 -> 0.18181818
A86: СС | B86: 0.09 | C86: =B86/12*$C$14 -> 0.0375 | D86: =AR86 -> 0.19230769 | E86: =IF(D86>0%,C86/D86,100%) -> 0.195 | F86: 6 | H86: =G86/F86 -> 0 | I86: 5 | J86: 1 | K86: =J86/I86 -> 0.2 | L86: 5 | N86: =M86/L86 -> 0 | O86: 5 | Q86: =P86/O86 -> 0 | R86: 5 | T86: =S86/R86 -> 0 | W86: =V86/U86 -> 0 | Z86: =Y86/X86 -> 0 | AC86: =AB86/AA86 -> 0 | AF86: =AE86/AD86 -> 0 | AI86: =AH86/AG86 -> 0 | AL86: =AK86/AJ86 -> 0 | AO86: =AN86/AM86 -> 0 | AP86: =AVERAGE(F86,I86,L86,O86,R86,U86,X86,AA86,AD86,AG86,AJ86,AM86) -> 5.2 | AQ86: =SUM(G86,J86,M86,P86,S86,V86,Y86,AB86,AE86,AH86,AK86,AN86) -> 1 | AR86: =AQ86/AP86 -> 0.19230769
A87: ОТП | B87: 0.09 | C87: =B87/12*$C$14 -> 0.0375 | D87: =AR87 -> 0 | E87: =IF(D87>0%,C87/D87,100%) -> 1 | F87: 5 | H87: =G87/F87 -> 0 | I87: 5 | K87: =J87/I87 -> 0 | L87: 5 | N87: =M87/L87 -> 0 | O87: 5 | Q87: =P87/O87 -> 0 | R87: 5 | T87: =S87/R87 -> 0 | W87: =V87/U87 -> 0 | Z87: =Y87/X87 -> 0 | AC87: =AB87/AA87 -> 0 | AF87: =AE87/AD87 -> 0 | AI87: =AH87/AG87 -> 0 | AL87: =AK87/AJ87 -> 0 | AO87: =AN87/AM87 -> 0 | AP87: =AVERAGE(F87,I87,L87,O87,R87,U87,X87,AA87,AD87,AG87,AJ87,AM87) -> 5 | AQ87: =SUM(G87,J87,M87,P87,S87,V87,Y87,AB87,AE87,AH87,AK87,AN87) -> 0 | AR87: =AQ87/AP87 -> 0
A88: Отдел рекламаций | B88: 0 | C88: =B88/12*$C$14 -> 0 | D88: =AR88 -> 0 | E88: =IF(D88>0%,C88/D88,100%) -> 1 | F88: 3 | H88: =G88/F88 -> 0 | I88: 3 | K88: =J88/I88 -> 0 | L88: 3 | N88: =M88/L88 -> 0 | O88: 3 | Q88: =P88/O88 -> 0 | R88: 3 | T88: =S88/R88 -> 0 | W88: =V88/U88 -> 0 | Z88: =Y88/X88 -> 0 | AC88: =AB88/AA88 -> 0 | AF88: =AE88/AD88 -> 0 | AI88: =AH88/AG88 -> 0 | AL88: =AK88/AJ88 -> 0 | AO88: =AN88/AM88 -> 0 | AP88: =AVERAGE(F88,I88,L88,O88,R88,U88,X88,AA88,AD88,AG88,AJ88,AM88) -> 3 | AQ88: =SUM(G88,J88,M88,P88,S88,V88,Y88,AB88,AE88,AH88,AK88,AN88) -> 0 | AR88: =AQ88/AP88 -> 0
A89: ЦФО Руководство (2 ур) | B89: 0.05 | C89: =B89/12*$C$14 -> 0.020833333 | D89: =AR89 -> 0.25 | E89: =IF(D89>0%,C89/D89,100%) -> 0.083333333 | F89: =SUM(F90:F92)+5 -> 13 | G89: =SUM(G90:G92) -> 0 | H89: =G89/F89 -> 0 | I89: =SUM(I90:I92)+5 -> 13 | J89: =SUM(J90:J92) -> 0 | K89: =J89/I89 -> 0 | L89: =SUM(L90:L92)+5 -> 12 | M89: 1 | N89: =M89/L89 -> 0.083333333 | O89: 11 | P89: 1 | Q89: =P89/O89 -> 0.090909091 | R89: 12 | S89: =SUM(S90:S92) -> 0 | T89: =S89/R89 -> 0 | U89: =SUM(U90:U92)+5 -> 5 | V89: =SUM(V90:V92) -> 0 | W89: =V89/U89 -> 0 | X89: =SUM(X90:X92)+5 -> 5 | Y89: =SUM(Y90:Y92) -> 0 | Z89: =Y89/X89 -> 0 | AA89: =SUM(AA90:AA92)+5 -> 5 | AB89: =SUM(AB90:AB92) -> 0 | AC89: =AB89/AA89 -> 0 | AD89: =SUM(AD90:AD92)+5 -> 5 | AE89: =SUM(AE90:AE92) -> 0 | AF89: =AE89/AD89 -> 0 | AG89: =SUM(AG90:AG92)+5 -> 5 | AH89: =SUM(AH90:AH92) -> 0 | AI89: =AH89/AG89 -> 0 | AJ89: =SUM(AJ90:AJ92)+5 -> 5 | AK89: =SUM(AK90:AK92) -> 0 | AL89: =AK89/AJ89 -> 0 | AM89: =SUM(AM90:AM92)+5 -> 5 | AN89: =SUM(AN90:AN92) -> 0 | AO89: =AN89/AM89 -> 0 | AP89: =AVERAGE(F89,I89,L89,O89,R89,U89,X89,AA89,AD89,AG89,AJ89,AM89) -> 8 | AQ89: =SUM(G89,J89,M89,P89,S89,V89,Y89,AB89,AE89,AH89,AK89,AN89) -> 2 | AR89: =AQ89/AP89 -> 0.25
A90: УД | B90: 0.03 | C90: =B90/12*$C$14 -> 0.0125 | D90: =AR90 -> 0.29411765 | E90: =IF(D90>0%,C90/D90,100%) -> 0.0425 | F90: 4 | H90: =G90/F90 -> 0 | I90: 4 | K90: =J90/I90 -> 0 | L90: 3 | N90: =M90/L90 -> 0 | O90: 3 | P90: 1 | Q90: =P90/O90 -> 0.33333333 | R90: 3 | T90: =S90/R90 -> 0 | W90: =V90/U90 -> 0 | Z90: =Y90/X90 -> 0 | AC90: =AB90/AA90 -> 0 | AF90: =AE90/AD90 -> 0 | AI90: =AH90/AG90 -> 0 | AL90: =AK90/AJ90 -> 0 | AO90: =AN90/AM90 -> 0 | AP90: =AVERAGE(F90,I90,L90,O90,R90,U90,X90,AA90,AD90,AG90,AJ90,AM90) -> 3.4 | AQ90: =SUM(G90,J90,M90,P90,S90,V90,Y90,AB90,AE90,AH90,AK90,AN90) -> 1 | AR90: =AQ90/AP90 -> 0.29411765
A91: Рвизионная комиссия | B91: 0 | C91: =B91/12*$C$14 -> 0 | D91: =AR91 | E91: =IF(D91>0%,C91/D91,100%) -> 1 | F91: 2 | H91: =G91/F91 -> 0 | I91: 2 | K91: =J91/I91 -> 0 | L91: 2 | N91: =M91/L91 -> 0 | O91: 2 | Q91: =P91/O91 -> 0 | R91: 7 | T91: =S91/R91 -> 0 | W91: =V91/U91 -> 0 | Z91: =Y91/X91 -> 0 | AC91: =AB91/AA91 -> 0 | AF91: =AE91/AD91 -> 0 | AI91: =AH91/AG91 -> 0 | AL91: =AK91/AJ91 -> 0 | AO91: =AN91/AM91 -> 0 | AP91: =AVERAGE(F91,I91,L91,O91,R91,U91,X91,AA91,AD91,AG91,AJ91,AM91) -> 3
A92: Юр. отдел | B92: 0 | C92: =B92/12*$C$14 -> 0 | D92: =AR92 | E92: =IF(D92>0%,C92/D92,100%) -> 1 | F92: 2 | H92: =G92/F92 -> 0 | I92: 2 | K92: =J92/I92 -> 0 | L92: 2 | N92: =M92/L92 -> 0 | O92: 2 | Q92: =P92/O92 -> 0 | R92: 2 | T92: =S92/R92 -> 0 | W92: =V92/U92 -> 0 | Z92: =Y92/X92 -> 0 | AC92: =AB92/AA92 -> 0 | AF92: =AE92/AD92 -> 0 | AI92: =AH92/AG92 -> 0 | AL92: =AK92/AJ92 -> 0 | AO92: =AN92/AM92 -> 0 | AP92: =AVERAGE(F92,I92,L92,O92,R92,U92,X92,AA92,AD92,AG92,AJ92,AM92) -> 2
A93: ЦФО Служба безопасности (2 ур) | B93: 0.09 | C93: =B93/12*$C$14 -> 0.0375 | D93: =AR93 -> 0.13333333 | E93: =IF(D93>0%,C93/D93,100%) -> 0.28125 | F93: =SUM(F94:F95) -> 18 | G93: =SUM(G94:G95) -> 0 | H93: =G93/F93 -> 0 | I93: =SUM(I94:I95) -> 17 | K93: =J93/I93 -> 0 | L93: 18 | M93: 1 | N93: =M93/L93 -> 0.055555556 | O93: 18 | P93: =SUM(P94:P95) -> 0 | Q93: =P93/O93 -> 0 | R93: =SUM(R94:R95) -> 19 | S93: =SUM(S94:S95) -> 0 | T93: =S93/R93 -> 0 | U93: =SUM(U94:U95) -> 0 | V93: =SUM(V94:V95) -> 0 | W93: =V93/U93 -> 0 | X93: =SUM(X94:X95) -> 0 | Y93: =SUM(Y94:Y95) -> 0 | Z93: =Y93/X93 -> 0 | AA93: =SUM(AA94:AA95) -> 0 | AB93: =SUM(AB94:AB95) -> 0 | AC93: =AB93/AA93 -> 0 | AD93: =SUM(AD94:AD95) -> 0 | AE93: =SUM(AE94:AE95) -> 0 | AF93: =AE93/AD93 -> 0 | AG93: =SUM(AG94:AG95) -> 0 | AH93: =SUM(AH94:AH95) -> 0 | AI93: =AH93/AG93 -> 0 | AJ93: =SUM(AJ94:AJ95) -> 0 | AK93: =SUM(AK94:AK95) -> 0 | AL93: =AK93/AJ93 -> 0 | AM93: =SUM(AM94:AM95) -> 0 | AN93: =SUM(AN94:AN95) -> 0 | AO93: =AN93/AM93 -> 0 | AP93: =AVERAGE(F93,I93,L93,O93,R93,U93,X93,AA93,AD93,AG93,AJ93,AM93) -> 7.5 | AQ93: =SUM(G93,J93,M93,P93,S93,V93,Y93,AB93,AE93,AH93,AK93,AN93) -> 1 | AR93: =AQ93/AP93 -> 0.13333333
A94: Охрана | B94: 0.15 | C94: =B94/12*$C$14 -> 0.0625 | D94: =AR94 -> 0 | E94: =IF(D94>0%,C94/D94,100%) -> 1 | F94: 17 | H94: =G94/F94 -> 0 | I94: 16 | K94: =J94/I94 -> 0 | L94: 17 | N94: =M94/L94 -> 0 | O94: 17 | Q94: =P94/O94 -> 0 | R94: 18 | T94: =S94/R94 -> 0 | W94: =V94/U94 -> 0 | Z94: =Y94/X94 -> 0 | AC94: =AB94/AA94 -> 0 | AF94: =AE94/AD94 -> 0 | AI94: =AH94/AG94 -> 0 | AL94: =AK94/AJ94 -> 0 | AO94: =AN94/AM94 -> 0 | AP94: =AVERAGE(F94,I94,L94,O94,R94,U94,X94,AA94,AD94,AG94,AJ94,AM94) -> 17 | AQ94: =SUM(G94,J94,M94,P94,S94,V94,Y94,AB94,AE94,AH94,AK94,AN94) -> 0 | AR94: =AQ94/AP94 -> 0
A95: СБ | B95: 0 | C95: =B95/12*$C$14 -> 0 | D95: =AR95 -> 0 | E95: =IF(D95>0%,C95/D95,100%) -> 1 | F95: 1 | H95: =G95/F95 -> 0 | I95: 1 | K95: =J95/I95 -> 0 | L95: 1 | N95: =M95/L95 -> 0 | O95: 1 | Q95: =P95/O95 -> 0 | R95: 1 | T95: =S95/R95 -> 0 | W95: =V95/U95 -> 0 | Z95: =Y95/X95 -> 0 | AC95: =AB95/AA95 -> 0 | AF95: =AE95/AD95 -> 0 | AI95: =AH95/AG95 -> 0 | AL95: =AK95/AJ95 -> 0 | AO95: =AN95/AM95 -> 0 | AP95: =AVERAGE(F95,I95,L95,O95,R95,U95,X95,AA95,AD95,AG95,AJ95,AM95) -> 1 | AQ95: =SUM(G95,J95,M95,P95,S95,V95,Y95,AB95,AE95,AH95,AK95,AN95) -> 0 | AR95: =AQ95/AP95 -> 0
A96: Итого | F96: =F17+F19+F20+F21+F22+F26+F35+F36+F42+F43+F48+F54+F57+F61+F65+F68+F73+F89+F93 -> 471 | G96: =SUM(G17:G95) -> 14 | H96: =G96/F96 -> 0.029723992 | I96: =I17+I19+I20+I21+I22+I26+I35+I36+I42+I43+I48+I54+I57+I61+I65+I68+I73+I89+I93 -> 465 | J96: =J22+J35+J26+J36+J41+J57+J61+J65+J68+J73+J89+J93 -> 12 | K96: =J96/I96 -> 0.025806452 | L96: =L17+L19+L20+L21+L22+L26+L35+L36+L42+L43+L48+L54+L57+L61+L65+L68+L73+L89+L93 -> 472 | M96: =M22+M35+M26+M36+M41+M57+M61+M65+M68+M73+M80+M85+M89+M93 -> 8 | N96: =M96/L96 -> 0.016949153 | O96: =O17+O19+O20+O21+O22+O26+O35+O36+O42+O43+O48+O54+O57+O61+O65+O68+O73+O89+O93 -> 431 | P96: =P22+P35+P26+P36+P41+P57+P61+P65+P68+P73+P80+P85+P89+P93 -> 7 | Q96: =P96/O96 -> 0.016241299
A98: Текучесть в адаптацию в разрезе ЦФО | B98: План на 2026 | C98: План | D98: Факт | E98: % выполнения | F98: январь | I98: февраль | L98: март | O98: апрель | R98: май | U98: июнь | X98: июль | AA98: август | AD98: сентябрь | AG98: октябрь | AJ98: ноябрь | AM98: декабрь | AP98: ГОД
A99: ЦФО | F99: численность | G99: увольнение | H99: текучесть | I99: численность | J99: увольнение | K99: текучесть | L99: численность | M99: увольнение | N99: текучесть | O99: численность | P99: увольнение | Q99: текучесть | R99: численность | S99: увольнение | T99: текучесть | U99: численность | V99: увольнение | W99: текучесть | X99: численность | Y99: увольнение | Z99: текучесть | AA99: численность | AB99: увольнение | AC99: текучесть | AD99: численность | AE99: увольнение | AF99: текучесть | AG99: численность | AH99: увольнение | AI99: текучесть | AJ99: численность | AK99: увольнение | AL99: текучесть | AM99: численность | AN99: увольнение | AO99: текучесть | AP99: численность | AQ99: увольнение | AR99: текучесть | AS99: план приемы
A100: ЦФО Амурская легенда (1 ур) | B100: 0.15 | C100: =B100/12*$C$14 -> 0.0625 | D100: =C100/12*$C$14 -> 0.026041667 | E100: =IF(D100>0%,C100/D100,100%) -> 2.4 | H100: 0 | I100: 2 | K100: =J100/I100 -> 0 | L100: 1 | N100: =M100/L100 -> 0 | O100: 3 | P100: 1 | Q100: =P100/O100 -> 0.33333333 | T100: =S100/R100 -> 0 | W100: =V100/U100 -> 0 | Z100: =Y100/X100 -> 0 | AC100: =AB100/AA100 -> 0 | AF100: =AE100/AD100 -> 0 | AI100: =AH100/AG100 -> 0 | AL100: =AK100/AJ100 -> 0 | AO100: =AN100/AM100 -> 0 | AP100: =F100+I100+L100+O100+R100+U100+X100+AA100+AD100+AG100+AJ100+AM100 -> 6 | AQ100: =SUM(G100,J100,M100,P100,S100,V100,Y100,AB100,AE100,AH100,AK100,AN100) -> 1 | AR100: =AQ100/AP100 -> 0.16666667 | AS100: 9 | AT100: =AS100*0.15 -> 1.35
A101: ЦФО Директор НПО (2 ур) | B101: 0.18 | C101: =B101/12*$C$14 -> 0.075 | D101: =C101/12*$C$14 -> 0.03125 | E101: =IF(D101>0%,C101/D101,100%) -> 2.4 | F101: 0 | G101: 0 | H101: 0 | K101: 0 | N101: 0 | Q101: =P101/O101 -> 0 | T101: =S101/R101 -> 0 | W101: =V101/U101 -> 0 | Z101: =Y101/X101 -> 0 | AC101: =AB101/AA101 -> 0 | AF101: =AE101/AD101 -> 0 | AI101: =AH101/AG101 -> 0 | AL101: =AK101/AJ101 -> 0 | AO101: =AN101/AM101 -> 0 | AP101: =F101+I101+L101+O101+R101+U101+X101+AA101+AD101+AG101+AJ101+AM101 -> 0 | AQ101: =SUM(G101,J101,M101,P101,S101,V101,Y101,AB101,AE101,AH101,AK101,AN101) -> 0 | AR101: =AQ101/AP101 -> 0 | AS101: 1 | AT101: =AS101*0.15 -> 0.15
A102: СУП | B102: 0.1 | C102: =B102/12*$C$14 -> 0.041666667 | D102: =C102/12*$C$14 -> 0.017361111 | E102: =IF(D102>0%,C102/D102,100%) -> 2.4 | F102: 0 | H102: 0 | K102: 0 | N102: 0 | Q102: =P102/O102 -> 0 | T102: =S102/R102 -> 0 | W102: =V102/U102 -> 0 | Z102: =Y102/X102 -> 0 | AC102: =AB102/AA102 -> 0 | AF102: =AE102/AD102 -> 0 | AI102: =AH102/AG102 -> 0 | AL102: =AK102/AJ102 -> 0 | AO102: =AN102/AM102 -> 0 | AP102: =F102+I102+L102+O102+R102+U102+X102+AA102+AD102+AG102+AJ102+AM102 -> 0 | AQ102: =SUM(G102,J102,M102,P102,S102,V102,Y102,AB102,AE102,AH102,AK102,AN102) -> 0 | AR102: =AQ102/AP102 -> 0 | AS102: #REF! | AT102: =AS102*0.15 -> 0
...

Sheet Обучение
A1: Заполняем вручную, настроен выпадающий список | B1: Заполняем вручную, настроен выпадающий список | F1: Заполняем вручную, настроен выпадающий список | G1: Заполняем вручную, настроен выпадающий список | I1: Заполняем вручную, настроен выпадающий список | J1: Заполняем вручную, настроен выпадающий список
A2: Город | B2: Название компании | C2: ФИО | D2: Подразделение | E2: Должность | F2: ЦФО | G2: Вид обучения | H2: Тема обучения | I2: Направление обучения | J2: Месяц обучения | K2: Дата начала обучения | L2: Дата окончания обучения | M2: Количество часов обучения | N2: Затраты на обучение, руб | O2: Допольнительные затраты | P2: Затраты на командировку | Q2: Обучающая организация | R2: ФИО лектора | S2: Комментарии
R3: Биденко Е.Г.
R4: Биденко Е.Г.
R5: Биденко Е.Г.
R6: Биденко Е.Г.
R7: Биденко Е.Г.
R8: Биденко Е.Г.
R9: Биденко Е.Г.
R10: Биденко Е.Г.
R11: Биденко Е.Г.
R12: Биденко Е.Г.
R13: Биденко Е.Г.
R14: Биденко Е.Г.
... R39: Биденко Е.Г.

Sheet Нетрудоспособность 
A1: Заполняем вручную, настроен выпадающий список | B1: Заполняем вручную, настроен выпадающий список | F1: Заполняем вручную, настроен выпадающий список | G1: Заполняем вручную, настроен выпадающий список | H1: Заполняем вручную, настроен выпадающий список | K1: Заполняется автоматически
A2: Город | B2: Предприятие | C2: ФИО | D2: Подразделение | E2: Должность | F2: Причина нетрудоспособности | G2: Месяц начала | H2: Месяц окончания | I2: Дата начала больничного листа | J2: Дата окончания больничного листа | K2: Количество календарных дней по болезни | L2: Комментарии
K3: =J3-I3+1 -> 1
K4: =J4-I4+1 -> 1
K5: =J5-I5+1 -> 1
K6: =J6-I6+1 -> 1
K7: =J7-I7+1 -> 1
K8: =J8-I8+1 -> 1
K9: =J9-I9+1 -> 1
K10: =J10-I10+1 -> 1
K11: =J11-I11+1 -> 1
K12: =J12-I12+1 -> 1
K13: =J13-I13+1 -> 1
K14: =J14-I14+1 -> 1
... K27: =J27-I27+1 -> 1
K28: 11
K29: 4
K30: 19
K31: 4
K32: 12
K33: 30
K34: 8
K35: 12
K36: 9
K37: 6
K38: 30
K39: 15
... K44: 14
K45: =J45-I45+1 -> 1
K46: =J46-I46+1 -> 1
K47: =J47-I47+1 -> 1
K48: =J48-I48+1 -> 1
K49: =J49-I49+1 -> 1
K50: =J50-I50+1 -> 1
K51: =J51-I51+1 -> 1
K52: =J52-I52+1 -> 1
K53: =J53-I53+1 -> 1
K54: =J54-I54+1 -> 1
K55: =J55-I55+1 -> 1
K56: =J56-I56+1 -> 1
... K343: =J343-I343+1 -> 1

Sheet Пенсия
A1: Компания | B1: Дата рождения | C1: Сотрудник | D1: Подразделение | E1: Должность | F1: Пол | G1: Возраст выхода | H1: Дата выхода на пенсию
A2: ИП Корниенко М.В. | B2: 21.10.1967 | C2: Ершова Ирина Лаврентьевна | D2: Отдел материально-технического обеспечения | E2: Ведущий менеджер | F2: =IF(ISBLANK(C2),"-",IF(ISERROR(FIND("вич",C2,1)),"ж","м")) -> ж | G2: 59 | H2: 46316
A3: МГС | B3: 25061 | C3: Бодрова Элеонора Геннадьевна | D3: Каменск-Шахтинский СЦ | E3: Кассир-приемщик | F3: =IF(ISBLANK(C3),"-",IF(ISERROR(FIND("вич",C3,1)),"ж","м")) -> ж | G3: 60 | H3: 46976
A4: МГС | B4: 25032 | C4: Боровикова Виктория Ричардовна | D4: Ростов (Нагибина) СЦ | E4: Кассир-приемщик | F4: =IF(ISBLANK(C4),"-",IF(ISERROR(FIND("вич",C4,1)),"ж","м")) -> ж | G4: 60 | H4: 46947
A5: МГС | B5: 23099 | C5: Остроухов Андрей Анатольевич | D5: Семикаракорский СЦ | E5: Начальник сервисного центра | F5: =IF(ISBLANK(C5),"-",IF(ISERROR(FIND("вич",C5,1)),"ж","м")) -> м | G5: 65 | H5: 46841
A6: НПО Турбулентность-ДОН | B6: 24230 | C6: Свистун Сергей Николаевич | D6: Служба экономической безопасности | E6: Заместитель директора по экономической безопасности | F6: =IF(ISBLANK(C6),"-",IF(ISERROR(FIND("вич",C6,1)),"ж","м")) -> м | G6: 65 | H6: 47971
A7: НПО Турбулентность-ДОН | B7: 22529 | C7: Гасанов Абдулгамид Османович | D7: Служба безопасности | E7: Контролер поста контроля | F7: =IF(ISBLANK(C7),"-",IF(ISERROR(FIND("вич",C7,1)),"ж","м")) -> м | G7: 63 | H7: 45540
A8: НПО Турбулентность-ДОН | B8: 22646 | C8: Дутов Александр Федорович | D8: Служба безопасности | E8: Контролер поста контроля | F8: =IF(ISBLANK(C8),"-",IF(ISERROR(FIND("вич",C8,1)),"ж","м")) -> м | G8: 63 | H8: 45657
A9: НПО Турбулентность-ДОН | B9: 23031 | C9: Мельников Александр Викторович охранник | D9: Служба безопасности | E9: Контролер поста контроля | F9: =IF(ISBLANK(C9),"-",IF(ISERROR(FIND("вич",C9,1)),"ж","м")) -> м | G9: 65 | H9: 46772
A10: НПО Турбулентность-ДОН | B10: 23337 | C10: Муштат Сергей Николаевич | D10: Малярно-слесарный участок | E10: Слесарь механосборочных работ | F10: =IF(ISBLANK(C10),"-",IF(ISERROR(FIND("вич",C10,1)),"ж","м")) -> м | G10: 65 | H10: 47079
A11: НПО Турбулентность-ДОН | B11: 24287 | C11: Четверня Людмила Ивановна | D11: Заготовительный участок для сборки UFG | E11: Монтажник РЭА | F11: =IF(ISBLANK(C11),"-",IF(ISERROR(FIND("вич",C11,1)),"ж","м")) -> ж | G11: 58 | H11: 45472
A12: НПО Турбулентность-ДОН | B12: 25160 | C12: Ярмизина Евгения Александровна | D12: Отдел дилерских продаж | E12: Менеджер по сопровождению | F12: =IF(ISBLANK(C12),"-",IF(ISERROR(FIND("вич",C12,1)),"ж","м")) -> ж | G12: 60 | H12: 47075
A13: НПО Турбулентность-ДОН | B13: 24630 | C13: Терехова Елена Николаевна | D13: Конструкторское бюро | E13: Технический писатель | F13: =IF(ISBLANK(C13),"-",IF(ISERROR(FIND("вич",C13,1)),"ж","м")) -> ж | G13: 59 | H13: 46180
A14: НПО Турбулентность-ДОН | B14: 22670 | C14: Корниенко Сергей Александрович | D14: Эксплуатационная служба | E14: Энергетик | F14: =IF(ISBLANK(C14),"-",IF(ISERROR(FIND("вич",C14,1)),"ж","м")) -> м | G14: 64 | H14: 46046
... A19: НПО Турбулентность-ДОН | B19: 25089 | C19: Пономарева Марина Николаевна | D19: Транспортная служба | E19: Диспетчер | F19: =IF(ISBLANK(C19),"-",IF(ISERROR(FIND("вич",C19,1)),"ж","м")) -> ж | G19: 60 | H19: 47004

Sheet Декретчицы
C1: меньше, чем 6 месяцев | F1: Заполняем вручную, настроен выпадающий список | G1: Заполняем вручную, настроен выпадающий список
C2: меньше, чем 3 месяца
A3: № п/п | B3: таб № | C3: ФИО | D3: Подразделение | E3: Должность | F3: Город | G3: Предприятие | H3: Отпуск по беременности и родам | J3: Отпуск по уходу за ребенком до достижения им 1,5 лет | L3: Отпуск по уходу за ребенком до достижения им 3-х лет | N3: Комментарии
H4: Начало | I4: Окончание | J4: Начало | K4: Окончание | L4: Начало | M4: Окончание
A5: 1 | B5: 4 | C5: Водяникина Галина Ивановна | D5: Конструкторско-технологический отдел | E5: Специалист по сопровождению 1С:ERP | F5: Ростов-на-Дону | G5: НПО Турбулентность-Дон | L5: 45077 | M5: 46095
A6: 2 | B6: 570 | C6: Окольничникова Алена Павловна | D6: Служба управления персоналом | E6: Ведущий менеджер по персоналу | F6: Ростов-на-Дону | G6: НПО Турбулентность-Дон | J6: 45741 | K6: 46219 | L6: 46220 | M6: 46768
A7: 3 | B7: НП00-000007 | C7: Красильникова Илона Алексеевна | D7: Отдел технической поддержки | E7: Диспетчер | F7: Ростов-на-Дону | G7: НПО Турбулентность-Дон | L7: 45388 | M7: 45935
A8: 4 | B8: 00-0000860 | C8: Милютенко Ольга Николаевна | D8: Коммерческая служба | E8: Коммерческий директор | F8: Ростов-на-Дону | G8: НПО Турбулентность-Дон | L8: 45510 | M8: 46058
A9: 5 | B9: 0000000873 | C9: Черепахина Елена Алексеевна | D9: Управление делами | E9: Офис-менеджер | F9: Ростов-на-Дону | G9: НПО Турбулентность-Дон | L9: 45213 | M9: 46215
A10: 6 | B10: 00150 | C10: Бареева Виктория Олеговна | D10: Конструкторское бюро | E10: Руководитель проектов по сертификации | F10: Ростов-на-Дону | G10: НПО Турбулентность-Дон | L10: 46108 | M10: 46656
A11: 7 | B11: 0005 | C11: Калашникова Анастасия Антоновна | D11: Служба приема и размещения | E11: Портье | F11: Ростов-на-Дону | G11: ООО МИЛАКА | L11: 45145 | M11: 46175
A12: 8 | B12: 00184 | C12: Некрас Кристина Игоревна | D12: Управление делами | E12: Помощник руководителя | F12: Ростов-на-Дону | G12: НПО Турбулентность-Дон | L12: 45875 | M12: 46892
A13: 9 | B13: 00426 | C13: Борисова Валерия Витальевна | D13: Отдел тендерных продаж | E13: Начальник отдела | F13: Ростов-на-Дону | G13: НПО Турбулентность-Дон | H13: 45803 | I13: 45942
A14: 10 | B14: 0000000005 | C14: Глушнева Татьяна Вадимовна | D14: Отдел продаж | E14: Ведущий менеджер | F14: Ростов-на-Дону | G14: ТД Амурская легенда | L14: 45867 | M14: 46888

Sheet Срочники
B1: меньше, чем 6 месяцев | D1: Заполняем вручную, настроен выпадающий список | E1: Заполняем вручную, настроен выпадающий список
B2: меньше, чем 3 месяца
